Workbook

Sheet Cover
A1: Coverage X — Management Forecast V51
A3: Model | B3: CoverageX Management Forecast
A4: Version | B4: V56 — Honest revenue composition (V50 baseline CPS + Mepco IAA recognition)
A5: Build date | B5: 2026-05-20
A6: Forecast horizon | B6: 2024A – 2030E (monthly granularity, 72 forward months)
A7: Anchor period | B7: LTM Sep-25 (CX Quarterly Consolidated Report 2025-9-30)
A8: Engine logic | B8: Vintage cohort survival, per V50 (cancel curve × monthly originations)
A9: Tax basis | B9: LLC pass-through (0%); normalized 21% C-corp in DCF only
A10: Currency / units | B10: USD
A12: WORKBOOK CONTENTS
A13: Cover | B13: This sheet
A14: Live Data | B14: FRED + Yahoo peer snapshot (refresh via refresh_live_data.py)
A15: Assumptions | B15: V50 driver structure + Live Data links — single source of truth
A16: Sources | B16: Citation table
A17: Cancel Curves | B17: Vintage cohort survival rates per product (CX, ASD, Home, Producer)
A18: CX Sales | B18: CX retail VSC engine
A19: ASD Sales | B19: ASD VSC channel engine
A20: Home Sales | B20: CX Home / HWS engine
A21: Producer Sales | B21: Third-party producer commission engine
A22: Mepco Outstanding | B22: IAA roll-forward by vintage (cross-collateralized)
A23: Marketing Budget | B23: Ad spend → leads → contracts by channel
A24: Ops Staffing | B24: Headcount per 1,000 active contracts; loaded comp
... A34: Audit Log | B34: Build history + tie-out checks
A36: COLOR LEGEND
A37: Hardcoded input
A38: Formula
A39: Link to Live Data / cross-sheet
A41: PROVENANCE
A42: V50 source: ~/Downloads/Amwest-CoverageX Data/Coverage X - Management Forecast V50.xlsx
A43: Q3 actuals: ~/Downloads/CoverageX Data/CX Quarterly Consolidated Report-2025-9-30.pdf
A44: Covenant tie-out: ~/Downloads/CoverageX Data/CNB - CoverageX_Covenant Worksheet Dec 31, 2025.xlsx
A45: Mepco terms: COVERAGE X & MEPCO PROG AG v6 (07/12/2025)

Sheet Live Data
A1: Live Data — Coverage X
A2: Auto-refreshed by GitHub Actions at 2026-10-15T15:38:46Z. Re-download from the published URL to get the latest.
A3: Last refreshed: 2026-10-15T15:38:46Z
A4: Metric | B4: Value | C4: Unit | D4: Source | E4: Series | F4: URL | G4: As-of | H4: Refreshed | I4: Prior | J4: Pct Chg | K4: Drift
A5: 10Y Treasury (Rf) | B5: 5.21 | C5: % | D5: FRED | E5: DGS10 | F5: https://fred.stlouisfed.org/series/DGS10 | G5: 2026-10-13 | H5: 2026-10-15T15:38:46Z | I5: 4.67 | J5: 0
A6: Fed Funds Upper | B6: 4 | C6: % | D6: FRED | E6: DFEDTARU | F6: https://fred.stlouisfed.org/series/DFEDTARU | G6: 2026-10-15 | H6: 2026-10-15T15:38:46Z | I6: 3.75 | J6: 0
A7: 10Y-2Y Spread | B7: 0.37 | C7: % | D7: FRED | E7: T10Y2Y | F7: https://fred.stlouisfed.org/series/T10Y2Y | G7: 2026-10-14 | H7: 2026-10-15T15:38:46Z | I7: 0.53 | J7: 0
A8: Auto sales SAAR | B8: 16.378 | C8: millions | D8: FRED | E8: TOTALSA | F8: https://fred.stlouisfed.org/series/TOTALSA | G8: 2026-09-01 | H8: 2026-10-15T15:38:46Z | I8: 16.696 | J8: 0
A9: CPI used cars/trucks | B9: 184.395 | C9: index | D9: FRED | E9: CUUR0000SETA02 | F9: https://fred.stlouisfed.org/series/CUUR0000SETA02 | G9: 2026-09-01 | H9: 2026-10-15T15:38:46Z | I9: 177.936 | J9: 0
A10: U Mich Consumer Sentiment | B10: 51.7 | C10: index | D10: FRED | E10: UMCSENT | F10: https://fred.stlouisfed.org/series/UMCSENT | G10: 2026-08-01 | H10: 2026-10-15T15:38:46Z | I10: 53.3 | J10: 0
A11: Unemployment rate | B11: 4.2 | C11: % | D11: FRED | E11: UNRATE | F11: https://fred.stlouisfed.org/series/UNRATE | G11: 2026-09-01 | H11: 2026-10-15T15:38:46Z | I11: 4.3 | J11: 0
A12: 30Y Mortgage Rate | B12: 7.4 | C12: % | D12: FRED | E12: MORTGAGE30US | F12: https://fred.stlouisfed.org/series/MORTGAGE30US | G12: 2026-10-08 | H12: 2026-10-15T15:38:46Z | I12: 6.51 | J12: 0
A13: Vehicle Miles Traveled (idx) | B13: 294124 | C13: index | D13: FRED | E13: TRFVOLUSM227NFWA | F13: https://fred.stlouisfed.org/series/TRFVOLUSM227NFWA | G13: 2026-08-01 | H13: 2026-10-15T15:38:46Z | I13: 283207 | J13: 0
A14: Light truck inventory (idx) | B14: 187.097 | C14: thousands | D14: FRED | E14: AUINSA | F14: https://fred.stlouisfed.org/series/AUINSA | G14: 2026-08-01 | H14: 2026-10-15T15:38:46Z | I14: 198.116 | J14: 0
A15: AutoLoanRate_48mo | B15: 7.47 | C15: % | D15: FRED | E15: TERMCBAUTO48NS | F15: https://fred.stlouisfed.org/series/TERMCBAUTO48NS | G15: 2026-08-01 | H15: 2026-10-15T15:38:46Z | I15: 7.36 | J15: 0
A16: PEERS (public comps — caveat: no exact match for private specialty F&I)
A17: Ticker | B17: Name | C17: Sector | D17: Mkt Cap ($M) | E17: EV ($M) | F17: P/E (TTM) | G17: P/E (Fwd) | H17: P/B | I17: EV/EBITDA | J17: EV/Revenue | K17: Beta | L17: Live Price
A18: AIZ | B18: Assurant, Inc. | C18: Financial Services | D18: 12707.483 | E18: 12993.483 | F18: 13.138832 | G18: 11.407976 | H18: 2.1704397 | I18: 254.85001 | J18: 0.987 | K18: 0.556 | L18: 280.565
A19: ALLY | B19: Ally Financial Inc. | C19: Financial Services | D19: 12521.467 | E19: 26923.467 | F19: 9.915049 | G19: 6.297889 | H19: 0.9452517 | I19: 42.860001 | J19: 3.502 | K19: 1.109 | L19: 37.59
A20: KMX | B20: CarMax Inc | C20: Consumer Cyclical | D20: 5143.8377 | E20: 23757.896 | F20: 21.589287 | G20: 12.983712 | H20: 0.8733446 | I20: 38.525002 | J20: 0.856 | K20: 1.184 | L20: 51.919998
A21: CACC | B21: Credit Acceptance Corporation | C21: Financial Services | D21: 5731.3869 | E21: 12114.287 | F21: 13.660683 | G21: 10.018833 | H21: 3.7719598 | I21: 547.39001 | J21: 9.496 | K21: 1.358 | L21: 545.67999
A22: COF | B22: Capital One Financial Corporati | C22: Financial Services | D22: 113275.96 | E22: 95171.953 | F22: 55.83742 | G22: 7.539235 | H22: 1.049134 | I22: 185.88 | J22: 2.621 | K22: 1.05 | L22: 196.34
A24: Median | D24: =IFERROR(MEDIAN(D18:D22),"") | E24: =IFERROR(MEDIAN(E18:E22),"") | F24: =IFERROR(MEDIAN(F18:F22),"") | G24: =IFERROR(MEDIAN(G18:G22),"") | H24: =IFERROR(MEDIAN(H18:H22),"") | I24: =IFERROR(MEDIAN(I18:I22),"") | J24: =IFERROR(MEDIAN(J18:J22),"") | K24: =IFERROR(MEDIAN(K18:K22),"")
A25: Mean | D25: =IFERROR(AVERAGE(D18:D22),"") | E25: =IFERROR(AVERAGE(E18:E22),"") | F25: =IFERROR(AVERAGE(F18:F22),"") | G25: =IFERROR(AVERAGE(G18:G22),"") | H25: =IFERROR(AVERAGE(H18:H22),"") | I25: =IFERROR(AVERAGE(I18:I22),"") | J25: =IFERROR(AVERAGE(J18:J22),"") | K25: =IFERROR(AVERAGE(K18:K22),"")

Sheet Assumptions
A1: Assumptions — V56 (final; IAA gross/net dual-documentation)
A2: Hardcoded blue. Live Data links green. Salt-and-pepper layout matches V50 for diff-ability.
A4: CORE OPERATING ASSUMPTIONS (V50 structure preserved)
A5: Corporate Tax Rate (Fed & State) | B5: 0
A6: Investor Distributions — threshold ($) | B6: 1000000000
A7: Investor Distributions — start month | B7: 12
A8: Accounts Receivable (days) | B8: 30
A9: Annual Increase — Contracts | B9: 0.03 | D9: Price escalator
A10: Annual Increase — All Else | B10: 0.03
A11: Annual Increase — Salaries | B11: 0.03
A12: Payroll Taxes | B12: 0.15
A13: Benefits | B13: 0.2
A16: CONTRACT TERMS — Coverage X
A17: Avg Monthly Customer Payment ($) | B17: 125 | D17: Calibrated to FY 2025 subscription revenue actual ($118.7M)
A18: Advanced Customer Payments (months) | B18: 8
A19: Mepco IAA per contract — derived ($) | B19: =B17*B18
A20: Insurance Premium — upfront ($) | B20: 12 | D20: Sourced from FY 2025 actual $1.2M / ~100K new contracts
A21: Insurance Premium — after cancel ($) | B21: 50
A22: PB Reserve (Mepco) per New Contract ($) | B22: 0
A23: Cancel Curve Improvement | B23: 0.2 | D23: PRIMARY STICK-RATE LEVER — higher = contracts last longer
A24: Claims Reserve Account ($/contract) | B24: 150
A25: Actual Claims Expense Start (month #) | B25: 12
A26: Charge Back rate | B26: 0.025
A27: Merchant Fees | B27: 0.035
A28: Merchant Reserve | B28: 0.035
A29: Contract Fulfillment — Postage ($) | B29: 1.83
A30: Contract Fulfillment — Printing ($) | B30: 1
A32: Initiation fee per new contract ($) | B32: 64 | D32: Sourced from FY 2025 Q4 PDF: $5.16M init fee / ~100K new contracts
A33: MEPCO PROGRAMME AGREEMENT v6 (07/12/2025)
A34: Mepco IAA per contract — gross programme value (revenue recognition basis, ASC 606) | B34: 1450 | D34: Per Programme Agreement; differs from V50 derived
A35: Mepco PB premium (% IAA) | B35: 0.06 | D35: 6% per Programme Agreement
A36: PB Period (months) | B36: 24
A37: Earliest claim filing (month) | B37: 26
A38: Producer commission per contract ($) | B38: 500
A39: Funding cadence | B39: Weekly (Thursday)
A40: Mepco reserve release at CNB loan close | B40: 10000000
A42: CHANNEL SPECIFICS — ASD & Producer
A43: ASD Increase Sales per Month | B43: 100
A44: Producer Increase Sales per Month | B44: 150
A45: Producer Fulfillment — Postage ($) | B45: 1.77
A46: Producer Fulfillment — Printing ($) | B46: 1
A48: DEBT — CNB Line of Credit
A49: Beginning Balance | B49: 15000000
A50: Bank Underwriting Fee (% of facility) | B50: 0.01
A51: Net Interest Rate | B51: 0.08
A52: Term (months) | B52: 0
A53: Loan Starts (month #) | B53: 7
A54: Monthly Interest (calc) | B54: =B49*B51/12
A56: MACRO + VALUATION (linked to Live Data)
A57: Risk-free rate (10Y UST) | B57: ='Live Data'!B5
A58: Fed Funds Upper | B58: ='Live Data'!B6
A59: Auto Sales SAAR (M) | B59: ='Live Data'!B8
A60: Used Car CPI (idx) | B60: ='Live Data'!B9
A61: Consumer Sentiment | B61: ='Live Data'!B10
A62: Equity risk premium (ERP) | B62: 0.055
A63: Beta (peer-derived) | B63: 1.2
A64: Size / illiquidity premium | B64: 0.03
A65: Cost of equity (Ke) | B65: =B57+B63*B62+B64
A66: Pre-tax cost of debt (Kd) | B66: 0.085
A67: Target debt / total cap | B67: 0.2
A68: C-corp normalized tax (DCF) | B68: 0.21
A69: WACC | B69: =B65*(1-B67)+B66*(1-B68)*B67
A70: Terminal growth rate | B70: 0.025
A71: Exit multiple (EV/EBITDA) | B71: 8
A73: V54 REVENUE RECOGNITION (added in V54)
A74: Avg contract term for IAA amortization (months) | B74: 12 | D74: Mepco amortization policy window; separate from cancel curve avg life (13.77mo)
A75: Mepco IAA per contract ($, linked to programme) | B75: =B34 | D75: Programme Agreement v6 value
A76: IAA recognition revenue/mo/active ($) | B76: =B75/B74 | D76: IAA amortized over avg term
A77: LTV per contract ($) — customer payments only | B77: =B17*B74 | D77: CPS × avg term = $125 × 12 = $1,500
A84: ── Net cash basis references (documentation only — not used in revenue formula) ──
A85: Net IAA cash to CX per contract — dad-reported / V50 B19 | B85: 1000
A86: Net IAA cash to CX — derived: gross less producer comm, PB premium, insurance | B86: =B34 - B38 - (B34*B35) - B20
A87: → flows: $1,450 gross − $500 producer comm − $87 PB premium − $12 insurance = $851 derived
A89: Revenue recognition: V55 uses GROSS programme value ($1,450) amortized over 12 months per ASC 606.
A90: Producer commission ($500), PB premium, and insurance flow through Cost of Service — see Producer Sales R18-21.

Sheet Sources
A1: Sources & Data Lineage
A2: One row per source. Last Refresh updated by refresh_live_data.py.
A4: Source | B4: Type | C4: Identifier | D4: URL / Path | E4: Used in | F4: Last Refresh
A5: V50 — Coverage X Management Forecast | B5: Internal | C5: V50.xlsx | D5: ~/Downloads/Amwest-CoverageX Data/ | E5: Cancel curve, monthly contracts, unit econ | F5: static (V50)
A6: FRED — 10Y Treasury | B6: Macro | C6: DGS10 | D6: https://fred.stlouisfed.org/series/DGS10 | E6: Live Data; Assumptions Rf; WACC | F6: 2026-05-20 03:20 UTC
A7: FRED — Fed Funds Upper | B7: Macro | C7: DFEDTARU | D7: https://fred.stlouisfed.org/series/DFEDTARU | E7: Live Data | F7: 2026-05-20 03:20 UTC
A8: FRED — 10Y-2Y Spread | B8: Macro | C8: T10Y2Y | D8: https://fred.stlouisfed.org/series/T10Y2Y | E8: Live Data; recession context | F8: 2026-05-20 03:20 UTC
A9: FRED — Auto SAAR | B9: Macro | C9: TOTALSA | D9: https://fred.stlouisfed.org/series/TOTALSA | E9: Live Data; auto market context | F9: 2026-05-20 03:20 UTC
A10: FRED — Used Vehicle CPI | B10: Macro | C10: CUUR0000SETA02 | D10: https://fred.stlouisfed.org/series/CUUR0000SETA02 | E10: Live Data; VSC value proxy | F10: 2026-05-20 03:20 UTC
A11: FRED — U Mich Sentiment | B11: Macro | C11: UMCSENT | D11: https://fred.stlouisfed.org/series/UMCSENT | E11: Live Data; consumer demand | F11: 2026-05-20 03:20 UTC
A12: FRED — Unemployment Rate | B12: Macro | C12: UNRATE | D12: https://fred.stlouisfed.org/series/UNRATE | E12: Live Data; cancel curve sensitivity | F12: 2026-05-20 03:20 UTC
A13: FRED — 30Y Mortgage Rate | B13: Macro | C13: MORTGAGE30US | D13: https://fred.stlouisfed.org/series/MORTGAGE30US | E13: Live Data; cross-product context | F13: 2026-05-20 03:20 UTC
A14: FRED — Vehicle Miles Traveled | B14: Macro | C14: TRFVOLUSM227NFWA | D14: https://fred.stlouisfed.org/series/TRFVOLUSM227NFWA | E14: Live Data; VSC usage proxy | F14: 2026-05-20 03:20 UTC
A15: Yahoo Finance — AIZ | B15: Peer | C15: AIZ | D15: https://finance.yahoo.com/quote/AIZ | E15: Live Data; Trading Comps | F15: 2026-05-20 03:20 UTC
... A24: CNB Contract Insurance Endorsements (Add 2/3/4) | B24: Legal | C24: 2023-2024 | D24: ~/Downloads/CoverageX Data/ | E24: Insurance premium structure context | F24: static

Sheet Cancel Curves
A1: Cancel Curves — Vintage Cohort Survival by Product
A2: Source: V50 cancel curve + improvement factor from Assumptions!B23. Same curve applied to all 4 products in V50.
A4: A. Cancel rates by month-since-origination (raw — pre-improvement)
A5: Month # | B5: 1 | C5: 2 | D5: 3 | E5: 4 | F5: 5 | G5: 6 | H5: 7 | I5: 8 | J5: 9 | K5: 10 | L5: 11 | M5: 12 | N5: 13 | O5: 14 | P5: 15 | Q5: 16 | R5: 17 | S5: 18 | T5: 19 | U5: 20 | V5: 21 | W5: 22 | X5: 23 | Y5: 24 | Z5: 25 | AA5: 26 | AB5: 27 | AC5: 28 | AD5: 29 | AE5: 30 | AF5: 31 | AG5: 32 | AH5: 33 | AI5: 34 | AJ5: 35 | AK5: 36 | AL5: 37 | AM5: 38 | AN5: 39 | AO5: 40 | AP5: 41 | AQ5: 42 | AR5: 43 | AS5: 44 | AT5: 45 | AU5: 46 | AV5: 47 | AW5: 48 | AX5: 49 | AY5: 50 | AZ5: 51 | BA5: 52 | BB5: 53 | BC5: 54 | BD5: 55 | BE5: 56 | BF5: 57 | BG5: 58 | BH5: 59 | BI5: 60 | BJ5: 61 | BK5: 62 | BL5: 63 | BM5: 64 | BN5: 65 | BO5: 66 | BP5: 67 | BQ5: 68 | BR5: 69 | BS5: 70 | BT5: 71
A6: Cancel rate (raw) | B6: 0.28 | C6: 0.13 | D6: 0.1 | E6: 0.08 | F6: 0.07 | G6: 0.06 | H6: 0.06 | I6: 0.05 | J6: 0.05 | K6: 0.05 | L6: 0.04 | M6: 0.04 | N6: 0.04 | O6: 0.03 | P6: 0.03 | Q6: 0.03 | R6: 0.02 | S6: 0.02 | T6: 0.02 | U6: 0.02 | V6: 0.02 | W6: 0.02 | X6: 0.02 | Y6: 0.01 | Z6: 0.01 | AA6: 0.01 | AB6: 0.01 | AC6: 0.01 | AD6: 0.01 | AE6: 1 | AF6: 1 | AG6: 1 | AH6: 1 | AI6: 1 | AJ6: 1 | AK6: 1 | AL6: 1 | AM6: 1 | AN6: 1 | AO6: 1 | AP6: 1 | AQ6: 1 | AR6: 1 | AS6: 1 | AT6: 1 | AU6: 1 | AV6: 1 | AW6: 1 | AX6: 1 | AY6: 1 | AZ6: 1 | BA6: 1 | BB6: 1 | BC6: 1 | BD6: 1 | BE6: 1 | BF6: 1 | BG6: 1 | BH6: 1 | BI6: 1 | BJ6: 1 | BK6: 1 | BL6: 1 | BM6: 1 | BN6: 1 | BO6: 1 | BP6: 1 | BQ6: 1 | BR6: 1 | BS6: 1 | BT6: 1
A8: B. Adjusted cancel rate (raw × (1 − improvement factor))
A9: Adjusted cancel | B9: =B6*(1-Assumptions!$B$23) | C9: =C6*(1-Assumptions!$B$23) | D9: =D6*(1-Assumptions!$B$23) | E9: =E6*(1-Assumptions!$B$23) | F9: =F6*(1-Assumptions!$B$23) | G9: =G6*(1-Assumptions!$B$23) | H9: =H6*(1-Assumptions!$B$23) | I9: =I6*(1-Assumptions!$B$23) | ... BT9: =BT6*(1-Assumptions!$B$23)
A11: C. Survival rate (Π_{k=0..n} (1 - adjusted_k))
A12: Survival | B12: 1 | C12: =B12*(1-B9) | D12: =C12*(1-C9) | E12: =D12*(1-D9) | F12: =E12*(1-E9) | G12: =F12*(1-F9) | H12: =G12*(1-G9) | I12: =H12*(1-H9) | J12: =I12*(1-I9) | ... BT12: =BS12*(1-BS9)
A14: Avg months/contract | B14: =SUM(B12:BT12)
A16: Curve length: 71 months. Month 30+ = full cancel per V50.
A17: Survival vector is referenced by all 4 product engines (CX/ASD/Home/Producer).
A18: V50 applied one shared curve to all products. V51 preserves this behavior.

Sheet CX Sales
A1: CX Retail VSC — Engine (Vintage Cohort Survival)
A2: Monthly originations × shared cancel curve. CPS (customer payment per service) = $100.0/mo.
C3: 2024A | D3: 2025 | E3: 2025 | F3: 2025 | G3: 2025 | H3: 2025 | I3: 2025 | J3: 2025 | K3: 2025 | L3: 2025 | M3: 2025 | N3: 2025 | O3: 2025 | P3: 2026 | Q3: 2026 | R3: 2026 | S3: 2026 | T3: 2026 | U3: 2026 | V3: 2026 | W3: 2026 | X3: 2026 | Y3: 2026 | Z3: 2026 | AA3: 2026 | AB3: 2027 | AC3: 2027 | AD3: 2027 | AE3: 2027 | AF3: 2027 | AG3: 2027 | AH3: 2027 | AI3: 2027 | AJ3: 2027 | AK3: 2027 | AL3: 2027 | AM3: 2027 | AN3: 2028 | AO3: 2028 | AP3: 2028 | AQ3: 2028 | AR3: 2028 | AS3: 2028 | AT3: 2028 | AU3: 2028 | AV3: 2028 | AW3: 2028 | AX3: 2028 | AY3: 2028 | AZ3: 2029 | BA3: 2029 | BB3: 2029 | BC3: 2029 | BD3: 2029 | BE3: 2029 | BF3: 2029 | BG3: 2029 | BH3: 2029 | BI3: 2029 | BJ3: 2029 | BK3: 2029 | BL3: 2030 | BM3: 2030 | BN3: 2030 | BO3: 2030 | BP3: 2030 | BQ3: 2030 | BR3: 2030 | BS3: 2030 | BT3: 2030 | BU3: 2030 | BV3: 2030 | BW3: 2030
C4: Anchor | D4: 2025-01 | E4: 2025-02 | F4: 2025-03 | G4: 2025-04 | H4: 2025-05 | I4: 2025-06 | J4: 2025-07 | K4: 2025-08 | L4: 2025-09 | M4: 2025-10 | N4: 2025-11 | O4: 2025-12 | P4: 2026-01 | Q4: 2026-02 | R4: 2026-03 | S4: 2026-04 | T4: 2026-05 | U4: 2026-06 | V4: 2026-07 | W4: 2026-08 | X4: 2026-09 | Y4: 2026-10 | Z4: 2026-11 | AA4: 2026-12 | AB4: 2027-01 | AC4: 2027-02 | AD4: 2027-03 | AE4: 2027-04 | AF4: 2027-05 | AG4: 2027-06 | AH4: 2027-07 | AI4: 2027-08 | AJ4: 2027-09 | AK4: 2027-10 | AL4: 2027-11 | AM4: 2027-12 | AN4: 2028-01 | AO4: 2028-02 | AP4: 2028-03 | AQ4: 2028-04 | AR4: 2028-05 | AS4: 2028-06 | AT4: 2028-07 | AU4: 2028-08 | AV4: 2028-09 | AW4: 2028-10 | AX4: 2028-11 | AY4: 2028-12 | AZ4: 2029-01 | BA4: 2029-02 | BB4: 2029-03 | BC4: 2029-04 | BD4: 2029-05 | BE4: 2029-06 | BF4: 2029-07 | BG4: 2029-08 | BH4: 2029-09 | BI4: 2029-10 | BJ4: 2029-11 | BK4: 2029-12 | BL4: 2030-01 | BM4: 2030-02 | BN4: 2030-03 | BO4: 2030-04 | BP4: 2030-05 | BQ4: 2030-06 | BR4: 2030-07 | BS4: 2030-08 | BT4: 2030-09 | BU4: 2030-10 | BV4: 2030-11 | BW4: 2030-12
A5: New contracts originated | D5: 959 | E5: 806 | F5: 1103 | G5: 1857 | H5: 2500 | I5: 2500 | J5: 2500 | K5: 2500 | L5: 2400 | M5: 2500 | N5: 2750 | O5: 3000 | P5: 3500 | Q5: 4000 | R5: 4500 | S5: 5000 | T5: 5500 | U5: 6000 | V5: 6500 | W5: 7000 | X5: 7500 | Y5: 8000 | Z5: 8500 | AA5: 9000 | AB5: 9250 | AC5: 9500 | AD5: 9750 | AE5: 10000 | AF5: 10250 | AG5: 10500 | AH5: 10750 | AI5: 11000 | AJ5: 11250 | AK5: 11500 | AL5: 11750 | AM5: 12000 | AN5: 12250 | AO5: 12500 | AP5: 12750 | AQ5: 13000 | AR5: 13250 | AS5: 13500 | AT5: 13750 | AU5: 14000 | AV5: 14250 | AW5: 14500 | AX5: 14750 | AY5: 15000 | AZ5: 15250 | BA5: 15500 | BB5: 15750 | BC5: 16000 | BD5: 16250 | BE5: 16500 | BF5: 16750 | BG5: 17000 | BH5: 17250 | BI5: 17500 | BJ5: 17750 | BK5: 18000 | BL5: 18250 | BM5: 18500 | BN5: 18750 | BO5: 19000 | BP5: 19250 | BQ5: 19500 | BR5: 19750 | BS5: 20000 | BT5: 20250 | BU5: 20500 | BV5: 20750 | BW5: 21000
A6: Active contracts (vintage-weighted) | C6: =C7 | D6: =$D5*'Cancel Curves'!$B$12 + 2223.0342 | E6: =$D5*'Cancel Curves'!$C$12 + $E5*'Cancel Curves'!$B$12 + 2077.6668 | F6: =$D5*'Cancel Curves'!$D$12 + $E5*'Cancel Curves'!$C$12 + $F5*'Cancel Curves'!$B$12 + 1964.4647 | G6: =$D5*'Cancel Curves'!$E$12 + $E5*'Cancel Curves'!$D$12 + $F5*'Cancel Curves'!$C$12 + $G5*'Cancel Curves'!$B$12 + 1871.0865 | H6: =$D5*'Cancel Curves'!$F$12 + $E5*'Cancel Curves'!$E$12 + $F5*'Cancel Curves'!$D$12 + $G5*'Cancel Curves'!$C$12 + $H5*'Cancel Curves'!$B$12 + 1790.6773 | I6: =$D5*'Cancel Curves'!$G$12 + $E5*'Cancel Curves'!$F$12 + $F5*'Cancel Curves'!$E$12 + $G5*'Cancel Curves'!$D$12 + $H5*'Cancel Curves'!$C$12 + $I5*'Cancel Curves'!$B$12 + 1720.6687 | J6: =$D5*'Cancel Curves'!$H$12 + $E5*'Cancel Curves'!$G$12 + $F5*'Cancel Curves'!$F$12 + $G5*'Cancel Curves'!$E$12 + $H5*'Cancel Curves'!$D$12 + $I5*'Cancel Curves'!$C$12 + $J5*'Cancel Curves'!$B$12 + 1657.9772 | K6: =$D5*'Cancel Curves'!$I$12 + $E5*'Cancel Curves'!$H$12 + $F5*'Cancel Curves'!$G$12 + $G5*'Cancel Curves'!$F$12 + $H5*'Cancel Curves'!$E$12 + $I5*'Cancel Curves'!$D$12 + $J5*'Cancel Curves'!$C$12 + $K5*'Cancel Curves'!$B$12 + 1603.1434 | L6: =$D5*'Cancel Curves'!$J$12 + $E5*'Cancel Curves'!$I$12 + $F5*'Cancel Curves'!$H$12 + $G5*'Cancel Curves'!$G$12 + $H5*'Cancel Curves'!$F$12 + $I5*'Cancel Curves'!$E$12 + $J5*'Cancel Curves'!$D$12 + $K5*'Cancel Curves'!$C$12 + $L5*'Cancel Curves'!$B$12 + 1555.0072 | M6: =$D5*'Cancel Curves'!$K$12 + $E5*'Cancel Curves'!$J$12 + $F5*'Cancel Curves'!$I$12 + $G5*'Cancel Curves'!$H$12 + $H5*'Cancel Curves'!$G$12 + $I5*'Cancel Curves'!$F$12 + $J5*'Cancel Curves'!$E$12 + $K5*'Cancel Curves'!$D$12 + $L5*'Cancel Curves'!$C$12 + $M5*'Cancel Curves'!$B$12 + 1513.8620 | N6: =$D5*'Cancel Curves'!$L$12 + $E5*'Cancel Curves'!$K$12 + $F5*'Cancel Curves'!$J$12 + $G5*'Cancel Curves'!$I$12 + $H5*'Cancel Curves'!$H$12 + $I5*'Cancel Curves'!$G$12 + $J5*'Cancel Curves'!$F$12 + $K5*'Cancel Curves'!$E$12 + $L5*'Cancel Curves'!$D$12 + $M5*'Cancel Curves'!$C$12 + $N5*'Cancel Curves'!$B$12 + 1479.8521 | O6: =$D5*'Cancel Curves'!$M$12 + $E5*'Cancel Curves'!$L$12 + $F5*'Cancel Curves'!$K$12 + $G5*'Cancel Curves'!$J$12 + $H5*'Cancel Curves'!$I$12 + $I5*'Cancel Curves'!$H$12 + $J5*'Cancel Curves'!$G$12 + $K5*'Cancel Curves'!$F$12 + $L5*'Cancel Curves'!$E$12 + $M5*'Cancel Curves'!$D$12 + $N5*'Cancel Curves'!$C$12 + $O5*'Cancel Curves'!$B$12 + 1451.3929 | P6: =$D5*'Cancel Curves'!$N$12 + $E5*'Cancel Curves'!$M$12 + $F5*'Cancel Curves'!$L$12 + $G5*'Cancel Curves'!$K$12 + $H5*'Cancel Curves'!$J$12 + $I5*'Cancel Curves'!$I$12 + $J5*'Cancel Curves'!$H$12 + $K5*'Cancel Curves'!$G$12 + $L5*'Cancel Curves'!$F$12 + $M5*'Cancel Curves'!$E$12 + $N5*'Cancel Curves'!$D$12 + $O5*'Cancel Curves'!$C$12 + $P5*'Cancel Curves'!$B$12 + 1420.2274 | Q6: =$D5*'Cancel Curves'!$O$12 + $E5*'Cancel Curves'!$N$12 + $F5*'Cancel Curves'!$M$12 + $G5*'Cancel Curves'!$L$12 + $H5*'Cancel Curves'!$K$12 + $I5*'Cancel Curves'!$J$12 + $J5*'Cancel Curves'!$I$12 + $K5*'Cancel Curves'!$H$12 + $L5*'Cancel Curves'!$G$12 + $M5*'Cancel Curves'!$F$12 + $N5*'Cancel Curves'!$E$12 + $O5*'Cancel Curves'!$D$12 + $P5*'Cancel Curves'!$C$12 + $Q5*'Cancel Curves'!$B$12 + 1380.2485 | R6: =$D5*'Cancel Curves'!$P$12 + $E5*'Cancel Curves'!$O$12 + $F5*'Cancel Curves'!$N$12 + $G5*'Cancel Curves'!$M$12 + $H5*'Cancel Curves'!$L$12 + $I5*'Cancel Curves'!$K$12 + $J5*'Cancel Curves'!$J$12 + $K5*'Cancel Curves'!$I$12 + $L5*'Cancel Curves'!$H$12 + $M5*'Cancel Curves'!$G$12 + $N5*'Cancel Curves'!$F$12 + $O5*'Cancel Curves'!$E$12 + $P5*'Cancel Curves'!$D$12 + $Q5*'Cancel Curves'!$C$12 + $R5*'Cancel Curves'!$B$12 + 1302.7632 | S6: =$D5*'Cancel Curves'!$Q$12 + $E5*'Cancel Curves'!$P$12 + $F5*'Cancel Curves'!$O$12 + $G5*'Cancel Curves'!$N$12 + $H5*'Cancel Curves'!$M$12 + $I5*'Cancel Curves'!$L$12 + $J5*'Cancel Curves'!$K$12 + $K5*'Cancel Curves'!$J$12 + $L5*'Cancel Curves'!$I$12 + $M5*'Cancel Curves'!$H$12 + $N5*'Cancel Curves'!$G$12 + $O5*'Cancel Curves'!$F$12 + $P5*'Cancel Curves'!$E$12 + $Q5*'Cancel Curves'!$D$12 + $R5*'Cancel Curves'!$C$12 + $S5*'Cancel Curves'!$B$12 + 1194.8703 | T6: =$D5*'Cancel Curves'!$R$12 + $E5*'Cancel Curves'!$Q$12 + $F5*'Cancel Curves'!$P$12 + $G5*'Cancel Curves'!$O$12 + $H5*'Cancel Curves'!$N$12 + $I5*'Cancel Curves'!$M$12 + $J5*'Cancel Curves'!$L$12 + $K5*'Cancel Curves'!$K$12 + $L5*'Cancel Curves'!$J$12 + $M5*'Cancel Curves'!$I$12 + $N5*'Cancel Curves'!$H$12 + $O5*'Cancel Curves'!$G$12 + $P5*'Cancel Curves'!$F$12 + $Q5*'Cancel Curves'!$E$12 + $R5*'Cancel Curves'!$D$12 + $S5*'Cancel Curves'!$C$12 + $T5*'Cancel Curves'!$B$12 + 1083.5441 | U6: =$D5*'Cancel Curves'!$S$12 + $E5*'Cancel Curves'!$R$12 + $F5*'Cancel Curves'!$Q$12 + $G5*'Cancel Curves'!$P$12 + $H5*'Cancel Curves'!$O$12 + $I5*'Cancel Curves'!$N$12 + $J5*'Cancel Curves'!$M$12 + $K5*'Cancel Curves'!$L$12 + $L5*'Cancel Curves'!$K$12 + $M5*'Cancel Curves'!$J$12 + $N5*'Cancel Curves'!$I$12 + $O5*'Cancel Curves'!$H$12 + $P5*'Cancel Curves'!$G$12 + $Q5*'Cancel Curves'!$F$12 + $R5*'Cancel Curves'!$E$12 + $S5*'Cancel Curves'!$D$12 + $T5*'Cancel Curves'!$C$12 + $U5*'Cancel Curves'!$B$12 + 968.4575 | V6: =$D5*'Cancel Curves'!$T$12 + $E5*'Cancel Curves'!$S$12 + $F5*'Cancel Curves'!$R$12 + $G5*'Cancel Curves'!$Q$12 + $H5*'Cancel Curves'!$P$12 + $I5*'Cancel Curves'!$O$12 + $J5*'Cancel Curves'!$N$12 + $K5*'Cancel Curves'!$M$12 + $L5*'Cancel Curves'!$L$12 + $M5*'Cancel Curves'!$K$12 + $N5*'Cancel Curves'!$J$12 + $O5*'Cancel Curves'!$I$12 + $P5*'Cancel Curves'!$H$12 + $Q5*'Cancel Curves'!$G$12 + $R5*'Cancel Curves'!$F$12 + $S5*'Cancel Curves'!$E$12 + $T5*'Cancel Curves'!$D$12 + $U5*'Cancel Curves'!$C$12 + $V5*'Cancel Curves'!$B$12 + 857.1319 | W6: =$D5*'Cancel Curves'!$U$12 + $E5*'Cancel Curves'!$T$12 + $F5*'Cancel Curves'!$S$12 + $G5*'Cancel Curves'!$R$12 + $H5*'Cancel Curves'!$Q$12 + $I5*'Cancel Curves'!$P$12 + $J5*'Cancel Curves'!$O$12 + $K5*'Cancel Curves'!$N$12 + $L5*'Cancel Curves'!$M$12 + $M5*'Cancel Curves'!$L$12 + $N5*'Cancel Curves'!$K$12 + $O5*'Cancel Curves'!$J$12 + $P5*'Cancel Curves'!$I$12 + $Q5*'Cancel Curves'!$H$12 + $R5*'Cancel Curves'!$G$12 + $S5*'Cancel Curves'!$F$12 + $T5*'Cancel Curves'!$E$12 + $U5*'Cancel Curves'!$D$12 + $V5*'Cancel Curves'!$C$12 + $W5*'Cancel Curves'!$B$12 + 757.4654 | X6: =$D5*'Cancel Curves'!$V$12 + $E5*'Cancel Curves'!$U$12 + $F5*'Cancel Curves'!$T$12 + $G5*'Cancel Curves'!$S$12 + $H5*'Cancel Curves'!$R$12 + $I5*'Cancel Curves'!$Q$12 + $J5*'Cancel Curves'!$P$12 + $K5*'Cancel Curves'!$O$12 + $L5*'Cancel Curves'!$N$12 + $M5*'Cancel Curves'!$M$12 + $N5*'Cancel Curves'!$L$12 + $O5*'Cancel Curves'!$K$12 + $P5*'Cancel Curves'!$J$12 + $Q5*'Cancel Curves'!$I$12 + $R5*'Cancel Curves'!$H$12 + $S5*'Cancel Curves'!$G$12 + $T5*'Cancel Curves'!$F$12 + $U5*'Cancel Curves'!$E$12 + $V5*'Cancel Curves'!$D$12 + $W5*'Cancel Curves'!$C$12 + $X5*'Cancel Curves'!$B$12 + 625.8304 | Y6: =$D5*'Cancel Curves'!$W$12 + $E5*'Cancel Curves'!$V$12 + $F5*'Cancel Curves'!$U$12 + $G5*'Cancel Curves'!$T$12 + $H5*'Cancel Curves'!$S$12 + $I5*'Cancel Curves'!$R$12 + $J5*'Cancel Curves'!$Q$12 + $K5*'Cancel Curves'!$P$12 + $L5*'Cancel Curves'!$O$12 + $M5*'Cancel Curves'!$N$12 + $N5*'Cancel Curves'!$M$12 + $O5*'Cancel Curves'!$L$12 + $P5*'Cancel Curves'!$K$12 + $Q5*'Cancel Curves'!$J$12 + $R5*'Cancel Curves'!$I$12 + $S5*'Cancel Curves'!$H$12 + $T5*'Cancel Curves'!$G$12 + $U5*'Cancel Curves'!$F$12 + $V5*'Cancel Curves'!$E$12 + $W5*'Cancel Curves'!$D$12 + $X5*'Cancel Curves'!$C$12 + $Y5*'Cancel Curves'!$B$12 + 417.4710 | Z6: =$D5*'Cancel Curves'!$X$12 + $E5*'Cancel Curves'!$W$12 + $F5*'Cancel Curves'!$V$12 + $G5*'Cancel Curves'!$U$12 + $H5*'Cancel Curves'!$T$12 + $I5*'Cancel Curves'!$S$12 + $J5*'Cancel Curves'!$R$12 + $K5*'Cancel Curves'!$Q$12 + $L5*'Cancel Curves'!$P$12 + $M5*'Cancel Curves'!$O$12 + $N5*'Cancel Curves'!$N$12 + $O5*'Cancel Curves'!$M$12 + $P5*'Cancel Curves'!$L$12 + $Q5*'Cancel Curves'!$K$12 + $R5*'Cancel Curves'!$J$12 + $S5*'Cancel Curves'!$I$12 + $T5*'Cancel Curves'!$H$12 + $U5*'Cancel Curves'!$G$12 + $V5*'Cancel Curves'!$F$12 + $W5*'Cancel Curves'!$E$12 + $X5*'Cancel Curves'!$D$12 + $Y5*'Cancel Curves'!$C$12 + $Z5*'Cancel Curves'!$B$12 + 208.7355 | AA6: =$D5*'Cancel Curves'!$Y$12 + $E5*'Cancel Curves'!$X$12 + $F5*'Cancel Curves'!$W$12 + $G5*'Cancel Curves'!$V$12 + $H5*'Cancel Curves'!$U$12 + $I5*'Cancel Curves'!$T$12 + $J5*'Cancel Curves'!$S$12 + $K5*'Cancel Curves'!$R$12 + $L5*'Cancel Curves'!$Q$12 + $M5*'Cancel Curves'!$P$12 + $N5*'Cancel Curves'!$O$12 + $O5*'Cancel Curves'!$N$12 + $P5*'Cancel Curves'!$M$12 + $Q5*'Cancel Curves'!$L$12 + $R5*'Cancel Curves'!$K$12 + $S5*'Cancel Curves'!$J$12 + $T5*'Cancel Curves'!$I$12 + $U5*'Cancel Curves'!$H$12 + $V5*'Cancel Curves'!$G$12 + $W5*'Cancel Curves'!$F$12 + $X5*'Cancel Curves'!$E$12 + $Y5*'Cancel Curves'!$D$12 + $Z5*'Cancel Curves'!$C$12 + $AA5*'Cancel Curves'!$B$12 | AB6: =$D5*'Cancel Curves'!$Z$12 + $E5*'Cancel Curves'!$Y$12 + $F5*'Cancel Curves'!$X$12 + $G5*'Cancel Curves'!$W$12 + $H5*'Cancel Curves'!$V$12 + $I5*'Cancel Curves'!$U$12 + $J5*'Cancel Curves'!$T$12 + $K5*'Cancel Curves'!$S$12 + $L5*'Cancel Curves'!$R$12 + $M5*'Cancel Curves'!$Q$12 + $N5*'Cancel Curves'!$P$12 + $O5*'Cancel Curves'!$O$12 + $P5*'Cancel Curves'!$N$12 + $Q5*'Cancel Curves'!$M$12 + $R5*'Cancel Curves'!$L$12 + $S5*'Cancel Curves'!$K$12 + $T5*'Cancel Curves'!$J$12 + $U5*'Cancel Curves'!$I$12 + $V5*'Cancel Curves'!$H$12 + $W5*'Cancel Curves'!$G$12 + $X5*'Cancel Curves'!$F$12 + $Y5*'Cancel Curves'!$E$12 + $Z5*'Cancel Curves'!$D$12 + $AA5*'Cancel Curves'!$C$12 + $AB5*'Cancel Curves'!$B$12 | AC6: =$D5*'Cancel Curves'!$AA$12 + $E5*'Cancel Curves'!$Z$12 + $F5*'Cancel Curves'!$Y$12 + $G5*'Cancel Curves'!$X$12 + $H5*'Cancel Curves'!$W$12 + $I5*'Cancel Curves'!$V$12 + $J5*'Cancel Curves'!$U$12 + $K5*'Cancel Curves'!$T$12 + $L5*'Cancel Curves'!$S$12 + $M5*'Cancel Curves'!$R$12 + $N5*'Cancel Curves'!$Q$12 + $O5*'Cancel Curves'!$P$12 + $P5*'Cancel Curves'!$O$12 + $Q5*'Cancel Curves'!$N$12 + $R5*'Cancel Curves'!$M$12 + $S5*'Cancel Curves'!$L$12 + $T5*'Cancel Curves'!$K$12 + $U5*'Cancel Curves'!$J$12 + $V5*'Cancel Curves'!$I$12 + $W5*'Cancel Curves'!$H$12 + $X5*'Cancel Curves'!$G$12 + $Y5*'Cancel Curves'!$F$12 + $Z5*'Cancel Curves'!$E$12 + $AA5*'Cancel Curves'!$D$12 + $AB5*'Cancel Curves'!$C$12 + $AC5*'Cancel Curves'!$B$12 | AD6: =$D5*'Cancel Curves'!$AB$12 + $E5*'Cancel Curves'!$AA$12 + $F5*'Cancel Curves'!$Z$12 + $G5*'Cancel Curves'!$Y$12 + $H5*'Cancel Curves'!$X$12 + $I5*'Cancel Curves'!$W$12 + $J5*'Cancel Curves'!$V$12 + $K5*'Cancel Curves'!$U$12 + $L5*'Cancel Curves'!$T$12 + $M5*'Cancel Curves'!$S$12 + $N5*'Cancel Curves'!$R$12 + $O5*'Cancel Curves'!$Q$12 + $P5*'Cancel Curves'!$P$12 + $Q5*'Cancel Curves'!$O$12 + $R5*'Cancel Curves'!$N$12 + $S5*'Cancel Curves'!$M$12 + $T5*'Cancel Curves'!$L$12 + $U5*'Cancel Curves'!$K$12 + $V5*'Cancel Curves'!$J$12 + $W5*'Cancel Curves'!$I$12 + $X5*'Cancel Curves'!$H$12 + $Y5*'Cancel Curves'!$G$12 + $Z5*'Cancel Curves'!$F$12 + $AA5*'Cancel Curves'!$E$12 + $AB5*'Cancel Curves'!$D$12 + $AC5*'Cancel Curves'!$C$12 + $AD5*'Cancel Curves'!$B$12 | AE6: =$D5*'Cancel Curves'!$AC$12 + $E5*'Cancel Curves'!$AB$12 + $F5*'Cancel Curves'!$AA$12 + $G5*'Cancel Curves'!$Z$12 + $H5*'Cancel Curves'!$Y$12 + $I5*'Cancel Curves'!$X$12 + $J5*'Cancel Curves'!$W$12 + $K5*'Cancel Curves'!$V$12 + $L5*'Cancel Curves'!$U$12 + $M5*'Cancel Curves'!$T$12 + $N5*'Cancel Curves'!$S$12 + $O5*'Cancel Curves'!$R$12 + $P5*'Cancel Curves'!$Q$12 + $Q5*'Cancel Curves'!$P$12 + $R5*'Cancel Curves'!$O$12 + $S5*'Cancel Curves'!$N$12 + $T5*'Cancel Curves'!$M$12 + $U5*'Cancel Curves'!$L$12 + $V5*'Cancel Curves'!$K$12 + $W5*'Cancel Curves'!$J$12 + $X5*'Cancel Curves'!$I$12 + $Y5*'Cancel Curves'!$H$12 + $Z5*'Cancel Curves'!$G$12 + $AA5*'Cancel Curves'!$F$12 + $AB5*'Cancel Curves'!$E$12 + $AC5*'Cancel Curves'!$D$12 + $AD5*'Cancel Curves'!$C$12 + $AE5*'Cancel Curves'!$B$12 | AF6: =$D5*'Cancel Curves'!$AD$12 + $E5*'Cancel Curves'!$AC$12 + $F5*'Cancel Curves'!$AB$12 + $G5*'Cancel Curves'!$AA$12 + $H5*'Cancel Curves'!$Z$12 + $I5*'Cancel Curves'!$Y$12 + $J5*'Cancel Curves'!$X$12 + $K5*'Cancel Curves'!$W$12 + $L5*'Cancel Curves'!$V$12 + $M5*'Cancel Curves'!$U$12 + $N5*'Cancel Curves'!$T$12 + $O5*'Cancel Curves'!$S$12 + $P5*'Cancel Curves'!$R$12 + $Q5*'Cancel Curves'!$Q$12 + $R5*'Cancel Curves'!$P$12 + $S5*'Cancel Curves'!$O$12 + $T5*'Cancel Curves'!$N$12 + $U5*'Cancel Curves'!$M$12 + $V5*'Cancel Curves'!$L$12 + $W5*'Cancel Curves'!$K$12 + $X5*'Cancel Curves'!$J$12 + $Y5*'Cancel Curves'!$I$12 + $Z5*'Cancel Curves'!$H$12 + $AA5*'Cancel Curves'!$G$12 + $AB5*'Cancel Curves'!$F$12 + $AC5*'Cancel Curves'!$E$12 + $AD5*'Cancel Curves'!$D$12 + $AE5*'Cancel Curves'!$C$12 + $AF5*'Cancel Curves'!$B$12 | AG6: =$D5*'Cancel Curves'!$AE$12 + $E5*'Cancel Curves'!$AD$12 + $F5*'Cancel Curves'!$AC$12 + $G5*'Cancel Curves'!$AB$12 + $H5*'Cancel Curves'!$AA$12 + $I5*'Cancel Curves'!$Z$12 + $J5*'Cancel Curves'!$Y$12 + $K5*'Cancel Curves'!$X$12 + $L5*'Cancel Curves'!$W$12 + $M5*'Cancel Curves'!$V$12 + $N5*'Cancel Curves'!$U$12 + $O5*'Cancel Curves'!$T$12 + $P5*'Cancel Curves'!$S$12 + $Q5*'Cancel Curves'!$R$12 + $R5*'Cancel Curves'!$Q$12 + $S5*'Cancel Curves'!$P$12 + $T5*'Cancel Curves'!$O$12 + $U5*'Cancel Curves'!$N$12 + $V5*'Cancel Curves'!$M$12 + $W5*'Cancel Curves'!$L$12 + $X5*'Cancel Curves'!$K$12 + $Y5*'Cancel Curves'!$J$12 + $Z5*'Cancel Curves'!$I$12 + $AA5*'Cancel Curves'!$H$12 + $AB5*'Cancel Curves'!$G$12 + $AC5*'Cancel Curves'!$F$12 + $AD5*'Cancel Curves'!$E$12 + $AE5*'Cancel Curves'!$D$12 + $AF5*'Cancel Curves'!$C$12 + $AG5*'Cancel Curves'!$B$12 | AH6: =$E5*'Cancel Curves'!$AE$12 + $F5*'Cancel Curves'!$AD$12 + $G5*'Cancel Curves'!$AC$12 + $H5*'Cancel Curves'!$AB$12 + $I5*'Cancel Curves'!$AA$12 + $J5*'Cancel Curves'!$Z$12 + $K5*'Cancel Curves'!$Y$12 + $L5*'Cancel Curves'!$X$12 + $M5*'Cancel Curves'!$W$12 + $N5*'Cancel Curves'!$V$12 + $O5*'Cancel Curves'!$U$12 + $P5*'Cancel Curves'!$T$12 + $Q5*'Cancel Curves'!$S$12 + $R5*'Cancel Curves'!$R$12 + $S5*'Cancel Curves'!$Q$12 + $T5*'Cancel Curves'!$P$12 + $U5*'Cancel Curves'!$O$12 + $V5*'Cancel Curves'!$N$12 + $W5*'Cancel Curves'!$M$12 + $X5*'Cancel Curves'!$L$12 + $Y5*'Cancel Curves'!$K$12 + $Z5*'Cancel Curves'!$J$12 + $AA5*'Cancel Curves'!$I$12 + $AB5*'Cancel Curves'!$H$12 + $AC5*'Cancel Curves'!$G$12 + $AD5*'Cancel Curves'!$F$12 + $AE5*'Cancel Curves'!$E$12 + $AF5*'Cancel Curves'!$D$12 + $AG5*'Cancel Curves'!$C$12 + $AH5*'Cancel Curves'!$B$12 | AI6: =$F5*'Cancel Curves'!$AE$12 + $G5*'Cancel Curves'!$AD$12 + $H5*'Cancel Curves'!$AC$12 + $I5*'Cancel Curves'!$AB$12 + $J5*'Cancel Curves'!$AA$12 + $K5*'Cancel Curves'!$Z$12 + $L5*'Cancel Curves'!$Y$12 + $M5*'Cancel Curves'!$X$12 + $N5*'Cancel Curves'!$W$12 + $O5*'Cancel Curves'!$V$12 + $P5*'Cancel Curves'!$U$12 + $Q5*'Cancel Curves'!$T$12 + $R5*'Cancel Curves'!$S$12 + $S5*'Cancel Curves'!$R$12 + $T5*'Cancel Curves'!$Q$12 + $U5*'Cancel Curves'!$P$12 + $V5*'Cancel Curves'!$O$12 + $W5*'Cancel Curves'!$N$12 + $X5*'Cancel Curves'!$M$12 + $Y5*'Cancel Curves'!$L$12 + $Z5*'Cancel Curves'!$K$12 + $AA5*'Cancel Curves'!$J$12 + $AB5*'Cancel Curves'!$I$12 + $AC5*'Cancel Curves'!$H$12 + $AD5*'Cancel Curves'!$G$12 + $AE5*'Cancel Curves'!$F$12 + $AF5*'Cancel Curves'!$E$12 + $AG5*'Cancel Curves'!$D$12 + $AH5*'Cancel Curves'!$C$12 + $AI5*'Cancel Curves'!$B$12 | AJ6: =$G5*'Cancel Curves'!$AE$12 + $H5*'Cancel Curves'!$AD$12 + $I5*'Cancel Curves'!$AC$12 + $J5*'Cancel Curves'!$AB$12 + $K5*'Cancel Curves'!$AA$12 + $L5*'Cancel Curves'!$Z$12 + $M5*'Cancel Curves'!$Y$12 + $N5*'Cancel Curves'!$X$12 + $O5*'Cancel Curves'!$W$12 + $P5*'Cancel Curves'!$V$12 + $Q5*'Cancel Curves'!$U$12 + $R5*'Cancel Curves'!$T$12 + $S5*'Cancel Curves'!$S$12 + $T5*'Cancel Curves'!$R$12 + $U5*'Cancel Curves'!$Q$12 + $V5*'Cancel Curves'!$P$12 + $W5*'Cancel Curves'!$O$12 + $X5*'Cancel Curves'!$N$12 + $Y5*'Cancel Curves'!$M$12 + $Z5*'Cancel Curves'!$L$12 + $AA5*'Cancel Curves'!$K$12 + $AB5*'Cancel Curves'!$J$12 + $AC5*'Cancel Curves'!$I$12 + $AD5*'Cancel Curves'!$H$12 + $AE5*'Cancel Curves'!$G$12 + $AF5*'Cancel Curves'!$F$12 + $AG5*'Cancel Curves'!$E$12 + $AH5*'Cancel Curves'!$D$12 + $AI5*'Cancel Curves'!$C$12 + $AJ5*'Cancel Curves'!$B$12 | AK6: =$H5*'Cancel Curves'!$AE$12 + $I5*'Cancel Curves'!$AD$12 + $J5*'Cancel Curves'!$AC$12 + $K5*'Cancel Curves'!$AB$12 + $L5*'Cancel Curves'!$AA$12 + $M5*'Cancel Curves'!$Z$12 + $N5*'Cancel Curves'!$Y$12 + $O5*'Cancel Curves'!$X$12 + $P5*'Cancel Curves'!$W$12 + $Q5*'Cancel Curves'!$V$12 + $R5*'Cancel Curves'!$U$12 + $S5*'Cancel Curves'!$T$12 + $T5*'Cancel Curves'!$S$12 + $U5*'Cancel Curves'!$R$12 + $V5*'Cancel Curves'!$Q$12 + $W5*'Cancel Curves'!$P$12 + $X5*'Cancel Curves'!$O$12 + $Y5*'Cancel Curves'!$N$12 + $Z5*'Cancel Curves'!$M$12 + $AA5*'Cancel Curves'!$L$12 + $AB5*'Cancel Curves'!$K$12 + $AC5*'Cancel Curves'!$J$12 + $AD5*'Cancel Curves'!$I$12 + $AE5*'Cancel Curves'!$H$12 + $AF5*'Cancel Curves'!$G$12 + $AG5*'Cancel Curves'!$F$12 + $AH5*'Cancel Curves'!$E$12 + $AI5*'Cancel Curves'!$D$12 + $AJ5*'Cancel Curves'!$C$12 + $AK5*'Cancel Curves'!$B$12 | AL6: =$I5*'Cancel Curves'!$AE$12 + $J5*'Cancel Curves'!$AD$12 + $K5*'Cancel Curves'!$AC$12 + $L5*'Cancel Curves'!$AB$12 + $M5*'Cancel Curves'!$AA$12 + $N5*'Cancel Curves'!$Z$12 + $O5*'Cancel Curves'!$Y$12 + $P5*'Cancel Curves'!$X$12 + $Q5*'Cancel Curves'!$W$12 + $R5*'Cancel Curves'!$V$12 + $S5*'Cancel Curves'!$U$12 + $T5*'Cancel Curves'!$T$12 + $U5*'Cancel Curves'!$S$12 + $V5*'Cancel Curves'!$R$12 + $W5*'Cancel Curves'!$Q$12 + $X5*'Cancel Curves'!$P$12 + $Y5*'Cancel Curves'!$O$12 + $Z5*'Cancel Curves'!$N$12 + $AA5*'Cancel Curves'!$M$12 + $AB5*'Cancel Curves'!$L$12 + $AC5*'Cancel Curves'!$K$12 + $AD5*'Cancel Curves'!$J$12 + $AE5*'Cancel Curves'!$I$12 + $AF5*'Cancel Curves'!$H$12 + $AG5*'Cancel Curves'!$G$12 + $AH5*'Cancel Curves'!$F$12 + $AI5*'Cancel Curves'!$E$12 + $AJ5*'Cancel Curves'!$D$12 + $AK5*'Cancel Curves'!$C$12 + $AL5*'Cancel Curves'!$B$12 | AM6: =$J5*'Cancel Curves'!$AE$12 + $K5*'Cancel Curves'!$AD$12 + $L5*'Cancel Curves'!$AC$12 + $M5*'Cancel Curves'!$AB$12 + $N5*'Cancel Curves'!$AA$12 + $O5*'Cancel Curves'!$Z$12 + $P5*'Cancel Curves'!$Y$12 + $Q5*'Cancel Curves'!$X$12 + $R5*'Cancel Curves'!$W$12 + $S5*'Cancel Curves'!$V$12 + $T5*'Cancel Curves'!$U$12 + $U5*'Cancel Curves'!$T$12 + $V5*'Cancel Curves'!$S$12 + $W5*'Cancel Curves'!$R$12 + $X5*'Cancel Curves'!$Q$12 + $Y5*'Cancel Curves'!$P$12 + $Z5*'Cancel Curves'!$O$12 + $AA5*'Cancel Curves'!$N$12 + $AB5*'Cancel Curves'!$M$12 + $AC5*'Cancel Curves'!$L$12 + $AD5*'Cancel Curves'!$K$12 + $AE5*'Cancel Curves'!$J$12 + $AF5*'Cancel Curves'!$I$12 + $AG5*'Cancel Curves'!$H$12 + $AH5*'Cancel Curves'!$G$12 + $AI5*'Cancel Curves'!$F$12 + $AJ5*'Cancel Curves'!$E$12 + $AK5*'Cancel Curves'!$D$12 + $AL5*'Cancel Curves'!$C$12 + $AM5*'Cancel Curves'!$B$12 | AN6: =$K5*'Cancel Curves'!$AE$12 + $L5*'Cancel Curves'!$AD$12 + $M5*'Cancel Curves'!$AC$12 + $N5*'Cancel Curves'!$AB$12 + $O5*'Cancel Curves'!$AA$12 + $P5*'Cancel Curves'!$Z$12 + $Q5*'Cancel Curves'!$Y$12 + $R5*'Cancel Curves'!$X$12 + $S5*'Cancel Curves'!$W$12 + $T5*'Cancel Curves'!$V$12 + $U5*'Cancel Curves'!$U$12 + $V5*'Cancel Curves'!$T$12 + $W5*'Cancel Curves'!$S$12 + $X5*'Cancel Curves'!$R$12 + $Y5*'Cancel Curves'!$Q$12 + $Z5*'Cancel Curves'!$P$12 + $AA5*'Cancel Curves'!$O$12 + $AB5*'Cancel Curves'!$N$12 + $AC5*'Cancel Curves'!$M$12 + $AD5*'Cancel Curves'!$L$12 + $AE5*'Cancel Curves'!$K$12 + $AF5*'Cancel Curves'!$J$12 + $AG5*'Cancel Curves'!$I$12 + $AH5*'Cancel Curves'!$H$12 + $AI5*'Cancel Curves'!$G$12 + $AJ5*'Cancel Curves'!$F$12 + $AK5*'Cancel Curves'!$E$12 + $AL5*'Cancel Curves'!$D$12 + $AM5*'Cancel Curves'!$C$12 + $AN5*'Cancel Curves'!$B$12 | AO6: =$L5*'Cancel Curves'!$AE$12 + $M5*'Cancel Curves'!$AD$12 + $N5*'Cancel Curves'!$AC$12 + $O5*'Cancel Curves'!$AB$12 + $P5*'Cancel Curves'!$AA$12 + $Q5*'Cancel Curves'!$Z$12 + $R5*'Cancel Curves'!$Y$12 + $S5*'Cancel Curves'!$X$12 + $T5*'Cancel Curves'!$W$12 + $U5*'Cancel Curves'!$V$12 + $V5*'Cancel Curves'!$U$12 + $W5*'Cancel Curves'!$T$12 + $X5*'Cancel Curves'!$S$12 + $Y5*'Cancel Curves'!$R$12 + $Z5*'Cancel Curves'!$Q$12 + $AA5*'Cancel Curves'!$P$12 + $AB5*'Cancel Curves'!$O$12 + $AC5*'Cancel Curves'!$N$12 + $AD5*'Cancel Curves'!$M$12 + $AE5*'Cancel Curves'!$L$12 + $AF5*'Cancel Curves'!$K$12 + $AG5*'Cancel Curves'!$J$12 + $AH5*'Cancel Curves'!$I$12 + $AI5*'Cancel Curves'!$H$12 + $AJ5*'Cancel Curves'!$G$12 + $AK5*'Cancel Curves'!$F$12 + $AL5*'Cancel Curves'!$E$12 + $AM5*'Cancel Curves'!$D$12 + $AN5*'Cancel Curves'!$C$12 + $AO5*'Cancel Curves'!$B$12 | AP6: =$M5*'Cancel Curves'!$AE$12 + $N5*'Cancel Curves'!$AD$12 + $O5*'Cancel Curves'!$AC$12 + $P5*'Cancel Curves'!$AB$12 + $Q5*'Cancel Curves'!$AA$12 + $R5*'Cancel Curves'!$Z$12 + $S5*'Cancel Curves'!$Y$12 + $T5*'Cancel Curves'!$X$12 + $U5*'Cancel Curves'!$W$12 + $V5*'Cancel Curves'!$V$12 + $W5*'Cancel Curves'!$U$12 + $X5*'Cancel Curves'!$T$12 + $Y5*'Cancel Curves'!$S$12 + $Z5*'Cancel Curves'!$R$12 + $AA5*'Cancel Curves'!$Q$12 + $AB5*'Cancel Curves'!$P$12 + $AC5*'Cancel Curves'!$O$12 + $AD5*'Cancel Curves'!$N$12 + $AE5*'Cancel Curves'!$M$12 + $AF5*'Cancel Curves'!$L$12 + $AG5*'Cancel Curves'!$K$12 + $AH5*'Cancel Curves'!$J$12 + $AI5*'Cancel Curves'!$I$12 + $AJ5*'Cancel Curves'!$H$12 + $AK5*'Cancel Curves'!$G$12 + $AL5*'Cancel Curves'!$F$12 + $AM5*'Cancel Curves'!$E$12 + $AN5*'Cancel Curves'!$D$12 + $AO5*'Cancel Curves'!$C$12 + $AP5*'Cancel Curves'!$B$12 | AQ6: =$N5*'Cancel Curves'!$AE$12 + $O5*'Cancel Curves'!$AD$12 + $P5*'Cancel Curves'!$AC$12 + $Q5*'Cancel Curves'!$AB$12 + $R5*'Cancel Curves'!$AA$12 + $S5*'Cancel Curves'!$Z$12 + $T5*'Cancel Curves'!$Y$12 + $U5*'Cancel Curves'!$X$12 + $V5*'Cancel Curves'!$W$12 + $W5*'Cancel Curves'!$V$12 + $X5*'Cancel Curves'!$U$12 + $Y5*'Cancel Curves'!$T$12 + $Z5*'Cancel Curves'!$S$12 + $AA5*'Cancel Curves'!$R$12 + $AB5*'Cancel Curves'!$Q$12 + $AC5*'Cancel Curves'!$P$12 + $AD5*'Cancel Curves'!$O$12 + $AE5*'Cancel Curves'!$N$12 + $AF5*'Cancel Curves'!$M$12 + $AG5*'Cancel Curves'!$L$12 + $AH5*'Cancel Curves'!$K$12 + $AI5*'Cancel Curves'!$J$12 + $AJ5*'Cancel Curves'!$I$12 + $AK5*'Cancel Curves'!$H$12 + $AL5*'Cancel Curves'!$G$12 + $AM5*'Cancel Curves'!$F$12 + $AN5*'Cancel Curves'!$E$12 + $AO5*'Cancel Curves'!$D$12 + $AP5*'Cancel Curves'!$C$12 + $AQ5*'Cancel Curves'!$B$12 | AR6: =$O5*'Cancel Curves'!$AE$12 + $P5*'Cancel Curves'!$AD$12 + $Q5*'Cancel Curves'!$AC$12 + $R5*'Cancel Curves'!$AB$12 + $S5*'Cancel Curves'!$AA$12 + $T5*'Cancel Curves'!$Z$12 + $U5*'Cancel Curves'!$Y$12 + $V5*'Cancel Curves'!$X$12 + $W5*'Cancel Curves'!$W$12 + $X5*'Cancel Curves'!$V$12 + $Y5*'Cancel Curves'!$U$12 + $Z5*'Cancel Curves'!$T$12 + $AA5*'Cancel Curves'!$S$12 + $AB5*'Cancel Curves'!$R$12 + $AC5*'Cancel Curves'!$Q$12 + $AD5*'Cancel Curves'!$P$12 + $AE5*'Cancel Curves'!$O$12 + $AF5*'Cancel Curves'!$N$12 + $AG5*'Cancel Curves'!$M$12 + $AH5*'Cancel Curves'!$L$12 + $AI5*'Cancel Curves'!$K$12 + $AJ5*'Cancel Curves'!$J$12 + $AK5*'Cancel Curves'!$I$12 + $AL5*'Cancel Curves'!$H$12 + $AM5*'Cancel Curves'!$G$12 + $AN5*'Cancel Curves'!$F$12 + $AO5*'Cancel Curves'!$E$12 + $AP5*'Cancel Curves'!$D$12 + $AQ5*'Cancel Curves'!$C$12 + $AR5*'Cancel Curves'!$B$12 | AS6: =$P5*'Cancel Curves'!$AE$12 + $Q5*'Cancel Curves'!$AD$12 + $R5*'Cancel Curves'!$AC$12 + $S5*'Cancel Curves'!$AB$12 + $T5*'Cancel Curves'!$AA$12 + $U5*'Cancel Curves'!$Z$12 + $V5*'Cancel Curves'!$Y$12 + $W5*'Cancel Curves'!$X$12 + $X5*'Cancel Curves'!$W$12 + $Y5*'Cancel Curves'!$V$12 + $Z5*'Cancel Curves'!$U$12 + $AA5*'Cancel Curves'!$T$12 + $AB5*'Cancel Curves'!$S$12 + $AC5*'Cancel Curves'!$R$12 + $AD5*'Cancel Curves'!$Q$12 + $AE5*'Cancel Curves'!$P$12 + $AF5*'Cancel Curves'!$O$12 + $AG5*'Cancel Curves'!$N$12 + $AH5*'Cancel Curves'!$M$12 + $AI5*'Cancel Curves'!$L$12 + $AJ5*'Cancel Curves'!$K$12 + $AK5*'Cancel Curves'!$J$12 + $AL5*'Cancel Curves'!$I$12 + $AM5*'Cancel Curves'!$H$12 + $AN5*'Cancel Curves'!$G$12 + $AO5*'Cancel Curves'!$F$12 + $AP5*'Cancel Curves'!$E$12 + $AQ5*'Cancel Curves'!$D$12 + $AR5*'Cancel Curves'!$C$12 + $AS5*'Cancel Curves'!$B$12 | AT6: =$Q5*'Cancel Curves'!$AE$12 + $R5*'Cancel Curves'!$AD$12 + $S5*'Cancel Curves'!$AC$12 + $T5*'Cancel Curves'!$AB$12 + $U5*'Cancel Curves'!$AA$12 + $V5*'Cancel Curves'!$Z$12 + $W5*'Cancel Curves'!$Y$12 + $X5*'Cancel Curves'!$X$12 + $Y5*'Cancel Curves'!$W$12 + $Z5*'Cancel Curves'!$V$12 + $AA5*'Cancel Curves'!$U$12 + $AB5*'Cancel Curves'!$T$12 + $AC5*'Cancel Curves'!$S$12 + $AD5*'Cancel Curves'!$R$12 + $AE5*'Cancel Curves'!$Q$12 + $AF5*'Cancel Curves'!$P$12 + $AG5*'Cancel Curves'!$O$12 + $AH5*'Cancel Curves'!$N$12 + $AI5*'Cancel Curves'!$M$12 + $AJ5*'Cancel Curves'!$L$12 + $AK5*'Cancel Curves'!$K$12 + $AL5*'Cancel Curves'!$J$12 + $AM5*'Cancel Curves'!$I$12 + $AN5*'Cancel Curves'!$H$12 + $AO5*'Cancel Curves'!$G$12 + $AP5*'Cancel Curves'!$F$12 + $AQ5*'Cancel Curves'!$E$12 + $AR5*'Cancel Curves'!$D$12 + $AS5*'Cancel Curves'!$C$12 + $AT5*'Cancel Curves'!$B$12 | AU6: =$R5*'Cancel Curves'!$AE$12 + $S5*'Cancel Curves'!$AD$12 + $T5*'Cancel Curves'!$AC$12 + $U5*'Cancel Curves'!$AB$12 + $V5*'Cancel Curves'!$AA$12 + $W5*'Cancel Curves'!$Z$12 + $X5*'Cancel Curves'!$Y$12 + $Y5*'Cancel Curves'!$X$12 + $Z5*'Cancel Curves'!$W$12 + $AA5*'Cancel Curves'!$V$12 + $AB5*'Cancel Curves'!$U$12 + $AC5*'Cancel Curves'!$T$12 + $AD5*'Cancel Curves'!$S$12 + $AE5*'Cancel Curves'!$R$12 + $AF5*'Cancel Curves'!$Q$12 + $AG5*'Cancel Curves'!$P$12 + $AH5*'Cancel Curves'!$O$12 + $AI5*'Cancel Curves'!$N$12 + $AJ5*'Cancel Curves'!$M$12 + $AK5*'Cancel Curves'!$L$12 + $AL5*'Cancel Curves'!$K$12 + $AM5*'Cancel Curves'!$J$12 + $AN5*'Cancel Curves'!$I$12 + $AO5*'Cancel Curves'!$H$12 + $AP5*'Cancel Curves'!$G$12 + $AQ5*'Cancel Curves'!$F$12 + $AR5*'Cancel Curves'!$E$12 + $AS5*'Cancel Curves'!$D$12 + $AT5*'Cancel Curves'!$C$12 + $AU5*'Cancel Curves'!$B$12 | AV6: =$S5*'Cancel Curves'!$AE$12 + $T5*'Cancel Curves'!$AD$12 + $U5*'Cancel Curves'!$AC$12 + $V5*'Cancel Curves'!$AB$12 + $W5*'Cancel Curves'!$AA$12 + $X5*'Cancel Curves'!$Z$12 + $Y5*'Cancel Curves'!$Y$12 + $Z5*'Cancel Curves'!$X$12 + $AA5*'Cancel Curves'!$W$12 + $AB5*'Cancel Curves'!$V$12 + $AC5*'Cancel Curves'!$U$12 + $AD5*'Cancel Curves'!$T$12 + $AE5*'Cancel Curves'!$S$12 + $AF5*'Cancel Curves'!$R$12 + $AG5*'Cancel Curves'!$Q$12 + $AH5*'Cancel Curves'!$P$12 + $AI5*'Cancel Curves'!$O$12 + $AJ5*'Cancel Curves'!$N$12 + $AK5*'Cancel Curves'!$M$12 + $AL5*'Cancel Curves'!$L$12 + $AM5*'Cancel Curves'!$K$12 + $AN5*'Cancel Curves'!$J$12 + $AO5*'Cancel Curves'!$I$12 + $AP5*'Cancel Curves'!$H$12 + $AQ5*'Cancel Curves'!$G$12 + $AR5*'Cancel Curves'!$F$12 + $AS5*'Cancel Curves'!$E$12 + $AT5*'Cancel Curves'!$D$12 + $AU5*'Cancel Curves'!$C$12 + $AV5*'Cancel Curves'!$B$12 | AW6: =$T5*'Cancel Curves'!$AE$12 + $U5*'Cancel Curves'!$AD$12 + $V5*'Cancel Curves'!$AC$12 + $W5*'Cancel Curves'!$AB$12 + $X5*'Cancel Curves'!$AA$12 + $Y5*'Cancel Curves'!$Z$12 + $Z5*'Cancel Curves'!$Y$12 + $AA5*'Cancel Curves'!$X$12 + $AB5*'Cancel Curves'!$W$12 + $AC5*'Cancel Curves'!$V$12 + $AD5*'Cancel Curves'!$U$12 + $AE5*'Cancel Curves'!$T$12 + $AF5*'Cancel Curves'!$S$12 + $AG5*'Cancel Curves'!$R$12 + $AH5*'Cancel Curves'!$Q$12 + $AI5*'Cancel Curves'!$P$12 + $AJ5*'Cancel Curves'!$O$12 + $AK5*'Cancel Curves'!$N$12 + $AL5*'Cancel Curves'!$M$12 + $AM5*'Cancel Curves'!$L$12 + $AN5*'Cancel Curves'!$K$12 + $AO5*'Cancel Curves'!$J$12 + $AP5*'Cancel Curves'!$I$12 + $AQ5*'Cancel Curves'!$H$12 + $AR5*'Cancel Curves'!$G$12 + $AS5*'Cancel Curves'!$F$12 + $AT5*'Cancel Curves'!$E$12 + $AU5*'Cancel Curves'!$D$12 + $AV5*'Cancel Curves'!$C$12 + $AW5*'Cancel Curves'!$B$12 | AX6: =$U5*'Cancel Curves'!$AE$12 + $V5*'Cancel Curves'!$AD$12 + $W5*'Cancel Curves'!$AC$12 + $X5*'Cancel Curves'!$AB$12 + $Y5*'Cancel Curves'!$AA$12 + $Z5*'Cancel Curves'!$Z$12 + $AA5*'Cancel Curves'!$Y$12 + $AB5*'Cancel Curves'!$X$12 + $AC5*'Cancel Curves'!$W$12 + $AD5*'Cancel Curves'!$V$12 + $AE5*'Cancel Curves'!$U$12 + $AF5*'Cancel Curves'!$T$12 + $AG5*'Cancel Curves'!$S$12 + $AH5*'Cancel Curves'!$R$12 + $AI5*'Cancel Curves'!$Q$12 + $AJ5*'Cancel Curves'!$P$12 + $AK5*'Cancel Curves'!$O$12 + $AL5*'Cancel Curves'!$N$12 + $AM5*'Cancel Curves'!$M$12 + $AN5*'Cancel Curves'!$L$12 + $AO5*'Cancel Curves'!$K$12 + $AP5*'Cancel Curves'!$J$12 + $AQ5*'Cancel Curves'!$I$12 + $AR5*'Cancel Curves'!$H$12 + $AS5*'Cancel Curves'!$G$12 + $AT5*'Cancel Curves'!$F$12 + $AU5*'Cancel Curves'!$E$12 + $AV5*'Cancel Curves'!$D$12 + $AW5*'Cancel Curves'!$C$12 + $AX5*'Cancel Curves'!$B$12 | AY6: =$V5*'Cancel Curves'!$AE$12 + $W5*'Cancel Curves'!$AD$12 + $X5*'Cancel Curves'!$AC$12 + $Y5*'Cancel Curves'!$AB$12 + $Z5*'Cancel Curves'!$AA$12 + $AA5*'Cancel Curves'!$Z$12 + $AB5*'Cancel Curves'!$Y$12 + $AC5*'Cancel Curves'!$X$12 + $AD5*'Cancel Curves'!$W$12 + $AE5*'Cancel Curves'!$V$12 + $AF5*'Cancel Curves'!$U$12 + $AG5*'Cancel Curves'!$T$12 + $AH5*'Cancel Curves'!$S$12 + $AI5*'Cancel Curves'!$R$12 + $AJ5*'Cancel Curves'!$Q$12 + $AK5*'Cancel Curves'!$P$12 + $AL5*'Cancel Curves'!$O$12 + $AM5*'Cancel Curves'!$N$12 + $AN5*'Cancel Curves'!$M$12 + $AO5*'Cancel Curves'!$L$12 + $AP5*'Cancel Curves'!$K$12 + $AQ5*'Cancel Curves'!$J$12 + $AR5*'Cancel Curves'!$I$12 + $AS5*'Cancel Curves'!$H$12 + $AT5*'Cancel Curves'!$G$12 + $AU5*'Cancel Curves'!$F$12 + $AV5*'Cancel Curves'!$E$12 + $AW5*'Cancel Curves'!$D$12 + $AX5*'Cancel Curves'!$C$12 + $AY5*'Cancel Curves'!$B$12 | AZ6: =$W5*'Cancel Curves'!$AE$12 + $X5*'Cancel Curves'!$AD$12 + $Y5*'Cancel Curves'!$AC$12 + $Z5*'Cancel Curves'!$AB$12 + $AA5*'Cancel Curves'!$AA$12 + $AB5*'Cancel Curves'!$Z$12 + $AC5*'Cancel Curves'!$Y$12 + $AD5*'Cancel Curves'!$X$12 + $AE5*'Cancel Curves'!$W$12 + $AF5*'Cancel Curves'!$V$12 + $AG5*'Cancel Curves'!$U$12 + $AH5*'Cancel Curves'!$T$12 + $AI5*'Cancel Curves'!$S$12 + $AJ5*'Cancel Curves'!$R$12 + $AK5*'Cancel Curves'!$Q$12 + $AL5*'Cancel Curves'!$P$12 + $AM5*'Cancel Curves'!$O$12 + $AN5*'Cancel Curves'!$N$12 + $AO5*'Cancel Curves'!$M$12 + $AP5*'Cancel Curves'!$L$12 + $AQ5*'Cancel Curves'!$K$12 + $AR5*'Cancel Curves'!$J$12 + $AS5*'Cancel Curves'!$I$12 + $AT5*'Cancel Curves'!$H$12 + $AU5*'Cancel Curves'!$G$12 + $AV5*'Cancel Curves'!$F$12 + $AW5*'Cancel Curves'!$E$12 + $AX5*'Cancel Curves'!$D$12 + $AY5*'Cancel Curves'!$C$12 + $AZ5*'Cancel Curves'!$B$12 | BA6: =$X5*'Cancel Curves'!$AE$12 + $Y5*'Cancel Curves'!$AD$12 + $Z5*'Cancel Curves'!$AC$12 + $AA5*'Cancel Curves'!$AB$12 + $AB5*'Cancel Curves'!$AA$12 + $AC5*'Cancel Curves'!$Z$12 + $AD5*'Cancel Curves'!$Y$12 + $AE5*'Cancel Curves'!$X$12 + $AF5*'Cancel Curves'!$W$12 + $AG5*'Cancel Curves'!$V$12 + $AH5*'Cancel Curves'!$U$12 + $AI5*'Cancel Curves'!$T$12 + $AJ5*'Cancel Curves'!$S$12 + $AK5*'Cancel Curves'!$R$12 + $AL5*'Cancel Curves'!$Q$12 + $AM5*'Cancel Curves'!$P$12 + $AN5*'Cancel Curves'!$O$12 + $AO5*'Cancel Curves'!$N$12 + $AP5*'Cancel Curves'!$M$12 + $AQ5*'Cancel Curves'!$L$12 + $AR5*'Cancel Curves'!$K$12 + $AS5*'Cancel Curves'!$J$12 + $AT5*'Cancel Curves'!$I$12 + $AU5*'Cancel Curves'!$H$12 + $AV5*'Cancel Curves'!$G$12 + $AW5*'Cancel Curves'!$F$12 + $AX5*'Cancel Curves'!$E$12 + $AY5*'Cancel Curves'!$D$12 + $AZ5*'Cancel Curves'!$C$12 + $BA5*'Cancel Curves'!$B$12 | BB6: =$Y5*'Cancel Curves'!$AE$12 + $Z5*'Cancel Curves'!$AD$12 + $AA5*'Cancel Curves'!$AC$12 + $AB5*'Cancel Curves'!$AB$12 + $AC5*'Cancel Curves'!$AA$12 + $AD5*'Cancel Curves'!$Z$12 + $AE5*'Cancel Curves'!$Y$12 + $AF5*'Cancel Curves'!$X$12 + $AG5*'Cancel Curves'!$W$12 + $AH5*'Cancel Curves'!$V$12 + $AI5*'Cancel Curves'!$U$12 + $AJ5*'Cancel Curves'!$T$12 + $AK5*'Cancel Curves'!$S$12 + $AL5*'Cancel Curves'!$R$12 + $AM5*'Cancel Curves'!$Q$12 + $AN5*'Cancel Curves'!$P$12 + $AO5*'Cancel Curves'!$O$12 + $AP5*'Cancel Curves'!$N$12 + $AQ5*'Cancel Curves'!$M$12 + $AR5*'Cancel Curves'!$L$12 + $AS5*'Cancel Curves'!$K$12 + $AT5*'Cancel Curves'!$J$12 + $AU5*'Cancel Curves'!$I$12 + $AV5*'Cancel Curves'!$H$12 + $AW5*'Cancel Curves'!$G$12 + $AX5*'Cancel Curves'!$F$12 + $AY5*'Cancel Curves'!$E$12 + $AZ5*'Cancel Curves'!$D$12 + $BA5*'Cancel Curves'!$C$12 + $BB5*'Cancel Curves'!$B$12 | BC6: =$Z5*'Cancel Curves'!$AE$12 + $AA5*'Cancel Curves'!$AD$12 + $AB5*'Cancel Curves'!$AC$12 + $AC5*'Cancel Curves'!$AB$12 + $AD5*'Cancel Curves'!$AA$12 + $AE5*'Cancel Curves'!$Z$12 + $AF5*'Cancel Curves'!$Y$12 + $AG5*'Cancel Curves'!$X$12 + $AH5*'Cancel Curves'!$W$12 + $AI5*'Cancel Curves'!$V$12 + $AJ5*'Cancel Curves'!$U$12 + $AK5*'Cancel Curves'!$T$12 + $AL5*'Cancel Curves'!$S$12 + $AM5*'Cancel Curves'!$R$12 + $AN5*'Cancel Curves'!$Q$12 + $AO5*'Cancel Curves'!$P$12 + $AP5*'Cancel Curves'!$O$12 + $AQ5*'Cancel Curves'!$N$12 + $AR5*'Cancel Curves'!$M$12 + $AS5*'Cancel Curves'!$L$12 + $AT5*'Cancel Curves'!$K$12 + $AU5*'Cancel Curves'!$J$12 + $AV5*'Cancel Curves'!$I$12 + $AW5*'Cancel Curves'!$H$12 + $AX5*'Cancel Curves'!$G$12 + $AY5*'Cancel Curves'!$F$12 + $AZ5*'Cancel Curves'!$E$12 + $BA5*'Cancel Curves'!$D$12 + $BB5*'Cancel Curves'!$C$12 + $BC5*'Cancel Curves'!$B$12 | BD6: =$AA5*'Cancel Curves'!$AE$12 + $AB5*'Cancel Curves'!$AD$12 + $AC5*'Cancel Curves'!$AC$12 + $AD5*'Cancel Curves'!$AB$12 + $AE5*'Cancel Curves'!$AA$12 + $AF5*'Cancel Curves'!$Z$12 + $AG5*'Cancel Curves'!$Y$12 + $AH5*'Cancel Curves'!$X$12 + $AI5*'Cancel Curves'!$W$12 + $AJ5*'Cancel Curves'!$V$12 + $AK5*'Cancel Curves'!$U$12 + $AL5*'Cancel Curves'!$T$12 + $AM5*'Cancel Curves'!$S$12 + $AN5*'Cancel Curves'!$R$12 + $AO5*'Cancel Curves'!$Q$12 + $AP5*'Cancel Curves'!$P$12 + $AQ5*'Cancel Curves'!$O$12 + $AR5*'Cancel Curves'!$N$12 + $AS5*'Cancel Curves'!$M$12 + $AT5*'Cancel Curves'!$L$12 + $AU5*'Cancel Curves'!$K$12 + $AV5*'Cancel Curves'!$J$12 + $AW5*'Cancel Curves'!$I$12 + $AX5*'Cancel Curves'!$H$12 + $AY5*'Cancel Curves'!$G$12 + $AZ5*'Cancel Curves'!$F$12 + $BA5*'Cancel Curves'!$E$12 + $BB5*'Cancel Curves'!$D$12 + $BC5*'Cancel Curves'!$C$12 + $BD5*'Cancel Curves'!$B$12 | BE6: =$AB5*'Cancel Curves'!$AE$12 + $AC5*'Cancel Curves'!$AD$12 + $AD5*'Cancel Curves'!$AC$12 + $AE5*'Cancel Curves'!$AB$12 + $AF5*'Cancel Curves'!$AA$12 + $AG5*'Cancel Curves'!$Z$12 + $AH5*'Cancel Curves'!$Y$12 + $AI5*'Cancel Curves'!$X$12 + $AJ5*'Cancel Curves'!$W$12 + $AK5*'Cancel Curves'!$V$12 + $AL5*'Cancel Curves'!$U$12 + $AM5*'Cancel Curves'!$T$12 + $AN5*'Cancel Curves'!$S$12 + $AO5*'Cancel Curves'!$R$12 + $AP5*'Cancel Curves'!$Q$12 + $AQ5*'Cancel Curves'!$P$12 + $AR5*'Cancel Curves'!$O$12 + $AS5*'Cancel Curves'!$N$12 + $AT5*'Cancel Curves'!$M$12 + $AU5*'Cancel Curves'!$L$12 + $AV5*'Cancel Curves'!$K$12 + $AW5*'Cancel Curves'!$J$12 + $AX5*'Cancel Curves'!$I$12 + $AY5*'Cancel Curves'!$H$12 + $AZ5*'Cancel Curves'!$G$12 + $BA5*'Cancel Curves'!$F$12 + $BB5*'Cancel Curves'!$E$12 + $BC5*'Cancel Curves'!$D$12 + $BD5*'Cancel Curves'!$C$12 + $BE5*'Cancel Curves'!$B$12 | BF6: =$AC5*'Cancel Curves'!$AE$12 + $AD5*'Cancel Curves'!$AD$12 + $AE5*'Cancel Curves'!$AC$12 + $AF5*'Cancel Curves'!$AB$12 + $AG5*'Cancel Curves'!$AA$12 + $AH5*'Cancel Curves'!$Z$12 + $AI5*'Cancel Curves'!$Y$12 + $AJ5*'Cancel Curves'!$X$12 + $AK5*'Cancel Curves'!$W$12 + $AL5*'Cancel Curves'!$V$12 + $AM5*'Cancel Curves'!$U$12 + $AN5*'Cancel Curves'!$T$12 + $AO5*'Cancel Curves'!$S$12 + $AP5*'Cancel Curves'!$R$12 + $AQ5*'Cancel Curves'!$Q$12 + $AR5*'Cancel Curves'!$P$12 + $AS5*'Cancel Curves'!$O$12 + $AT5*'Cancel Curves'!$N$12 + $AU5*'Cancel Curves'!$M$12 + $AV5*'Cancel Curves'!$L$12 + $AW5*'Cancel Curves'!$K$12 + $AX5*'Cancel Curves'!$J$12 + $AY5*'Cancel Curves'!$I$12 + $AZ5*'Cancel Curves'!$H$12 + $BA5*'Cancel Curves'!$G$12 + $BB5*'Cancel Curves'!$F$12 + $BC5*'Cancel Curves'!$E$12 + $BD5*'Cancel Curves'!$D$12 + $BE5*'Cancel Curves'!$C$12 + $BF5*'Cancel Curves'!$B$12 | BG6: =$AD5*'Cancel Curves'!$AE$12 + $AE5*'Cancel Curves'!$AD$12 + $AF5*'Cancel Curves'!$AC$12 + $AG5*'Cancel Curves'!$AB$12 + $AH5*'Cancel Curves'!$AA$12 + $AI5*'Cancel Curves'!$Z$12 + $AJ5*'Cancel Curves'!$Y$12 + $AK5*'Cancel Curves'!$X$12 + $AL5*'Cancel Curves'!$W$12 + $AM5*'Cancel Curves'!$V$12 + $AN5*'Cancel Curves'!$U$12 + $AO5*'Cancel Curves'!$T$12 + $AP5*'Cancel Curves'!$S$12 + $AQ5*'Cancel Curves'!$R$12 + $AR5*'Cancel Curves'!$Q$12 + $AS5*'Cancel Curves'!$P$12 + $AT5*'Cancel Curves'!$O$12 + $AU5*'Cancel Curves'!$N$12 + $AV5*'Cancel Curves'!$M$12 + $AW5*'Cancel Curves'!$L$12 + $AX5*'Cancel Curves'!$K$12 + $AY5*'Cancel Curves'!$J$12 + $AZ5*'Cancel Curves'!$I$12 + $BA5*'Cancel Curves'!$H$12 + $BB5*'Cancel Curves'!$G$12 + $BC5*'Cancel Curves'!$F$12 + $BD5*'Cancel Curves'!$E$12 + $BE5*'Cancel Curves'!$D$12 + $BF5*'Cancel Curves'!$C$12 + $BG5*'Cancel Curves'!$B$12 | BH6: =$AE5*'Cancel Curves'!$AE$12 + $AF5*'Cancel Curves'!$AD$12 + $AG5*'Cancel Curves'!$AC$12 + $AH5*'Cancel Curves'!$AB$12 + $AI5*'Cancel Curves'!$AA$12 + $AJ5*'Cancel Curves'!$Z$12 + $AK5*'Cancel Curves'!$Y$12 + $AL5*'Cancel Curves'!$X$12 + $AM5*'Cancel Curves'!$W$12 + $AN5*'Cancel Curves'!$V$12 + $AO5*'Cancel Curves'!$U$12 + $AP5*'Cancel Curves'!$T$12 + $AQ5*'Cancel Curves'!$S$12 + $AR5*'Cancel Curves'!$R$12 + $AS5*'Cancel Curves'!$Q$12 + $AT5*'Cancel Curves'!$P$12 + $AU5*'Cancel Curves'!$O$12 + $AV5*'Cancel Curves'!$N$12 + $AW5*'Cancel Curves'!$M$12 + $AX5*'Cancel Curves'!$L$12 + $AY5*'Cancel Curves'!$K$12 + $AZ5*'Cancel Curves'!$J$12 + $BA5*'Cancel Curves'!$I$12 + $BB5*'Cancel Curves'!$H$12 + $BC5*'Cancel Curves'!$G$12 + $BD5*'Cancel Curves'!$F$12 + $BE5*'Cancel Curves'!$E$12 + $BF5*'Cancel Curves'!$D$12 + $BG5*'Cancel Curves'!$C$12 + $BH5*'Cancel Curves'!$B$12 | BI6: =$AF5*'Cancel Curves'!$AE$12 + $AG5*'Cancel Curves'!$AD$12 + $AH5*'Cancel Curves'!$AC$12 + $AI5*'Cancel Curves'!$AB$12 + $AJ5*'Cancel Curves'!$AA$12 + $AK5*'Cancel Curves'!$Z$12 + $AL5*'Cancel Curves'!$Y$12 + $AM5*'Cancel Curves'!$X$12 + $AN5*'Cancel Curves'!$W$12 + $AO5*'Cancel Curves'!$V$12 + $AP5*'Cancel Curves'!$U$12 + $AQ5*'Cancel Curves'!$T$12 + $AR5*'Cancel Curves'!$S$12 + $AS5*'Cancel Curves'!$R$12 + $AT5*'Cancel Curves'!$Q$12 + $AU5*'Cancel Curves'!$P$12 + $AV5*'Cancel Curves'!$O$12 + $AW5*'Cancel Curves'!$N$12 + $AX5*'Cancel Curves'!$M$12 + $AY5*'Cancel Curves'!$L$12 + $AZ5*'Cancel Curves'!$K$12 + $BA5*'Cancel Curves'!$J$12 + $BB5*'Cancel Curves'!$I$12 + $BC5*'Cancel Curves'!$H$12 + $BD5*'Cancel Curves'!$G$12 + $BE5*'Cancel Curves'!$F$12 + $BF5*'Cancel Curves'!$E$12 + $BG5*'Cancel Curves'!$D$12 + $BH5*'Cancel Curves'!$C$12 + $BI5*'Cancel Curves'!$B$12 | BJ6: =$AG5*'Cancel Curves'!$AE$12 + $AH5*'Cancel Curves'!$AD$12 + $AI5*'Cancel Curves'!$AC$12 + $AJ5*'Cancel Curves'!$AB$12 + $AK5*'Cancel Curves'!$AA$12 + $AL5*'Cancel Curves'!$Z$12 + $AM5*'Cancel Curves'!$Y$12 + $AN5*'Cancel Curves'!$X$12 + $AO5*'Cancel Curves'!$W$12 + $AP5*'Cancel Curves'!$V$12 + $AQ5*'Cancel Curves'!$U$12 + $AR5*'Cancel Curves'!$T$12 + $AS5*'Cancel Curves'!$S$12 + $AT5*'Cancel Curves'!$R$12 + $AU5*'Cancel Curves'!$Q$12 + $AV5*'Cancel Curves'!$P$12 + $AW5*'Cancel Curves'!$O$12 + $AX5*'Cancel Curves'!$N$12 + $AY5*'Cancel Curves'!$M$12 + $AZ5*'Cancel Curves'!$L$12 + $BA5*'Cancel Curves'!$K$12 + $BB5*'Cancel Curves'!$J$12 + $BC5*'Cancel Curves'!$I$12 + $BD5*'Cancel Curves'!$H$12 + $BE5*'Cancel Curves'!$G$12 + $BF5*'Cancel Curves'!$F$12 + $BG5*'Cancel Curves'!$E$12 + $BH5*'Cancel Curves'!$D$12 + $BI5*'Cancel Curves'!$C$12 + $BJ5*'Cancel Curves'!$B$12 | BK6: =$AH5*'Cancel Curves'!$AE$12 + $AI5*'Cancel Curves'!$AD$12 + $AJ5*'Cancel Curves'!$AC$12 + $AK5*'Cancel Curves'!$AB$12 + $AL5*'Cancel Curves'!$AA$12 + $AM5*'Cancel Curves'!$Z$12 + $AN5*'Cancel Curves'!$Y$12 + $AO5*'Cancel Curves'!$X$12 + $AP5*'Cancel Curves'!$W$12 + $AQ5*'Cancel Curves'!$V$12 + $AR5*'Cancel Curves'!$U$12 + $AS5*'Cancel Curves'!$T$12 + $AT5*'Cancel Curves'!$S$12 + $AU5*'Cancel Curves'!$R$12 + $AV5*'Cancel Curves'!$Q$12 + $AW5*'Cancel Curves'!$P$12 + $AX5*'Cancel Curves'!$O$12 + $AY5*'Cancel Curves'!$N$12 + $AZ5*'Cancel Curves'!$M$12 + $BA5*'Cancel Curves'!$L$12 + $BB5*'Cancel Curves'!$K$12 + $BC5*'Cancel Curves'!$J$12 + $BD5*'Cancel Curves'!$I$12 + $BE5*'Cancel Curves'!$H$12 + $BF5*'Cancel Curves'!$G$12 + $BG5*'Cancel Curves'!$F$12 + $BH5*'Cancel Curves'!$E$12 + $BI5*'Cancel Curves'!$D$12 + $BJ5*'Cancel Curves'!$C$12 + $BK5*'Cancel Curves'!$B$12 | BL6: =$AI5*'Cancel Curves'!$AE$12 + $AJ5*'Cancel Curves'!$AD$12 + $AK5*'Cancel Curves'!$AC$12 + $AL5*'Cancel Curves'!$AB$12 + $AM5*'Cancel Curves'!$AA$12 + $AN5*'Cancel Curves'!$Z$12 + $AO5*'Cancel Curves'!$Y$12 + $AP5*'Cancel Curves'!$X$12 + $AQ5*'Cancel Curves'!$W$12 + $AR5*'Cancel Curves'!$V$12 + $AS5*'Cancel Curves'!$U$12 + $AT5*'Cancel Curves'!$T$12 + $AU5*'Cancel Curves'!$S$12 + $AV5*'Cancel Curves'!$R$12 + $AW5*'Cancel Curves'!$Q$12 + $AX5*'Cancel Curves'!$P$12 + $AY5*'Cancel Curves'!$O$12 + $AZ5*'Cancel Curves'!$N$12 + $BA5*'Cancel Curves'!$M$12 + $BB5*'Cancel Curves'!$L$12 + $BC5*'Cancel Curves'!$K$12 + $BD5*'Cancel Curves'!$J$12 + $BE5*'Cancel Curves'!$I$12 + $BF5*'Cancel Curves'!$H$12 + $BG5*'Cancel Curves'!$G$12 + $BH5*'Cancel Curves'!$F$12 + $BI5*'Cancel Curves'!$E$12 + $BJ5*'Cancel Curves'!$D$12 + $BK5*'Cancel Curves'!$C$12 + $BL5*'Cancel Curves'!$B$12 | BM6: =$AJ5*'Cancel Curves'!$AE$12 + $AK5*'Cancel Curves'!$AD$12 + $AL5*'Cancel Curves'!$AC$12 + $AM5*'Cancel Curves'!$AB$12 + $AN5*'Cancel Curves'!$AA$12 + $AO5*'Cancel Curves'!$Z$12 + $AP5*'Cancel Curves'!$Y$12 + $AQ5*'Cancel Curves'!$X$12 + $AR5*'Cancel Curves'!$W$12 + $AS5*'Cancel Curves'!$V$12 + $AT5*'Cancel Curves'!$U$12 + $AU5*'Cancel Curves'!$T$12 + $AV5*'Cancel Curves'!$S$12 + $AW5*'Cancel Curves'!$R$12 + $AX5*'Cancel Curves'!$Q$12 + $AY5*'Cancel Curves'!$P$12 + $AZ5*'Cancel Curves'!$O$12 + $BA5*'Cancel Curves'!$N$12 + $BB5*'Cancel Curves'!$M$12 + $BC5*'Cancel Curves'!$L$12 + $BD5*'Cancel Curves'!$K$12 + $BE5*'Cancel Curves'!$J$12 + $BF5*'Cancel Curves'!$I$12 + $BG5*'Cancel Curves'!$H$12 + $BH5*'Cancel Curves'!$G$12 + $BI5*'Cancel Curves'!$F$12 + $BJ5*'Cancel Curves'!$E$12 + $BK5*'Cancel Curves'!$D$12 + $BL5*'Cancel Curves'!$C$12 + $BM5*'Cancel Curves'!$B$12 | BN6: =$AK5*'Cancel Curves'!$AE$12 + $AL5*'Cancel Curves'!$AD$12 + $AM5*'Cancel Curves'!$AC$12 + $AN5*'Cancel Curves'!$AB$12 + $AO5*'Cancel Curves'!$AA$12 + $AP5*'Cancel Curves'!$Z$12 + $AQ5*'Cancel Curves'!$Y$12 + $AR5*'Cancel Curves'!$X$12 + $AS5*'Cancel Curves'!$W$12 + $AT5*'Cancel Curves'!$V$12 + $AU5*'Cancel Curves'!$U$12 + $AV5*'Cancel Curves'!$T$12 + $AW5*'Cancel Curves'!$S$12 + $AX5*'Cancel Curves'!$R$12 + $AY5*'Cancel Curves'!$Q$12 + $AZ5*'Cancel Curves'!$P$12 + $BA5*'Cancel Curves'!$O$12 + $BB5*'Cancel Curves'!$N$12 + $BC5*'Cancel Curves'!$M$12 + $BD5*'Cancel Curves'!$L$12 + $BE5*'Cancel Curves'!$K$12 + $BF5*'Cancel Curves'!$J$12 + $BG5*'Cancel Curves'!$I$12 + $BH5*'Cancel Curves'!$H$12 + $BI5*'Cancel Curves'!$G$12 + $BJ5*'Cancel Curves'!$F$12 + $BK5*'Cancel Curves'!$E$12 + $BL5*'Cancel Curves'!$D$12 + $BM5*'Cancel Curves'!$C$12 + $BN5*'Cancel Curves'!$B$12 | BO6: =$AL5*'Cancel Curves'!$AE$12 + $AM5*'Cancel Curves'!$AD$12 + $AN5*'Cancel Curves'!$AC$12 + $AO5*'Cancel Curves'!$AB$12 + $AP5*'Cancel Curves'!$AA$12 + $AQ5*'Cancel Curves'!$Z$12 + $AR5*'Cancel Curves'!$Y$12 + $AS5*'Cancel Curves'!$X$12 + $AT5*'Cancel Curves'!$W$12 + $AU5*'Cancel Curves'!$V$12 + $AV5*'Cancel Curves'!$U$12 + $AW5*'Cancel Curves'!$T$12 + $AX5*'Cancel Curves'!$S$12 + $AY5*'Cancel Curves'!$R$12 + $AZ5*'Cancel Curves'!$Q$12 + $BA5*'Cancel Curves'!$P$12 + $BB5*'Cancel Curves'!$O$12 + $BC5*'Cancel Curves'!$N$12 + $BD5*'Cancel Curves'!$M$12 + $BE5*'Cancel Curves'!$L$12 + $BF5*'Cancel Curves'!$K$12 + $BG5*'Cancel Curves'!$J$12 + $BH5*'Cancel Curves'!$I$12 + $BI5*'Cancel Curves'!$H$12 + $BJ5*'Cancel Curves'!$G$12 + $BK5*'Cancel Curves'!$F$12 + $BL5*'Cancel Curves'!$E$12 + $BM5*'Cancel Curves'!$D$12 + $BN5*'Cancel Curves'!$C$12 + $BO5*'Cancel Curves'!$B$12 | BP6: =$AM5*'Cancel Curves'!$AE$12 + $AN5*'Cancel Curves'!$AD$12 + $AO5*'Cancel Curves'!$AC$12 + $AP5*'Cancel Curves'!$AB$12 + $AQ5*'Cancel Curves'!$AA$12 + $AR5*'Cancel Curves'!$Z$12 + $AS5*'Cancel Curves'!$Y$12 + $AT5*'Cancel Curves'!$X$12 + $AU5*'Cancel Curves'!$W$12 + $AV5*'Cancel Curves'!$V$12 + $AW5*'Cancel Curves'!$U$12 + $AX5*'Cancel Curves'!$T$12 + $AY5*'Cancel Curves'!$S$12 + $AZ5*'Cancel Curves'!$R$12 + $BA5*'Cancel Curves'!$Q$12 + $BB5*'Cancel Curves'!$P$12 + $BC5*'Cancel Curves'!$O$12 + $BD5*'Cancel Curves'!$N$12 + $BE5*'Cancel Curves'!$M$12 + $BF5*'Cancel Curves'!$L$12 + $BG5*'Cancel Curves'!$K$12 + $BH5*'Cancel Curves'!$J$12 + $BI5*'Cancel Curves'!$I$12 + $BJ5*'Cancel Curves'!$H$12 + $BK5*'Cancel Curves'!$G$12 + $BL5*'Cancel Curves'!$F$12 + $BM5*'Cancel Curves'!$E$12 + $BN5*'Cancel Curves'!$D$12 + $BO5*'Cancel Curves'!$C$12 + $BP5*'Cancel Curves'!$B$12 | BQ6: =$AN5*'Cancel Curves'!$AE$12 + $AO5*'Cancel Curves'!$AD$12 + $AP5*'Cancel Curves'!$AC$12 + $AQ5*'Cancel Curves'!$AB$12 + $AR5*'Cancel Curves'!$AA$12 + $AS5*'Cancel Curves'!$Z$12 + $AT5*'Cancel Curves'!$Y$12 + $AU5*'Cancel Curves'!$X$12 + $AV5*'Cancel Curves'!$W$12 + $AW5*'Cancel Curves'!$V$12 + $AX5*'Cancel Curves'!$U$12 + $AY5*'Cancel Curves'!$T$12 + $AZ5*'Cancel Curves'!$S$12 + $BA5*'Cancel Curves'!$R$12 + $BB5*'Cancel Curves'!$Q$12 + $BC5*'Cancel Curves'!$P$12 + $BD5*'Cancel Curves'!$O$12 + $BE5*'Cancel Curves'!$N$12 + $BF5*'Cancel Curves'!$M$12 + $BG5*'Cancel Curves'!$L$12 + $BH5*'Cancel Curves'!$K$12 + $BI5*'Cancel Curves'!$J$12 + $BJ5*'Cancel Curves'!$I$12 + $BK5*'Cancel Curves'!$H$12 + $BL5*'Cancel Curves'!$G$12 + $BM5*'Cancel Curves'!$F$12 + $BN5*'Cancel Curves'!$E$12 + $BO5*'Cancel Curves'!$D$12 + $BP5*'Cancel Curves'!$C$12 + $BQ5*'Cancel Curves'!$B$12 | BR6: =$AO5*'Cancel Curves'!$AE$12 + $AP5*'Cancel Curves'!$AD$12 + $AQ5*'Cancel Curves'!$AC$12 + $AR5*'Cancel Curves'!$AB$12 + $AS5*'Cancel Curves'!$AA$12 + $AT5*'Cancel Curves'!$Z$12 + $AU5*'Cancel Curves'!$Y$12 + $AV5*'Cancel Curves'!$X$12 + $AW5*'Cancel Curves'!$W$12 + $AX5*'Cancel Curves'!$V$12 + $AY5*'Cancel Curves'!$U$12 + $AZ5*'Cancel Curves'!$T$12 + $BA5*'Cancel Curves'!$S$12 + $BB5*'Cancel Curves'!$R$12 + $BC5*'Cancel Curves'!$Q$12 + $BD5*'Cancel Curves'!$P$12 + $BE5*'Cancel Curves'!$O$12 + $BF5*'Cancel Curves'!$N$12 + $BG5*'Cancel Curves'!$M$12 + $BH5*'Cancel Curves'!$L$12 + $BI5*'Cancel Curves'!$K$12 + $BJ5*'Cancel Curves'!$J$12 + $BK5*'Cancel Curves'!$I$12 + $BL5*'Cancel Curves'!$H$12 + $BM5*'Cancel Curves'!$G$12 + $BN5*'Cancel Curves'!$F$12 + $BO5*'Cancel Curves'!$E$12 + $BP5*'Cancel Curves'!$D$12 + $BQ5*'Cancel Curves'!$C$12 + $BR5*'Cancel Curves'!$B$12 | BS6: =$AP5*'Cancel Curves'!$AE$12 + $AQ5*'Cancel Curves'!$AD$12 + $AR5*'Cancel Curves'!$AC$12 + $AS5*'Cancel Curves'!$AB$12 + $AT5*'Cancel Curves'!$AA$12 + $AU5*'Cancel Curves'!$Z$12 + $AV5*'Cancel Curves'!$Y$12 + $AW5*'Cancel Curves'!$X$12 + $AX5*'Cancel Curves'!$W$12 + $AY5*'Cancel Curves'!$V$12 + $AZ5*'Cancel Curves'!$U$12 + $BA5*'Cancel Curves'!$T$12 + $BB5*'Cancel Curves'!$S$12 + $BC5*'Cancel Curves'!$R$12 + $BD5*'Cancel Curves'!$Q$12 + $BE5*'Cancel Curves'!$P$12 + $BF5*'Cancel Curves'!$O$12 + $BG5*'Cancel Curves'!$N$12 + $BH5*'Cancel Curves'!$M$12 + $BI5*'Cancel Curves'!$L$12 + $BJ5*'Cancel Curves'!$K$12 + $BK5*'Cancel Curves'!$J$12 + $BL5*'Cancel Curves'!$I$12 + $BM5*'Cancel Curves'!$H$12 + $BN5*'Cancel Curves'!$G$12 + $BO5*'Cancel Curves'!$F$12 + $BP5*'Cancel Curves'!$E$12 + $BQ5*'Cancel Curves'!$D$12 + $BR5*'Cancel Curves'!$C$12 + $BS5*'Cancel Curves'!$B$12 | BT6: =$AQ5*'Cancel Curves'!$AE$12 + $AR5*'Cancel Curves'!$AD$12 + $AS5*'Cancel Curves'!$AC$12 + $AT5*'Cancel Curves'!$AB$12 + $AU5*'Cancel Curves'!$AA$12 + $AV5*'Cancel Curves'!$Z$12 + $AW5*'Cancel Curves'!$Y$12 + $AX5*'Cancel Curves'!$X$12 + $AY5*'Cancel Curves'!$W$12 + $AZ5*'Cancel Curves'!$V$12 + $BA5*'Cancel Curves'!$U$12 + $BB5*'Cancel Curves'!$T$12 + $BC5*'Cancel Curves'!$S$12 + $BD5*'Cancel Curves'!$R$12 + $BE5*'Cancel Curves'!$Q$12 + $BF5*'Cancel Curves'!$P$12 + $BG5*'Cancel Curves'!$O$12 + $BH5*'Cancel Curves'!$N$12 + $BI5*'Cancel Curves'!$M$12 + $BJ5*'Cancel Curves'!$L$12 + $BK5*'Cancel Curves'!$K$12 + $BL5*'Cancel Curves'!$J$12 + $BM5*'Cancel Curves'!$I$12 + $BN5*'Cancel Curves'!$H$12 + $BO5*'Cancel Curves'!$G$12 + $BP5*'Cancel Curves'!$F$12 + $BQ5*'Cancel Curves'!$E$12 + $BR5*'Cancel Curves'!$D$12 + $BS5*'Cancel Curves'!$C$12 + $BT5*'Cancel Curves'!$B$12 | BU6: =$AR5*'Cancel Curves'!$AE$12 + $AS5*'Cancel Curves'!$AD$12 + $AT5*'Cancel Curves'!$AC$12 + $AU5*'Cancel Curves'!$AB$12 + $AV5*'Cancel Curves'!$AA$12 + $AW5*'Cancel Curves'!$Z$12 + $AX5*'Cancel Curves'!$Y$12 + $AY5*'Cancel Curves'!$X$12 + $AZ5*'Cancel Curves'!$W$12 + $BA5*'Cancel Curves'!$V$12 + $BB5*'Cancel Curves'!$U$12 + $BC5*'Cancel Curves'!$T$12 + $BD5*'Cancel Curves'!$S$12 + $BE5*'Cancel Curves'!$R$12 + $BF5*'Cancel Curves'!$Q$12 + $BG5*'Cancel Curves'!$P$12 + $BH5*'Cancel Curves'!$O$12 + $BI5*'Cancel Curves'!$N$12 + $BJ5*'Cancel Curves'!$M$12 + $BK5*'Cancel Curves'!$L$12 + $BL5*'Cancel Curves'!$K$12 + $BM5*'Cancel Curves'!$J$12 + $BN5*'Cancel Curves'!$I$12 + $BO5*'Cancel Curves'!$H$12 + $BP5*'Cancel Curves'!$G$12 + $BQ5*'Cancel Curves'!$F$12 + $BR5*'Cancel Curves'!$E$12 + $BS5*'Cancel Curves'!$D$12 + $BT5*'Cancel Curves'!$C$12 + $BU5*'Cancel Curves'!$B$12 | BV6: =$AS5*'Cancel Curves'!$AE$12 + $AT5*'Cancel Curves'!$AD$12 + $AU5*'Cancel Curves'!$AC$12 + $AV5*'Cancel Curves'!$AB$12 + $AW5*'Cancel Curves'!$AA$12 + $AX5*'Cancel Curves'!$Z$12 + $AY5*'Cancel Curves'!$Y$12 + $AZ5*'Cancel Curves'!$X$12 + $BA5*'Cancel Curves'!$W$12 + $BB5*'Cancel Curves'!$V$12 + $BC5*'Cancel Curves'!$U$12 + $BD5*'Cancel Curves'!$T$12 + $BE5*'Cancel Curves'!$S$12 + $BF5*'Cancel Curves'!$R$12 + $BG5*'Cancel Curves'!$Q$12 + $BH5*'Cancel Curves'!$P$12 + $BI5*'Cancel Curves'!$O$12 + $BJ5*'Cancel Curves'!$N$12 + $BK5*'Cancel Curves'!$M$12 + $BL5*'Cancel Curves'!$L$12 + $BM5*'Cancel Curves'!$K$12 + $BN5*'Cancel Curves'!$J$12 + $BO5*'Cancel Curves'!$I$12 + $BP5*'Cancel Curves'!$H$12 + $BQ5*'Cancel Curves'!$G$12 + $BR5*'Cancel Curves'!$F$12 + $BS5*'Cancel Curves'!$E$12 + $BT5*'Cancel Curves'!$D$12 + $BU5*'Cancel Curves'!$C$12 + $BV5*'Cancel Curves'!$B$12 | BW6: =$AT5*'Cancel Curves'!$AE$12 + $AU5*'Cancel Curves'!$AD$12 + $AV5*'Cancel Curves'!$AC$12 + $AW5*'Cancel Curves'!$AB$12 + $AX5*'Cancel Curves'!$AA$12 + $AY5*'Cancel Curves'!$Z$12 + $AZ5*'Cancel Curves'!$Y$12 + $BA5*'Cancel Curves'!$X$12 + $BB5*'Cancel Curves'!$W$12 + $BC5*'Cancel Curves'!$V$12 + $BD5*'Cancel Curves'!$U$12 + $BE5*'Cancel Curves'!$T$12 + $BF5*'Cancel Curves'!$S$12 + $BG5*'Cancel Curves'!$R$12 + $BH5*'Cancel Curves'!$Q$12 + $BI5*'Cancel Curves'!$P$12 + $BJ5*'Cancel Curves'!$O$12 + $BK5*'Cancel Curves'!$N$12 + $BL5*'Cancel Curves'!$M$12 + $BM5*'Cancel Curves'!$L$12 + $BN5*'Cancel Curves'!$K$12 + $BO5*'Cancel Curves'!$J$12 + $BP5*'Cancel Curves'!$I$12 + $BQ5*'Cancel Curves'!$H$12 + $BR5*'Cancel Curves'!$G$12 + $BS5*'Cancel Curves'!$F$12 + $BT5*'Cancel Curves'!$E$12 + $BU5*'Cancel Curves'!$D$12 + $BV5*'Cancel Curves'!$C$12 + $BW5*'Cancel Curves'!$B$12
A7: Active contracts (start of period) | C7: 0
A8: Cancels (period) | D8: =C6+D5-D6 | E8: =D6+E5-E6 | F8: =E6+F5-F6 | G8: =F6+G5-G6 | H8: =G6+H5-H6 | I8: =H6+I5-I6 | J8: =I6+J5-J6 | K8: =J6+K5-K6 | ... BW8: =BV6+BW5-BW6
A10: REVENUE
A11: Monthly contract value (active × CPS)
A12: CPS (customer payment per service) | D12: =Assumptions!$B$17*(1+Assumptions!$B$9)^0 | E12: =Assumptions!$B$17*(1+Assumptions!$B$9)^0 | F12: =Assumptions!$B$17*(1+Assumptions!$B$9)^0 | G12: =Assumptions!$B$17*(1+Assumptions!$B$9)^0 | H12: =Assumptions!$B$17*(1+Assumptions!$B$9)^0 | I12: =Assumptions!$B$17*(1+Assumptions!$B$9)^0 | J12: =Assumptions!$B$17*(1+Assumptions!$B$9)^0 | K12: =Assumptions!$B$17*(1+Assumptions!$B$9)^0 | ... O12: =Assumptions!$B$17*(1+Assumptions!$B$9)^0 | P12: =Assumptions!$B$17*(1+Assumptions!$B$9)^1 | Q12: =Assumptions!$B$17*(1+Assumptions!$B$9)^1 | R12: =Assumptions!$B$17*(1+Assumptions!$B$9)^1 | S12: =Assumptions!$B$17*(1+Assumptions!$B$9)^1 | T12: =Assumptions!$B$17*(1+Assumptions!$B$9)^1 | U12: =Assumptions!$B$17*(1+Assumptions!$B$9)^1 | V12: =Assumptions!$B$17*(1+Assumptions!$B$9)^1 | W12: =Assumptions!$B$17*(1+Assumptions!$B$9)^1 | ... AA12: =Assumptions!$B$17*(1+Assumptions!$B$9)^1 | AB12: =Assumptions!$B$17*(1+Assumptions!$B$9)^2 | AC12: =Assumptions!$B$17*(1+Assumptions!$B$9)^2 | AD12: =Assumptions!$B$17*(1+Assumptions!$B$9)^2 | AE12: =Assumptions!$B$17*(1+Assumptions!$B$9)^2 | AF12: =Assumptions!$B$17*(1+Assumptions!$B$9)^2 | AG12: =Assumptions!$B$17*(1+Assumptions!$B$9)^2 | AH12: =Assumptions!$B$17*(1+Assumptions!$B$9)^2 | AI12: =Assumptions!$B$17*(1+Assumptions!$B$9)^2 | ... AM12: =Assumptions!$B$17*(1+Assumptions!$B$9)^2 | AN12: =Assumptions!$B$17*(1+Assumptions!$B$9)^3 | AO12: =Assumptions!$B$17*(1+Assumptions!$B$9)^3 | AP12: =Assumptions!$B$17*(1+Assumptions!$B$9)^3 | AQ12: =Assumptions!$B$17*(1+Assumptions!$B$9)^3 | AR12: =Assumptions!$B$17*(1+Assumptions!$B$9)^3 | AS12: =Assumptions!$B$17*(1+Assumptions!$B$9)^3 | AT12: =Assumptions!$B$17*(1+Assumptions!$B$9)^3 | AU12: =Assumptions!$B$17*(1+Assumptions!$B$9)^3 | ... AY12: =Assumptions!$B$17*(1+Assumptions!$B$9)^3 | AZ12: =Assumptions!$B$17*(1+Assumptions!$B$9)^4 | BA12: =Assumptions!$B$17*(1+Assumptions!$B$9)^4 | BB12: =Assumptions!$B$17*(1+Assumptions!$B$9)^4 | BC12: =Assumptions!$B$17*(1+Assumptions!$B$9)^4 | BD12: =Assumptions!$B$17*(1+Assumptions!$B$9)^4 | BE12: =Assumptions!$B$17*(1+Assumptions!$B$9)^4 | BF12: =Assumptions!$B$17*(1+Assumptions!$B$9)^4 | BG12: =Assumptions!$B$17*(1+Assumptions!$B$9)^4 | ... BK12: =Assumptions!$B$17*(1+Assumptions!$B$9)^4 | BL12: =Assumptions!$B$17*(1+Assumptions!$B$9)^5 | BM12: =Assumptions!$B$17*(1+Assumptions!$B$9)^5 | BN12: =Assumptions!$B$17*(1+Assumptions!$B$9)^5 | BO12: =Assumptions!$B$17*(1+Assumptions!$B$9)^5 | BP12: =Assumptions!$B$17*(1+Assumptions!$B$9)^5 | BQ12: =Assumptions!$B$17*(1+Assumptions!$B$9)^5 | BR12: =Assumptions!$B$17*(1+Assumptions!$B$9)^5 | BS12: =Assumptions!$B$17*(1+Assumptions!$B$9)^5 | ... BW12: =Assumptions!$B$17*(1+Assumptions!$B$9)^5
A13: Subscription revenue (CPS + IAA amort.) | D13: =D6*D12 + ($D$5*'Cancel Curves'!$B$12 + 58*'Cancel Curves'!$M$12 + 169*'Cancel Curves'!$L$12 + 264*'Cancel Curves'!$K$12 + 287*'Cancel Curves'!$J$12 + 306*'Cancel Curves'!$I$12 + 296*'Cancel Curves'!$H$12 + 265*'Cancel Curves'!$G$12 + 350*'Cancel Curves'!$F$12 + 554*'Cancel Curves'!$E$12 + 555*'Cancel Curves'!$D$12 + 555*'Cancel Curves'!$C$12)*Assumptions!$B$76 | E13: =E6*E12 + ($D$5*'Cancel Curves'!$C$12 + $E$5*'Cancel Curves'!$B$12 + 169*'Cancel Curves'!$M$12 + 264*'Cancel Curves'!$L$12 + 287*'Cancel Curves'!$K$12 + 306*'Cancel Curves'!$J$12 + 296*'Cancel Curves'!$I$12 + 265*'Cancel Curves'!$H$12 + 350*'Cancel Curves'!$G$12 + 554*'Cancel Curves'!$F$12 + 555*'Cancel Curves'!$E$12 + 555*'Cancel Curves'!$D$12)*Assumptions!$B$76 | F13: =F6*F12 + ($D$5*'Cancel Curves'!$D$12 + $E$5*'Cancel Curves'!$C$12 + $F$5*'Cancel Curves'!$B$12 + 264*'Cancel Curves'!$M$12 + 287*'Cancel Curves'!$L$12 + 306*'Cancel Curves'!$K$12 + 296*'Cancel Curves'!$J$12 + 265*'Cancel Curves'!$I$12 + 350*'Cancel Curves'!$H$12 + 554*'Cancel Curves'!$G$12 + 555*'Cancel Curves'!$F$12 + 555*'Cancel Curves'!$E$12)*Assumptions!$B$76 | G13: =G6*G12 + ($D$5*'Cancel Curves'!$E$12 + $E$5*'Cancel Curves'!$D$12 + $F$5*'Cancel Curves'!$C$12 + $G$5*'Cancel Curves'!$B$12 + 287*'Cancel Curves'!$M$12 + 306*'Cancel Curves'!$L$12 + 296*'Cancel Curves'!$K$12 + 265*'Cancel Curves'!$J$12 + 350*'Cancel Curves'!$I$12 + 554*'Cancel Curves'!$H$12 + 555*'Cancel Curves'!$G$12 + 555*'Cancel Curves'!$F$12)*Assumptions!$B$76 | H13: =H6*H12 + ($D$5*'Cancel Curves'!$F$12 + $E$5*'Cancel Curves'!$E$12 + $F$5*'Cancel Curves'!$D$12 + $G$5*'Cancel Curves'!$C$12 + $H$5*'Cancel Curves'!$B$12 + 306*'Cancel Curves'!$M$12 + 296*'Cancel Curves'!$L$12 + 265*'Cancel Curves'!$K$12 + 350*'Cancel Curves'!$J$12 + 554*'Cancel Curves'!$I$12 + 555*'Cancel Curves'!$H$12 + 555*'Cancel Curves'!$G$12)*Assumptions!$B$76 | I13: =I6*I12 + ($D$5*'Cancel Curves'!$G$12 + $E$5*'Cancel Curves'!$F$12 + $F$5*'Cancel Curves'!$E$12 + $G$5*'Cancel Curves'!$D$12 + $H$5*'Cancel Curves'!$C$12 + $I$5*'Cancel Curves'!$B$12 + 296*'Cancel Curves'!$M$12 + 265*'Cancel Curves'!$L$12 + 350*'Cancel Curves'!$K$12 + 554*'Cancel Curves'!$J$12 + 555*'Cancel Curves'!$I$12 + 555*'Cancel Curves'!$H$12)*Assumptions!$B$76 | J13: =J6*J12 + ($D$5*'Cancel Curves'!$H$12 + $E$5*'Cancel Curves'!$G$12 + $F$5*'Cancel Curves'!$F$12 + $G$5*'Cancel Curves'!$E$12 + $H$5*'Cancel Curves'!$D$12 + $I$5*'Cancel Curves'!$C$12 + $J$5*'Cancel Curves'!$B$12 + 265*'Cancel Curves'!$M$12 + 350*'Cancel Curves'!$L$12 + 554*'Cancel Curves'!$K$12 + 555*'Cancel Curves'!$J$12 + 555*'Cancel Curves'!$I$12)*Assumptions!$B$76 | K13: =K6*K12 + ($D$5*'Cancel Curves'!$I$12 + $E$5*'Cancel Curves'!$H$12 + $F$5*'Cancel Curves'!$G$12 + $G$5*'Cancel Curves'!$F$12 + $H$5*'Cancel Curves'!$E$12 + $I$5*'Cancel Curves'!$D$12 + $J$5*'Cancel Curves'!$C$12 + $K$5*'Cancel Curves'!$B$12 + 350*'Cancel Curves'!$M$12 + 554*'Cancel Curves'!$L$12 + 555*'Cancel Curves'!$K$12 + 555*'Cancel Curves'!$J$12)*Assumptions!$B$76 | L13: =L6*L12 + ($D$5*'Cancel Curves'!$J$12 + $E$5*'Cancel Curves'!$I$12 + $F$5*'Cancel Curves'!$H$12 + $G$5*'Cancel Curves'!$G$12 + $H$5*'Cancel Curves'!$F$12 + $I$5*'Cancel Curves'!$E$12 + $J$5*'Cancel Curves'!$D$12 + $K$5*'Cancel Curves'!$C$12 + $L$5*'Cancel Curves'!$B$12 + 554*'Cancel Curves'!$M$12 + 555*'Cancel Curves'!$L$12 + 555*'Cancel Curves'!$K$12)*Assumptions!$B$76 | M13: =M6*M12 + ($D$5*'Cancel Curves'!$K$12 + $E$5*'Cancel Curves'!$J$12 + $F$5*'Cancel Curves'!$I$12 + $G$5*'Cancel Curves'!$H$12 + $H$5*'Cancel Curves'!$G$12 + $I$5*'Cancel Curves'!$F$12 + $J$5*'Cancel Curves'!$E$12 + $K$5*'Cancel Curves'!$D$12 + $L$5*'Cancel Curves'!$C$12 + $M$5*'Cancel Curves'!$B$12 + 555*'Cancel Curves'!$M$12 + 555*'Cancel Curves'!$L$12)*Assumptions!$B$76 | N13: =N6*N12 + ($D$5*'Cancel Curves'!$L$12 + $E$5*'Cancel Curves'!$K$12 + $F$5*'Cancel Curves'!$J$12 + $G$5*'Cancel Curves'!$I$12 + $H$5*'Cancel Curves'!$H$12 + $I$5*'Cancel Curves'!$G$12 + $J$5*'Cancel Curves'!$F$12 + $K$5*'Cancel Curves'!$E$12 + $L$5*'Cancel Curves'!$D$12 + $M$5*'Cancel Curves'!$C$12 + $N$5*'Cancel Curves'!$B$12 + 555*'Cancel Curves'!$M$12)*Assumptions!$B$76 | O13: =O6*O12 + ($D$5*'Cancel Curves'!$M$12 + $E$5*'Cancel Curves'!$L$12 + $F$5*'Cancel Curves'!$K$12 + $G$5*'Cancel Curves'!$J$12 + $H$5*'Cancel Curves'!$I$12 + $I$5*'Cancel Curves'!$H$12 + $J$5*'Cancel Curves'!$G$12 + $K$5*'Cancel Curves'!$F$12 + $L$5*'Cancel Curves'!$E$12 + $M$5*'Cancel Curves'!$D$12 + $N$5*'Cancel Curves'!$C$12 + $O$5*'Cancel Curves'!$B$12)*Assumptions!$B$76 | P13: =P6*P12 + ($E$5*'Cancel Curves'!$M$12 + $F$5*'Cancel Curves'!$L$12 + $G$5*'Cancel Curves'!$K$12 + $H$5*'Cancel Curves'!$J$12 + $I$5*'Cancel Curves'!$I$12 + $J$5*'Cancel Curves'!$H$12 + $K$5*'Cancel Curves'!$G$12 + $L$5*'Cancel Curves'!$F$12 + $M$5*'Cancel Curves'!$E$12 + $N$5*'Cancel Curves'!$D$12 + $O$5*'Cancel Curves'!$C$12 + $P$5*'Cancel Curves'!$B$12)*Assumptions!$B$76 | Q13: =Q6*Q12 + ($F$5*'Cancel Curves'!$M$12 + $G$5*'Cancel Curves'!$L$12 + $H$5*'Cancel Curves'!$K$12 + $I$5*'Cancel Curves'!$J$12 + $J$5*'Cancel Curves'!$I$12 + $K$5*'Cancel Curves'!$H$12 + $L$5*'Cancel Curves'!$G$12 + $M$5*'Cancel Curves'!$F$12 + $N$5*'Cancel Curves'!$E$12 + $O$5*'Cancel Curves'!$D$12 + $P$5*'Cancel Curves'!$C$12 + $Q$5*'Cancel Curves'!$B$12)*Assumptions!$B$76 | R13: =R6*R12 + ($G$5*'Cancel Curves'!$M$12 + $H$5*'Cancel Curves'!$L$12 + $I$5*'Cancel Curves'!$K$12 + $J$5*'Cancel Curves'!$J$12 + $K$5*'Cancel Curves'!$I$12 + $L$5*'Cancel Curves'!$H$12 + $M$5*'Cancel Curves'!$G$12 + $N$5*'Cancel Curves'!$F$12 + $O$5*'Cancel Curves'!$E$12 + $P$5*'Cancel Curves'!$D$12 + $Q$5*'Cancel Curves'!$C$12 + $R$5*'Cancel Curves'!$B$12)*Assumptions!$B$76 | S13: =S6*S12 + ($H$5*'Cancel Curves'!$M$12 + $I$5*'Cancel Curves'!$L$12 + $J$5*'Cancel Curves'!$K$12 + $K$5*'Cancel Curves'!$J$12 + $L$5*'Cancel Curves'!$I$12 + $M$5*'Cancel Curves'!$H$12 + $N$5*'Cancel Curves'!$G$12 + $O$5*'Cancel Curves'!$F$12 + $P$5*'Cancel Curves'!$E$12 + $Q$5*'Cancel Curves'!$D$12 + $R$5*'Cancel Curves'!$C$12 + $S$5*'Cancel Curves'!$B$12)*Assumptions!$B$76 | T13: =T6*T12 + ($I$5*'Cancel Curves'!$M$12 + $J$5*'Cancel Curves'!$L$12 + $K$5*'Cancel Curves'!$K$12 + $L$5*'Cancel Curves'!$J$12 + $M$5*'Cancel Curves'!$I$12 + $N$5*'Cancel Curves'!$H$12 + $O$5*'Cancel Curves'!$G$12 + $P$5*'Cancel Curves'!$F$12 + $Q$5*'Cancel Curves'!$E$12 + $R$5*'Cancel Curves'!$D$12 + $S$5*'Cancel Curves'!$C$12 + $T$5*'Cancel Curves'!$B$12)*Assumptions!$B$76 | U13: =U6*U12 + ($J$5*'Cancel Curves'!$M$12 + $K$5*'Cancel Curves'!$L$12 + $L$5*'Cancel Curves'!$K$12 + $M$5*'Cancel Curves'!$J$12 + $N$5*'Cancel Curves'!$I$12 + $O$5*'Cancel Curves'!$H$12 + $P$5*'Cancel Curves'!$G$12 + $Q$5*'Cancel Curves'!$F$12 + $R$5*'Cancel Curves'!$E$12 + $S$5*'Cancel Curves'!$D$12 + $T$5*'Cancel Curves'!$C$12 + $U$5*'Cancel Curves'!$B$12)*Assumptions!$B$76 | V13: =V6*V12 + ($K$5*'Cancel Curves'!$M$12 + $L$5*'Cancel Curves'!$L$12 + $M$5*'Cancel Curves'!$K$12 + $N$5*'Cancel Curves'!$J$12 + $O$5*'Cancel Curves'!$I$12 + $P$5*'Cancel Curves'!$H$12 + $Q$5*'Cancel Curves'!$G$12 + $R$5*'Cancel Curves'!$F$12 + $S$5*'Cancel Curves'!$E$12 + $T$5*'Cancel Curves'!$D$12 + $U$5*'Cancel Curves'!$C$12 + $V$5*'Cancel Curves'!$B$12)*Assumptions!$B$76 | W13: =W6*W12 + ($L$5*'Cancel Curves'!$M$12 + $M$5*'Cancel Curves'!$L$12 + $N$5*'Cancel Curves'!$K$12 + $O$5*'Cancel Curves'!$J$12 + $P$5*'Cancel Curves'!$I$12 + $Q$5*'Cancel Curves'!$H$12 + $R$5*'Cancel Curves'!$G$12 + $S$5*'Cancel Curves'!$F$12 + $T$5*'Cancel Curves'!$E$12 + $U$5*'Cancel Curves'!$D$12 + $V$5*'Cancel Curves'!$C$12 + $W$5*'Cancel Curves'!$B$12)*Assumptions!$B$76 | X13: =X6*X12 + ($M$5*'Cancel Curves'!$M$12 + $N$5*'Cancel Curves'!$L$12 + $O$5*'Cancel Curves'!$K$12 + $P$5*'Cancel Curves'!$J$12 + $Q$5*'Cancel Curves'!$I$12 + $R$5*'Cancel Curves'!$H$12 + $S$5*'Cancel Curves'!$G$12 + $T$5*'Cancel Curves'!$F$12 + $U$5*'Cancel Curves'!$E$12 + $V$5*'Cancel Curves'!$D$12 + $W$5*'Cancel Curves'!$C$12 + $X$5*'Cancel Curves'!$B$12)*Assumptions!$B$76 | Y13: =Y6*Y12 + ($N$5*'Cancel Curves'!$M$12 + $O$5*'Cancel Curves'!$L$12 + $P$5*'Cancel Curves'!$K$12 + $Q$5*'Cancel Curves'!$J$12 + $R$5*'Cancel Curves'!$I$12 + $S$5*'Cancel Curves'!$H$12 + $T$5*'Cancel Curves'!$G$12 + $U$5*'Cancel Curves'!$F$12 + $V$5*'Cancel Curves'!$E$12 + $W$5*'Cancel Curves'!$D$12 + $X$5*'Cancel Curves'!$C$12 + $Y$5*'Cancel Curves'!$B$12)*Assumptions!$B$76 | Z13: =Z6*Z12 + ($O$5*'Cancel Curves'!$M$12 + $P$5*'Cancel Curves'!$L$12 + $Q$5*'Cancel Curves'!$K$12 + $R$5*'Cancel Curves'!$J$12 + $S$5*'Cancel Curves'!$I$12 + $T$5*'Cancel Curves'!$H$12 + $U$5*'Cancel Curves'!$G$12 + $V$5*'Cancel Curves'!$F$12 + $W$5*'Cancel Curves'!$E$12 + $X$5*'Cancel Curves'!$D$12 + $Y$5*'Cancel Curves'!$C$12 + $Z$5*'Cancel Curves'!$B$12)*Assumptions!$B$76 | AA13: =AA6*AA12 + ($P$5*'Cancel Curves'!$M$12 + $Q$5*'Cancel Curves'!$L$12 + $R$5*'Cancel Curves'!$K$12 + $S$5*'Cancel Curves'!$J$12 + $T$5*'Cancel Curves'!$I$12 + $U$5*'Cancel Curves'!$H$12 + $V$5*'Cancel Curves'!$G$12 + $W$5*'Cancel Curves'!$F$12 + $X$5*'Cancel Curves'!$E$12 + $Y$5*'Cancel Curves'!$D$12 + $Z$5*'Cancel Curves'!$C$12 + $AA$5*'Cancel Curves'!$B$12)*Assumptions!$B$76 | AB13: =AB6*AB12 + ($Q$5*'Cancel Curves'!$M$12 + $R$5*'Cancel Curves'!$L$12 + $S$5*'Cancel Curves'!$K$12 + $T$5*'Cancel Curves'!$J$12 + $U$5*'Cancel Curves'!$I$12 + $V$5*'Cancel Curves'!$H$12 + $W$5*'Cancel Curves'!$G$12 + $X$5*'Cancel Curves'!$F$12 + $Y$5*'Cancel Curves'!$E$12 + $Z$5*'Cancel Curves'!$D$12 + $AA$5*'Cancel Curves'!$C$12 + $AB$5*'Cancel Curves'!$B$12)*Assumptions!$B$76 | AC13: =AC6*AC12 + ($R$5*'Cancel Curves'!$M$12 + $S$5*'Cancel Curves'!$L$12 + $T$5*'Cancel Curves'!$K$12 + $U$5*'Cancel Curves'!$J$12 + $V$5*'Cancel Curves'!$I$12 + $W$5*'Cancel Curves'!$H$12 + $X$5*'Cancel Curves'!$G$12 + $Y$5*'Cancel Curves'!$F$12 + $Z$5*'Cancel Curves'!$E$12 + $AA$5*'Cancel Curves'!$D$12 + $AB$5*'Cancel Curves'!$C$12 + $AC$5*'Cancel Curves'!$B$12)*Assumptions!$B$76 | AD13: =AD6*AD12 + ($S$5*'Cancel Curves'!$M$12 + $T$5*'Cancel Curves'!$L$12 + $U$5*'Cancel Curves'!$K$12 + $V$5*'Cancel Curves'!$J$12 + $W$5*'Cancel Curves'!$I$12 + $X$5*'Cancel Curves'!$H$12 + $Y$5*'Cancel Curves'!$G$12 + $Z$5*'Cancel Curves'!$F$12 + $AA$5*'Cancel Curves'!$E$12 + $AB$5*'Cancel Curves'!$D$12 + $AC$5*'Cancel Curves'!$C$12 + $AD$5*'Cancel Curves'!$B$12)*Assumptions!$B$76 | AE13: =AE6*AE12 + ($T$5*'Cancel Curves'!$M$12 + $U$5*'Cancel Curves'!$L$12 + $V$5*'Cancel Curves'!$K$12 + $W$5*'Cancel Curves'!$J$12 + $X$5*'Cancel Curves'!$I$12 + $Y$5*'Cancel Curves'!$H$12 + $Z$5*'Cancel Curves'!$G$12 + $AA$5*'Cancel Curves'!$F$12 + $AB$5*'Cancel Curves'!$E$12 + $AC$5*'Cancel Curves'!$D$12 + $AD$5*'Cancel Curves'!$C$12 + $AE$5*'Cancel Curves'!$B$12)*Assumptions!$B$76 | AF13: =AF6*AF12 + ($U$5*'Cancel Curves'!$M$12 + $V$5*'Cancel Curves'!$L$12 + $W$5*'Cancel Curves'!$K$12 + $X$5*'Cancel Curves'!$J$12 + $Y$5*'Cancel Curves'!$I$12 + $Z$5*'Cancel Curves'!$H$12 + $AA$5*'Cancel Curves'!$G$12 + $AB$5*'Cancel Curves'!$F$12 + $AC$5*'Cancel Curves'!$E$12 + $AD$5*'Cancel Curves'!$D$12 + $AE$5*'Cancel Curves'!$C$12 + $AF$5*'Cancel Curves'!$B$12)*Assumptions!$B$76 | AG13: =AG6*AG12 + ($V$5*'Cancel Curves'!$M$12 + $W$5*'Cancel Curves'!$L$12 + $X$5*'Cancel Curves'!$K$12 + $Y$5*'Cancel Curves'!$J$12 + $Z$5*'Cancel Curves'!$I$12 + $AA$5*'Cancel Curves'!$H$12 + $AB$5*'Cancel Curves'!$G$12 + $AC$5*'Cancel Curves'!$F$12 + $AD$5*'Cancel Curves'!$E$12 + $AE$5*'Cancel Curves'!$D$12 + $AF$5*'Cancel Curves'!$C$12 + $AG$5*'Cancel Curves'!$B$12)*Assumptions!$B$76 | AH13: =AH6*AH12 + ($W$5*'Cancel Curves'!$M$12 + $X$5*'Cancel Curves'!$L$12 + $Y$5*'Cancel Curves'!$K$12 + $Z$5*'Cancel Curves'!$J$12 + $AA$5*'Cancel Curves'!$I$12 + $AB$5*'Cancel Curves'!$H$12 + $AC$5*'Cancel Curves'!$G$12 + $AD$5*'Cancel Curves'!$F$12 + $AE$5*'Cancel Curves'!$E$12 + $AF$5*'Cancel Curves'!$D$12 + $AG$5*'Cancel Curves'!$C$12 + $AH$5*'Cancel Curves'!$B$12)*Assumptions!$B$76 | AI13: =AI6*AI12 + ($X$5*'Cancel Curves'!$M$12 + $Y$5*'Cancel Curves'!$L$12 + $Z$5*'Cancel Curves'!$K$12 + $AA$5*'Cancel Curves'!$J$12 + $AB$5*'Cancel Curves'!$I$12 + $AC$5*'Cancel Curves'!$H$12 + $AD$5*'Cancel Curves'!$G$12 + $AE$5*'Cancel Curves'!$F$12 + $AF$5*'Cancel Curves'!$E$12 + $AG$5*'Cancel Curves'!$D$12 + $AH$5*'Cancel Curves'!$C$12 + $AI$5*'Cancel Curves'!$B$12)*Assumptions!$B$76 | AJ13: =AJ6*AJ12 + ($Y$5*'Cancel Curves'!$M$12 + $Z$5*'Cancel Curves'!$L$12 + $AA$5*'Cancel Curves'!$K$12 + $AB$5*'Cancel Curves'!$J$12 + $AC$5*'Cancel Curves'!$I$12 + $AD$5*'Cancel Curves'!$H$12 + $AE$5*'Cancel Curves'!$G$12 + $AF$5*'Cancel Curves'!$F$12 + $AG$5*'Cancel Curves'!$E$12 + $AH$5*'Cancel Curves'!$D$12 + $AI$5*'Cancel Curves'!$C$12 + $AJ$5*'Cancel Curves'!$B$12)*Assumptions!$B$76 | AK13: =AK6*AK12 + ($Z$5*'Cancel Curves'!$M$12 + $AA$5*'Cancel Curves'!$L$12 + $AB$5*'Cancel Curves'!$K$12 + $AC$5*'Cancel Curves'!$J$12 + $AD$5*'Cancel Curves'!$I$12 + $AE$5*'Cancel Curves'!$H$12 + $AF$5*'Cancel Curves'!$G$12 + $AG$5*'Cancel Curves'!$F$12 + $AH$5*'Cancel Curves'!$E$12 + $AI$5*'Cancel Curves'!$D$12 + $AJ$5*'Cancel Curves'!$C$12 + $AK$5*'Cancel Curves'!$B$12)*Assumptions!$B$76 | AL13: =AL6*AL12 + ($AA$5*'Cancel Curves'!$M$12 + $AB$5*'Cancel Curves'!$L$12 + $AC$5*'Cancel Curves'!$K$12 + $AD$5*'Cancel Curves'!$J$12 + $AE$5*'Cancel Curves'!$I$12 + $AF$5*'Cancel Curves'!$H$12 + $AG$5*'Cancel Curves'!$G$12 + $AH$5*'Cancel Curves'!$F$12 + $AI$5*'Cancel Curves'!$E$12 + $AJ$5*'Cancel Curves'!$D$12 + $AK$5*'Cancel Curves'!$C$12 + $AL$5*'Cancel Curves'!$B$12)*Assumptions!$B$76 | AM13: =AM6*AM12 + ($AB$5*'Cancel Curves'!$M$12 + $AC$5*'Cancel Curves'!$L$12 + $AD$5*'Cancel Curves'!$K$12 + $AE$5*'Cancel Curves'!$J$12 + $AF$5*'Cancel Curves'!$I$12 + $AG$5*'Cancel Curves'!$H$12 + $AH$5*'Cancel Curves'!$G$12 + $AI$5*'Cancel Curves'!$F$12 + $AJ$5*'Cancel Curves'!$E$12 + $AK$5*'Cancel Curves'!$D$12 + $AL$5*'Cancel Curves'!$C$12 + $AM$5*'Cancel Curves'!$B$12)*Assumptions!$B$76 | AN13: =AN6*AN12 + ($AC$5*'Cancel Curves'!$M$12 + $AD$5*'Cancel Curves'!$L$12 + $AE$5*'Cancel Curves'!$K$12 + $AF$5*'Cancel Curves'!$J$12 + $AG$5*'Cancel Curves'!$I$12 + $AH$5*'Cancel Curves'!$H$12 + $AI$5*'Cancel Curves'!$G$12 + $AJ$5*'Cancel Curves'!$F$12 + $AK$5*'Cancel Curves'!$E$12 + $AL$5*'Cancel Curves'!$D$12 + $AM$5*'Cancel Curves'!$C$12 + $AN$5*'Cancel Curves'!$B$12)*Assumptions!$B$76 | AO13: =AO6*AO12 + ($AD$5*'Cancel Curves'!$M$12 + $AE$5*'Cancel Curves'!$L$12 + $AF$5*'Cancel Curves'!$K$12 + $AG$5*'Cancel Curves'!$J$12 + $AH$5*'Cancel Curves'!$I$12 + $AI$5*'Cancel Curves'!$H$12 + $AJ$5*'Cancel Curves'!$G$12 + $AK$5*'Cancel Curves'!$F$12 + $AL$5*'Cancel Curves'!$E$12 + $AM$5*'Cancel Curves'!$D$12 + $AN$5*'Cancel Curves'!$C$12 + $AO$5*'Cancel Curves'!$B$12)*Assumptions!$B$76 | AP13: =AP6*AP12 + ($AE$5*'Cancel Curves'!$M$12 + $AF$5*'Cancel Curves'!$L$12 + $AG$5*'Cancel Curves'!$K$12 + $AH$5*'Cancel Curves'!$J$12 + $AI$5*'Cancel Curves'!$I$12 + $AJ$5*'Cancel Curves'!$H$12 + $AK$5*'Cancel Curves'!$G$12 + $AL$5*'Cancel Curves'!$F$12 + $AM$5*'Cancel Curves'!$E$12 + $AN$5*'Cancel Curves'!$D$12 + $AO$5*'Cancel Curves'!$C$12 + $AP$5*'Cancel Curves'!$B$12)*Assumptions!$B$76 | AQ13: =AQ6*AQ12 + ($AF$5*'Cancel Curves'!$M$12 + $AG$5*'Cancel Curves'!$L$12 + $AH$5*'Cancel Curves'!$K$12 + $AI$5*'Cancel Curves'!$J$12 + $AJ$5*'Cancel Curves'!$I$12 + $AK$5*'Cancel Curves'!$H$12 + $AL$5*'Cancel Curves'!$G$12 + $AM$5*'Cancel Curves'!$F$12 + $AN$5*'Cancel Curves'!$E$12 + $AO$5*'Cancel Curves'!$D$12 + $AP$5*'Cancel Curves'!$C$12 + $AQ$5*'Cancel Curves'!$B$12)*Assumptions!$B$76 | AR13: =AR6*AR12 + ($AG$5*'Cancel Curves'!$M$12 + $AH$5*'Cancel Curves'!$L$12 + $AI$5*'Cancel Curves'!$K$12 + $AJ$5*'Cancel Curves'!$J$12 + $AK$5*'Cancel Curves'!$I$12 + $AL$5*'Cancel Curves'!$H$12 + $AM$5*'Cancel Curves'!$G$12 + $AN$5*'Cancel Curves'!$F$12 + $AO$5*'Cancel Curves'!$E$12 + $AP$5*'Cancel Curves'!$D$12 + $AQ$5*'Cancel Curves'!$C$12 + $AR$5*'Cancel Curves'!$B$12)*Assumptions!$B$76 | AS13: =AS6*AS12 + ($AH$5*'Cancel Curves'!$M$12 + $AI$5*'Cancel Curves'!$L$12 + $AJ$5*'Cancel Curves'!$K$12 + $AK$5*'Cancel Curves'!$J$12 + $AL$5*'Cancel Curves'!$I$12 + $AM$5*'Cancel Curves'!$H$12 + $AN$5*'Cancel Curves'!$G$12 + $AO$5*'Cancel Curves'!$F$12 + $AP$5*'Cancel Curves'!$E$12 + $AQ$5*'Cancel Curves'!$D$12 + $AR$5*'Cancel Curves'!$C$12 + $AS$5*'Cancel Curves'!$B$12)*Assumptions!$B$76 | AT13: =AT6*AT12 + ($AI$5*'Cancel Curves'!$M$12 + $AJ$5*'Cancel Curves'!$L$12 + $AK$5*'Cancel Curves'!$K$12 + $AL$5*'Cancel Curves'!$J$12 + $AM$5*'Cancel Curves'!$I$12 + $AN$5*'Cancel Curves'!$H$12 + $AO$5*'Cancel Curves'!$G$12 + $AP$5*'Cancel Curves'!$F$12 + $AQ$5*'Cancel Curves'!$E$12 + $AR$5*'Cancel Curves'!$D$12 + $AS$5*'Cancel Curves'!$C$12 + $AT$5*'Cancel Curves'!$B$12)*Assumptions!$B$76 | AU13: =AU6*AU12 + ($AJ$5*'Cancel Curves'!$M$12 + $AK$5*'Cancel Curves'!$L$12 + $AL$5*'Cancel Curves'!$K$12 + $AM$5*'Cancel Curves'!$J$12 + $AN$5*'Cancel Curves'!$I$12 + $AO$5*'Cancel Curves'!$H$12 + $AP$5*'Cancel Curves'!$G$12 + $AQ$5*'Cancel Curves'!$F$12 + $AR$5*'Cancel Curves'!$E$12 + $AS$5*'Cancel Curves'!$D$12 + $AT$5*'Cancel Curves'!$C$12 + $AU$5*'Cancel Curves'!$B$12)*Assumptions!$B$76 | AV13: =AV6*AV12 + ($AK$5*'Cancel Curves'!$M$12 + $AL$5*'Cancel Curves'!$L$12 + $AM$5*'Cancel Curves'!$K$12 + $AN$5*'Cancel Curves'!$J$12 + $AO$5*'Cancel Curves'!$I$12 + $AP$5*'Cancel Curves'!$H$12 + $AQ$5*'Cancel Curves'!$G$12 + $AR$5*'Cancel Curves'!$F$12 + $AS$5*'Cancel Curves'!$E$12 + $AT$5*'Cancel Curves'!$D$12 + $AU$5*'Cancel Curves'!$C$12 + $AV$5*'Cancel Curves'!$B$12)*Assumptions!$B$76 | AW13: =AW6*AW12 + ($AL$5*'Cancel Curves'!$M$12 + $AM$5*'Cancel Curves'!$L$12 + $AN$5*'Cancel Curves'!$K$12 + $AO$5*'Cancel Curves'!$J$12 + $AP$5*'Cancel Curves'!$I$12 + $AQ$5*'Cancel Curves'!$H$12 + $AR$5*'Cancel Curves'!$G$12 + $AS$5*'Cancel Curves'!$F$12 + $AT$5*'Cancel Curves'!$E$12 + $AU$5*'Cancel Curves'!$D$12 + $AV$5*'Cancel Curves'!$C$12 + $AW$5*'Cancel Curves'!$B$12)*Assumptions!$B$76 | AX13: =AX6*AX12 + ($AM$5*'Cancel Curves'!$M$12 + $AN$5*'Cancel Curves'!$L$12 + $AO$5*'Cancel Curves'!$K$12 + $AP$5*'Cancel Curves'!$J$12 + $AQ$5*'Cancel Curves'!$I$12 + $AR$5*'Cancel Curves'!$H$12 + $AS$5*'Cancel Curves'!$G$12 + $AT$5*'Cancel Curves'!$F$12 + $AU$5*'Cancel Curves'!$E$12 + $AV$5*'Cancel Curves'!$D$12 + $AW$5*'Cancel Curves'!$C$12 + $AX$5*'Cancel Curves'!$B$12)*Assumptions!$B$76 | AY13: =AY6*AY12 + ($AN$5*'Cancel Curves'!$M$12 + $AO$5*'Cancel Curves'!$L$12 + $AP$5*'Cancel Curves'!$K$12 + $AQ$5*'Cancel Curves'!$J$12 + $AR$5*'Cancel Curves'!$I$12 + $AS$5*'Cancel Curves'!$H$12 + $AT$5*'Cancel Curves'!$G$12 + $AU$5*'Cancel Curves'!$F$12 + $AV$5*'Cancel Curves'!$E$12 + $AW$5*'Cancel Curves'!$D$12 + $AX$5*'Cancel Curves'!$C$12 + $AY$5*'Cancel Curves'!$B$12)*Assumptions!$B$76 | AZ13: =AZ6*AZ12 + ($AO$5*'Cancel Curves'!$M$12 + $AP$5*'Cancel Curves'!$L$12 + $AQ$5*'Cancel Curves'!$K$12 + $AR$5*'Cancel Curves'!$J$12 + $AS$5*'Cancel Curves'!$I$12 + $AT$5*'Cancel Curves'!$H$12 + $AU$5*'Cancel Curves'!$G$12 + $AV$5*'Cancel Curves'!$F$12 + $AW$5*'Cancel Curves'!$E$12 + $AX$5*'Cancel Curves'!$D$12 + $AY$5*'Cancel Curves'!$C$12 + $AZ$5*'Cancel Curves'!$B$12)*Assumptions!$B$76 | BA13: =BA6*BA12 + ($AP$5*'Cancel Curves'!$M$12 + $AQ$5*'Cancel Curves'!$L$12 + $AR$5*'Cancel Curves'!$K$12 + $AS$5*'Cancel Curves'!$J$12 + $AT$5*'Cancel Curves'!$I$12 + $AU$5*'Cancel Curves'!$H$12 + $AV$5*'Cancel Curves'!$G$12 + $AW$5*'Cancel Curves'!$F$12 + $AX$5*'Cancel Curves'!$E$12 + $AY$5*'Cancel Curves'!$D$12 + $AZ$5*'Cancel Curves'!$C$12 + $BA$5*'Cancel Curves'!$B$12)*Assumptions!$B$76 | BB13: =BB6*BB12 + ($AQ$5*'Cancel Curves'!$M$12 + $AR$5*'Cancel Curves'!$L$12 + $AS$5*'Cancel Curves'!$K$12 + $AT$5*'Cancel Curves'!$J$12 + $AU$5*'Cancel Curves'!$I$12 + $AV$5*'Cancel Curves'!$H$12 + $AW$5*'Cancel Curves'!$G$12 + $AX$5*'Cancel Curves'!$F$12 + $AY$5*'Cancel Curves'!$E$12 + $AZ$5*'Cancel Curves'!$D$12 + $BA$5*'Cancel Curves'!$C$12 + $BB$5*'Cancel Curves'!$B$12)*Assumptions!$B$76 | BC13: =BC6*BC12 + ($AR$5*'Cancel Curves'!$M$12 + $AS$5*'Cancel Curves'!$L$12 + $AT$5*'Cancel Curves'!$K$12 + $AU$5*'Cancel Curves'!$J$12 + $AV$5*'Cancel Curves'!$I$12 + $AW$5*'Cancel Curves'!$H$12 + $AX$5*'Cancel Curves'!$G$12 + $AY$5*'Cancel Curves'!$F$12 + $AZ$5*'Cancel Curves'!$E$12 + $BA$5*'Cancel Curves'!$D$12 + $BB$5*'Cancel Curves'!$C$12 + $BC$5*'Cancel Curves'!$B$12)*Assumptions!$B$76 | BD13: =BD6*BD12 + ($AS$5*'Cancel Curves'!$M$12 + $AT$5*'Cancel Curves'!$L$12 + $AU$5*'Cancel Curves'!$K$12 + $AV$5*'Cancel Curves'!$J$12 + $AW$5*'Cancel Curves'!$I$12 + $AX$5*'Cancel Curves'!$H$12 + $AY$5*'Cancel Curves'!$G$12 + $AZ$5*'Cancel Curves'!$F$12 + $BA$5*'Cancel Curves'!$E$12 + $BB$5*'Cancel Curves'!$D$12 + $BC$5*'Cancel Curves'!$C$12 + $BD$5*'Cancel Curves'!$B$12)*Assumptions!$B$76 | BE13: =BE6*BE12 + ($AT$5*'Cancel Curves'!$M$12 + $AU$5*'Cancel Curves'!$L$12 + $AV$5*'Cancel Curves'!$K$12 + $AW$5*'Cancel Curves'!$J$12 + $AX$5*'Cancel Curves'!$I$12 + $AY$5*'Cancel Curves'!$H$12 + $AZ$5*'Cancel Curves'!$G$12 + $BA$5*'Cancel Curves'!$F$12 + $BB$5*'Cancel Curves'!$E$12 + $BC$5*'Cancel Curves'!$D$12 + $BD$5*'Cancel Curves'!$C$12 + $BE$5*'Cancel Curves'!$B$12)*Assumptions!$B$76 | BF13: =BF6*BF12 + ($AU$5*'Cancel Curves'!$M$12 + $AV$5*'Cancel Curves'!$L$12 + $AW$5*'Cancel Curves'!$K$12 + $AX$5*'Cancel Curves'!$J$12 + $AY$5*'Cancel Curves'!$I$12 + $AZ$5*'Cancel Curves'!$H$12 + $BA$5*'Cancel Curves'!$G$12 + $BB$5*'Cancel Curves'!$F$12 + $BC$5*'Cancel Curves'!$E$12 + $BD$5*'Cancel Curves'!$D$12 + $BE$5*'Cancel Curves'!$C$12 + $BF$5*'Cancel Curves'!$B$12)*Assumptions!$B$76 | BG13: =BG6*BG12 + ($AV$5*'Cancel Curves'!$M$12 + $AW$5*'Cancel Curves'!$L$12 + $AX$5*'Cancel Curves'!$K$12 + $AY$5*'Cancel Curves'!$J$12 + $AZ$5*'Cancel Curves'!$I$12 + $BA$5*'Cancel Curves'!$H$12 + $BB$5*'Cancel Curves'!$G$12 + $BC$5*'Cancel Curves'!$F$12 + $BD$5*'Cancel Curves'!$E$12 + $BE$5*'Cancel Curves'!$D$12 + $BF$5*'Cancel Curves'!$C$12 + $BG$5*'Cancel Curves'!$B$12)*Assumptions!$B$76 | BH13: =BH6*BH12 + ($AW$5*'Cancel Curves'!$M$12 + $AX$5*'Cancel Curves'!$L$12 + $AY$5*'Cancel Curves'!$K$12 + $AZ$5*'Cancel Curves'!$J$12 + $BA$5*'Cancel Curves'!$I$12 + $BB$5*'Cancel Curves'!$H$12 + $BC$5*'Cancel Curves'!$G$12 + $BD$5*'Cancel Curves'!$F$12 + $BE$5*'Cancel Curves'!$E$12 + $BF$5*'Cancel Curves'!$D$12 + $BG$5*'Cancel Curves'!$C$12 + $BH$5*'Cancel Curves'!$B$12)*Assumptions!$B$76 | BI13: =BI6*BI12 + ($AX$5*'Cancel Curves'!$M$12 + $AY$5*'Cancel Curves'!$L$12 + $AZ$5*'Cancel Curves'!$K$12 + $BA$5*'Cancel Curves'!$J$12 + $BB$5*'Cancel Curves'!$I$12 + $BC$5*'Cancel Curves'!$H$12 + $BD$5*'Cancel Curves'!$G$12 + $BE$5*'Cancel Curves'!$F$12 + $BF$5*'Cancel Curves'!$E$12 + $BG$5*'Cancel Curves'!$D$12 + $BH$5*'Cancel Curves'!$C$12 + $BI$5*'Cancel Curves'!$B$12)*Assumptions!$B$76 | BJ13: =BJ6*BJ12 + ($AY$5*'Cancel Curves'!$M$12 + $AZ$5*'Cancel Curves'!$L$12 + $BA$5*'Cancel Curves'!$K$12 + $BB$5*'Cancel Curves'!$J$12 + $BC$5*'Cancel Curves'!$I$12 + $BD$5*'Cancel Curves'!$H$12 + $BE$5*'Cancel Curves'!$G$12 + $BF$5*'Cancel Curves'!$F$12 + $BG$5*'Cancel Curves'!$E$12 + $BH$5*'Cancel Curves'!$D$12 + $BI$5*'Cancel Curves'!$C$12 + $BJ$5*'Cancel Curves'!$B$12)*Assumptions!$B$76 | BK13: =BK6*BK12 + ($AZ$5*'Cancel Curves'!$M$12 + $BA$5*'Cancel Curves'!$L$12 + $BB$5*'Cancel Curves'!$K$12 + $BC$5*'Cancel Curves'!$J$12 + $BD$5*'Cancel Curves'!$I$12 + $BE$5*'Cancel Curves'!$H$12 + $BF$5*'Cancel Curves'!$G$12 + $BG$5*'Cancel Curves'!$F$12 + $BH$5*'Cancel Curves'!$E$12 + $BI$5*'Cancel Curves'!$D$12 + $BJ$5*'Cancel Curves'!$C$12 + $BK$5*'Cancel Curves'!$B$12)*Assumptions!$B$76 | BL13: =BL6*BL12 + ($BA$5*'Cancel Curves'!$M$12 + $BB$5*'Cancel Curves'!$L$12 + $BC$5*'Cancel Curves'!$K$12 + $BD$5*'Cancel Curves'!$J$12 + $BE$5*'Cancel Curves'!$I$12 + $BF$5*'Cancel Curves'!$H$12 + $BG$5*'Cancel Curves'!$G$12 + $BH$5*'Cancel Curves'!$F$12 + $BI$5*'Cancel Curves'!$E$12 + $BJ$5*'Cancel Curves'!$D$12 + $BK$5*'Cancel Curves'!$C$12 + $BL$5*'Cancel Curves'!$B$12)*Assumptions!$B$76 | BM13: =BM6*BM12 + ($BB$5*'Cancel Curves'!$M$12 + $BC$5*'Cancel Curves'!$L$12 + $BD$5*'Cancel Curves'!$K$12 + $BE$5*'Cancel Curves'!$J$12 + $BF$5*'Cancel Curves'!$I$12 + $BG$5*'Cancel Curves'!$H$12 + $BH$5*'Cancel Curves'!$G$12 + $BI$5*'Cancel Curves'!$F$12 + $BJ$5*'Cancel Curves'!$E$12 + $BK$5*'Cancel Curves'!$D$12 + $BL$5*'Cancel Curves'!$C$12 + $BM$5*'Cancel Curves'!$B$12)*Assumptions!$B$76 | BN13: =BN6*BN12 + ($BC$5*'Cancel Curves'!$M$12 + $BD$5*'Cancel Curves'!$L$12 + $BE$5*'Cancel Curves'!$K$12 + $BF$5*'Cancel Curves'!$J$12 + $BG$5*'Cancel Curves'!$I$12 + $BH$5*'Cancel Curves'!$H$12 + $BI$5*'Cancel Curves'!$G$12 + $BJ$5*'Cancel Curves'!$F$12 + $BK$5*'Cancel Curves'!$E$12 + $BL$5*'Cancel Curves'!$D$12 + $BM$5*'Cancel Curves'!$C$12 + $BN$5*'Cancel Curves'!$B$12)*Assumptions!$B$76 | BO13: =BO6*BO12 + ($BD$5*'Cancel Curves'!$M$12 + $BE$5*'Cancel Curves'!$L$12 + $BF$5*'Cancel Curves'!$K$12 + $BG$5*'Cancel Curves'!$J$12 + $BH$5*'Cancel Curves'!$I$12 + $BI$5*'Cancel Curves'!$H$12 + $BJ$5*'Cancel Curves'!$G$12 + $BK$5*'Cancel Curves'!$F$12 + $BL$5*'Cancel Curves'!$E$12 + $BM$5*'Cancel Curves'!$D$12 + $BN$5*'Cancel Curves'!$C$12 + $BO$5*'Cancel Curves'!$B$12)*Assumptions!$B$76 | BP13: =BP6*BP12 + ($BE$5*'Cancel Curves'!$M$12 + $BF$5*'Cancel Curves'!$L$12 + $BG$5*'Cancel Curves'!$K$12 + $BH$5*'Cancel Curves'!$J$12 + $BI$5*'Cancel Curves'!$I$12 + $BJ$5*'Cancel Curves'!$H$12 + $BK$5*'Cancel Curves'!$G$12 + $BL$5*'Cancel Curves'!$F$12 + $BM$5*'Cancel Curves'!$E$12 + $BN$5*'Cancel Curves'!$D$12 + $BO$5*'Cancel Curves'!$C$12 + $BP$5*'Cancel Curves'!$B$12)*Assumptions!$B$76 | BQ13: =BQ6*BQ12 + ($BF$5*'Cancel Curves'!$M$12 + $BG$5*'Cancel Curves'!$L$12 + $BH$5*'Cancel Curves'!$K$12 + $BI$5*'Cancel Curves'!$J$12 + $BJ$5*'Cancel Curves'!$I$12 + $BK$5*'Cancel Curves'!$H$12 + $BL$5*'Cancel Curves'!$G$12 + $BM$5*'Cancel Curves'!$F$12 + $BN$5*'Cancel Curves'!$E$12 + $BO$5*'Cancel Curves'!$D$12 + $BP$5*'Cancel Curves'!$C$12 + $BQ$5*'Cancel Curves'!$B$12)*Assumptions!$B$76 | BR13: =BR6*BR12 + ($BG$5*'Cancel Curves'!$M$12 + $BH$5*'Cancel Curves'!$L$12 + $BI$5*'Cancel Curves'!$K$12 + $BJ$5*'Cancel Curves'!$J$12 + $BK$5*'Cancel Curves'!$I$12 + $BL$5*'Cancel Curves'!$H$12 + $BM$5*'Cancel Curves'!$G$12 + $BN$5*'Cancel Curves'!$F$12 + $BO$5*'Cancel Curves'!$E$12 + $BP$5*'Cancel Curves'!$D$12 + $BQ$5*'Cancel Curves'!$C$12 + $BR$5*'Cancel Curves'!$B$12)*Assumptions!$B$76 | BS13: =BS6*BS12 + ($BH$5*'Cancel Curves'!$M$12 + $BI$5*'Cancel Curves'!$L$12 + $BJ$5*'Cancel Curves'!$K$12 + $BK$5*'Cancel Curves'!$J$12 + $BL$5*'Cancel Curves'!$I$12 + $BM$5*'Cancel Curves'!$H$12 + $BN$5*'Cancel Curves'!$G$12 + $BO$5*'Cancel Curves'!$F$12 + $BP$5*'Cancel Curves'!$E$12 + $BQ$5*'Cancel Curves'!$D$12 + $BR$5*'Cancel Curves'!$C$12 + $BS$5*'Cancel Curves'!$B$12)*Assumptions!$B$76 | BT13: =BT6*BT12 + ($BI$5*'Cancel Curves'!$M$12 + $BJ$5*'Cancel Curves'!$L$12 + $BK$5*'Cancel Curves'!$K$12 + $BL$5*'Cancel Curves'!$J$12 + $BM$5*'Cancel Curves'!$I$12 + $BN$5*'Cancel Curves'!$H$12 + $BO$5*'Cancel Curves'!$G$12 + $BP$5*'Cancel Curves'!$F$12 + $BQ$5*'Cancel Curves'!$E$12 + $BR$5*'Cancel Curves'!$D$12 + $BS$5*'Cancel Curves'!$C$12 + $BT$5*'Cancel Curves'!$B$12)*Assumptions!$B$76 | BU13: =BU6*BU12 + ($BJ$5*'Cancel Curves'!$M$12 + $BK$5*'Cancel Curves'!$L$12 + $BL$5*'Cancel Curves'!$K$12 + $BM$5*'Cancel Curves'!$J$12 + $BN$5*'Cancel Curves'!$I$12 + $BO$5*'Cancel Curves'!$H$12 + $BP$5*'Cancel Curves'!$G$12 + $BQ$5*'Cancel Curves'!$F$12 + $BR$5*'Cancel Curves'!$E$12 + $BS$5*'Cancel Curves'!$D$12 + $BT$5*'Cancel Curves'!$C$12 + $BU$5*'Cancel Curves'!$B$12)*Assumptions!$B$76 | BV13: =BV6*BV12 + ($BK$5*'Cancel Curves'!$M$12 + $BL$5*'Cancel Curves'!$L$12 + $BM$5*'Cancel Curves'!$K$12 + $BN$5*'Cancel Curves'!$J$12 + $BO$5*'Cancel Curves'!$I$12 + $BP$5*'Cancel Curves'!$H$12 + $BQ$5*'Cancel Curves'!$G$12 + $BR$5*'Cancel Curves'!$F$12 + $BS$5*'Cancel Curves'!$E$12 + $BT$5*'Cancel Curves'!$D$12 + $BU$5*'Cancel Curves'!$C$12 + $BV$5*'Cancel Curves'!$B$12)*Assumptions!$B$76 | BW13: =BW6*BW12 + ($BL$5*'Cancel Curves'!$M$12 + $BM$5*'Cancel Curves'!$L$12 + $BN$5*'Cancel Curves'!$K$12 + $BO$5*'Cancel Curves'!$J$12 + $BP$5*'Cancel Curves'!$I$12 + $BQ$5*'Cancel Curves'!$H$12 + $BR$5*'Cancel Curves'!$G$12 + $BS$5*'Cancel Curves'!$F$12 + $BT$5*'Cancel Curves'!$E$12 + $BU$5*'Cancel Curves'!$D$12 + $BV$5*'Cancel Curves'!$C$12 + $BW$5*'Cancel Curves'!$B$12)*Assumptions!$B$76
A14: Initiation fee (new contracts × IAA) | D14: =D5*Assumptions!$B$32 | E14: =E5*Assumptions!$B$32 | F14: =F5*Assumptions!$B$32 | G14: =G5*Assumptions!$B$32 | H14: =H5*Assumptions!$B$32 | I14: =I5*Assumptions!$B$32 | J14: =J5*Assumptions!$B$32 | K14: =K5*Assumptions!$B$32 | ... BW14: =BW5*Assumptions!$B$32
A15: Total revenue | D15: =D13+D14 | E15: =E13+E14 | F15: =F13+F14 | G15: =G13+G14 | H15: =H13+H14 | I15: =I13+I14 | J15: =J13+J14 | K15: =K13+K14 | ... BW15: =BW13+BW14
A17: COST OF SERVICE
A18: Claims expense (active × claims reserve / 12) | D18: =IF(1<Assumptions!$B$25,0,D6*Assumptions!$B$24/12) | E18: =IF(2<Assumptions!$B$25,0,E6*Assumptions!$B$24/12) | F18: =IF(3<Assumptions!$B$25,0,F6*Assumptions!$B$24/12) | G18: =IF(4<Assumptions!$B$25,0,G6*Assumptions!$B$24/12) | H18: =IF(5<Assumptions!$B$25,0,H6*Assumptions!$B$24/12) | I18: =IF(6<Assumptions!$B$25,0,I6*Assumptions!$B$24/12) | J18: =IF(7<Assumptions!$B$25,0,J6*Assumptions!$B$24/12) | K18: =IF(8<Assumptions!$B$25,0,K6*Assumptions!$B$24/12) | L18: =IF(9<Assumptions!$B$25,0,L6*Assumptions!$B$24/12) | M18: =IF(10<Assumptions!$B$25,0,M6*Assumptions!$B$24/12) | N18: =IF(11<Assumptions!$B$25,0,N6*Assumptions!$B$24/12) | O18: =IF(12<Assumptions!$B$25,0,O6*Assumptions!$B$24/12) | P18: =IF(13<Assumptions!$B$25,0,P6*Assumptions!$B$24/12) | Q18: =IF(14<Assumptions!$B$25,0,Q6*Assumptions!$B$24/12) | R18: =IF(15<Assumptions!$B$25,0,R6*Assumptions!$B$24/12) | S18: =IF(16<Assumptions!$B$25,0,S6*Assumptions!$B$24/12) | T18: =IF(17<Assumptions!$B$25,0,T6*Assumptions!$B$24/12) | U18: =IF(18<Assumptions!$B$25,0,U6*Assumptions!$B$24/12) | V18: =IF(19<Assumptions!$B$25,0,V6*Assumptions!$B$24/12) | W18: =IF(20<Assumptions!$B$25,0,W6*Assumptions!$B$24/12) | X18: =IF(21<Assumptions!$B$25,0,X6*Assumptions!$B$24/12) | Y18: =IF(22<Assumptions!$B$25,0,Y6*Assumptions!$B$24/12) | Z18: =IF(23<Assumptions!$B$25,0,Z6*Assumptions!$B$24/12) | AA18: =IF(24<Assumptions!$B$25,0,AA6*Assumptions!$B$24/12) | AB18: =IF(25<Assumptions!$B$25,0,AB6*Assumptions!$B$24/12) | AC18: =IF(26<Assumptions!$B$25,0,AC6*Assumptions!$B$24/12) | AD18: =IF(27<Assumptions!$B$25,0,AD6*Assumptions!$B$24/12) | AE18: =IF(28<Assumptions!$B$25,0,AE6*Assumptions!$B$24/12) | AF18: =IF(29<Assumptions!$B$25,0,AF6*Assumptions!$B$24/12) | AG18: =IF(30<Assumptions!$B$25,0,AG6*Assumptions!$B$24/12) | AH18: =IF(31<Assumptions!$B$25,0,AH6*Assumptions!$B$24/12) | AI18: =IF(32<Assumptions!$B$25,0,AI6*Assumptions!$B$24/12) | AJ18: =IF(33<Assumptions!$B$25,0,AJ6*Assumptions!$B$24/12) | AK18: =IF(34<Assumptions!$B$25,0,AK6*Assumptions!$B$24/12) | AL18: =IF(35<Assumptions!$B$25,0,AL6*Assumptions!$B$24/12) | AM18: =IF(36<Assumptions!$B$25,0,AM6*Assumptions!$B$24/12) | AN18: =IF(37<Assumptions!$B$25,0,AN6*Assumptions!$B$24/12) | AO18: =IF(38<Assumptions!$B$25,0,AO6*Assumptions!$B$24/12) | AP18: =IF(39<Assumptions!$B$25,0,AP6*Assumptions!$B$24/12) | AQ18: =IF(40<Assumptions!$B$25,0,AQ6*Assumptions!$B$24/12) | AR18: =IF(41<Assumptions!$B$25,0,AR6*Assumptions!$B$24/12) | AS18: =IF(42<Assumptions!$B$25,0,AS6*Assumptions!$B$24/12) | AT18: =IF(43<Assumptions!$B$25,0,AT6*Assumptions!$B$24/12) | AU18: =IF(44<Assumptions!$B$25,0,AU6*Assumptions!$B$24/12) | AV18: =IF(45<Assumptions!$B$25,0,AV6*Assumptions!$B$24/12) | AW18: =IF(46<Assumptions!$B$25,0,AW6*Assumptions!$B$24/12) | AX18: =IF(47<Assumptions!$B$25,0,AX6*Assumptions!$B$24/12) | AY18: =IF(48<Assumptions!$B$25,0,AY6*Assumptions!$B$24/12) | AZ18: =IF(49<Assumptions!$B$25,0,AZ6*Assumptions!$B$24/12) | BA18: =IF(50<Assumptions!$B$25,0,BA6*Assumptions!$B$24/12) | BB18: =IF(51<Assumptions!$B$25,0,BB6*Assumptions!$B$24/12) | BC18: =IF(52<Assumptions!$B$25,0,BC6*Assumptions!$B$24/12) | BD18: =IF(53<Assumptions!$B$25,0,BD6*Assumptions!$B$24/12) | BE18: =IF(54<Assumptions!$B$25,0,BE6*Assumptions!$B$24/12) | BF18: =IF(55<Assumptions!$B$25,0,BF6*Assumptions!$B$24/12) | BG18: =IF(56<Assumptions!$B$25,0,BG6*Assumptions!$B$24/12) | BH18: =IF(57<Assumptions!$B$25,0,BH6*Assumptions!$B$24/12) | BI18: =IF(58<Assumptions!$B$25,0,BI6*Assumptions!$B$24/12) | BJ18: =IF(59<Assumptions!$B$25,0,BJ6*Assumptions!$B$24/12) | BK18: =IF(60<Assumptions!$B$25,0,BK6*Assumptions!$B$24/12) | BL18: =IF(61<Assumptions!$B$25,0,BL6*Assumptions!$B$24/12) | BM18: =IF(62<Assumptions!$B$25,0,BM6*Assumptions!$B$24/12) | BN18: =IF(63<Assumptions!$B$25,0,BN6*Assumptions!$B$24/12) | BO18: =IF(64<Assumptions!$B$25,0,BO6*Assumptions!$B$24/12) | BP18: =IF(65<Assumptions!$B$25,0,BP6*Assumptions!$B$24/12) | BQ18: =IF(66<Assumptions!$B$25,0,BQ6*Assumptions!$B$24/12) | BR18: =IF(67<Assumptions!$B$25,0,BR6*Assumptions!$B$24/12) | BS18: =IF(68<Assumptions!$B$25,0,BS6*Assumptions!$B$24/12) | BT18: =IF(69<Assumptions!$B$25,0,BT6*Assumptions!$B$24/12) | BU18: =IF(70<Assumptions!$B$25,0,BU6*Assumptions!$B$24/12) | BV18: =IF(71<Assumptions!$B$25,0,BV6*Assumptions!$B$24/12) | BW18: =IF(72<Assumptions!$B$25,0,BW6*Assumptions!$B$24/12)
A19: Contract insurance (Lloyd's premium) | D19: =D5*Assumptions!$B$20 | E19: =E5*Assumptions!$B$20 | F19: =F5*Assumptions!$B$20 | G19: =G5*Assumptions!$B$20 | H19: =H5*Assumptions!$B$20 | I19: =I5*Assumptions!$B$20 | J19: =J5*Assumptions!$B$20 | K19: =K5*Assumptions!$B$20 | ... BW19: =BW5*Assumptions!$B$20
A20: Finance fees | D20: =D6*D12*Assumptions!$B$26 | E20: =E6*E12*Assumptions!$B$26 | F20: =F6*F12*Assumptions!$B$26 | G20: =G6*G12*Assumptions!$B$26 | H20: =H6*H12*Assumptions!$B$26 | I20: =I6*I12*Assumptions!$B$26 | J20: =J6*J12*Assumptions!$B$26 | K20: =K6*K12*Assumptions!$B$26 | ... BW20: =BW6*BW12*Assumptions!$B$26
A22: Fulfillment — postage + printing | D22: =D5*(Assumptions!$B$29+Assumptions!$B$30) | E22: =E5*(Assumptions!$B$29+Assumptions!$B$30) | F22: =F5*(Assumptions!$B$29+Assumptions!$B$30) | G22: =G5*(Assumptions!$B$29+Assumptions!$B$30) | H22: =H5*(Assumptions!$B$29+Assumptions!$B$30) | I22: =I5*(Assumptions!$B$29+Assumptions!$B$30) | J22: =J5*(Assumptions!$B$29+Assumptions!$B$30) | K22: =K5*(Assumptions!$B$29+Assumptions!$B$30) | ... BW22: =BW5*(Assumptions!$B$29+Assumptions!$B$30)
A23: Merchant fees + chargebacks | D23: =D13*Assumptions!$B$27 | E23: =E13*Assumptions!$B$27 | F23: =F13*Assumptions!$B$27 | G23: =G13*Assumptions!$B$27 | H23: =H13*Assumptions!$B$27 | I23: =I13*Assumptions!$B$27 | J23: =J13*Assumptions!$B$27 | K23: =K13*Assumptions!$B$27 | ... BW23: =BW13*Assumptions!$B$27
A24: Total COS | D24: =SUM(D18:D23) | E24: =SUM(E18:E23) | F24: =SUM(F18:F23) | G24: =SUM(G18:G23) | H24: =SUM(H18:H23) | I24: =SUM(I18:I23) | J24: =SUM(J18:J23) | K24: =SUM(K18:K23) | ... BW24: =SUM(BW18:BW23)
A26: Gross profit | D26: =D15-D24 | E26: =E15-E24 | F26: =F15-F24 | G26: =G15-G24 | H26: =H15-H24 | I26: =I15-I24 | J26: =J15-J24 | K26: =K15-K24 | ... BW26: =BW15-BW24
A28: ANNUAL ROLL-UP | BY28: 2025A | BZ28: 2026E | CA28: 2027E | CB28: 2028E | CC28: 2029E | CD28: 2030E
A29: New contracts | BY29: =SUM(D5:O5) | BZ29: =SUM(P5:AA5) | CA29: =SUM(AB5:AM5) | CB29: =SUM(AN5:AY5) | CC29: =SUM(AZ5:BK5) | CD29: =SUM(BL5:BW5)
A30: Active contracts (Dec) | BY30: =O6 | BZ30: =AA6 | CA30: =AM6 | CB30: =AY6 | CC30: =BK6 | CD30: =BW6
A31: Total revenue | BY31: =SUM(D15:O15) | BZ31: =SUM(P15:AA15) | CA31: =SUM(AB15:AM15) | CB31: =SUM(AN15:AY15) | CC31: =SUM(AZ15:BK15) | CD31: =SUM(BL15:BW15)
A32: Total COS | BY32: =SUM(D24:O24) | BZ32: =SUM(P24:AA24) | CA32: =SUM(AB24:AM24) | CB32: =SUM(AN24:AY24) | CC32: =SUM(AZ24:BK24) | CD32: =SUM(BL24:BW24)
A33: Gross profit | BY33: =SUM(D26:O26) | BZ33: =SUM(P26:AA26) | CA33: =SUM(AB26:AM26) | CB33: =SUM(AN26:AY26) | CC33: =SUM(AZ26:BK26) | CD33: =SUM(BL26:BW26)

Sheet ASD Sales
A1: ASD Channel VSC — Engine (Vintage Cohort Survival)
A2: Monthly originations × shared cancel curve. CPS (customer payment per service) = $100.0/mo.
C3: 2024A | D3: 2025 | E3: 2025 | F3: 2025 | G3: 2025 | H3: 2025 | I3: 2025 | J3: 2025 | K3: 2025 | L3: 2025 | M3: 2025 | N3: 2025 | O3: 2025 | P3: 2026 | Q3: 2026 | R3: 2026 | S3: 2026 | T3: 2026 | U3: 2026 | V3: 2026 | W3: 2026 | X3: 2026 | Y3: 2026 | Z3: 2026 | AA3: 2026 | AB3: 2027 | AC3: 2027 | AD3: 2027 | AE3: 2027 | AF3: 2027 | AG3: 2027 | AH3: 2027 | AI3: 2027 | AJ3: 2027 | AK3: 2027 | AL3: 2027 | AM3: 2027 | AN3: 2028 | AO3: 2028 | AP3: 2028 | AQ3: 2028 | AR3: 2028 | AS3: 2028 | AT3: 2028 | AU3: 2028 | AV3: 2028 | AW3: 2028 | AX3: 2028 | AY3: 2028 | AZ3: 2029 | BA3: 2029 | BB3: 2029 | BC3: 2029 | BD3: 2029 | BE3: 2029 | BF3: 2029 | BG3: 2029 | BH3: 2029 | BI3: 2029 | BJ3: 2029 | BK3: 2029 | BL3: 2030 | BM3: 2030 | BN3: 2030 | BO3: 2030 | BP3: 2030 | BQ3: 2030 | BR3: 2030 | BS3: 2030 | BT3: 2030 | BU3: 2030 | BV3: 2030 | BW3: 2030
C4: Anchor | D4: 2025-01 | E4: 2025-02 | F4: 2025-03 | G4: 2025-04 | H4: 2025-05 | I4: 2025-06 | J4: 2025-07 | K4: 2025-08 | L4: 2025-09 | M4: 2025-10 | N4: 2025-11 | O4: 2025-12 | P4: 2026-01 | Q4: 2026-02 | R4: 2026-03 | S4: 2026-04 | T4: 2026-05 | U4: 2026-06 | V4: 2026-07 | W4: 2026-08 | X4: 2026-09 | Y4: 2026-10 | Z4: 2026-11 | AA4: 2026-12 | AB4: 2027-01 | AC4: 2027-02 | AD4: 2027-03 | AE4: 2027-04 | AF4: 2027-05 | AG4: 2027-06 | AH4: 2027-07 | AI4: 2027-08 | AJ4: 2027-09 | AK4: 2027-10 | AL4: 2027-11 | AM4: 2027-12 | AN4: 2028-01 | AO4: 2028-02 | AP4: 2028-03 | AQ4: 2028-04 | AR4: 2028-05 | AS4: 2028-06 | AT4: 2028-07 | AU4: 2028-08 | AV4: 2028-09 | AW4: 2028-10 | AX4: 2028-11 | AY4: 2028-12 | AZ4: 2029-01 | BA4: 2029-02 | BB4: 2029-03 | BC4: 2029-04 | BD4: 2029-05 | BE4: 2029-06 | BF4: 2029-07 | BG4: 2029-08 | BH4: 2029-09 | BI4: 2029-10 | BJ4: 2029-11 | BK4: 2029-12 | BL4: 2030-01 | BM4: 2030-02 | BN4: 2030-03 | BO4: 2030-04 | BP4: 2030-05 | BQ4: 2030-06 | BR4: 2030-07 | BS4: 2030-08 | BT4: 2030-09 | BU4: 2030-10 | BV4: 2030-11 | BW4: 2030-12
A5: New contracts originated | D5: 3668 | E5: 2896 | F5: 3414 | G5: 2731 | H5: 2831 | I5: 2931 | J5: 3031 | K5: 5000 | L5: 5100 | M5: 5100 | N5: 5200 | O5: 4800 | P5: 4900 | Q5: 5000 | R5: 5100 | S5: 5200 | T5: 5300 | U5: 5400 | V5: 5500 | W5: 5600 | X5: 5700 | Y5: 5800 | Z5: 5900 | AA5: 6000 | AB5: 6100 | AC5: 6200 | AD5: 6300 | AE5: 6400 | AF5: 6500 | AG5: 6600 | AH5: 6700 | AI5: 6800 | AJ5: 6900 | AK5: 7000 | AL5: 7100 | AM5: 7200 | AN5: 7300 | AO5: 7400 | AP5: 7500 | AQ5: 7600 | AR5: 7700 | AS5: 7800 | AT5: 7900 | AU5: 8000 | AV5: 8100 | AW5: 8200 | AX5: 8300 | AY5: 8400 | AZ5: 8500 | BA5: 8600 | BB5: 8700 | BC5: 8800 | BD5: 8900 | BE5: 9000 | BF5: 9100 | BG5: 9200 | BH5: 9300 | BI5: 9400 | BJ5: 9500 | BK5: 9600 | BL5: 9700 | BM5: 9800 | BN5: 9900 | BO5: 10000 | BP5: 10100 | BQ5: 10200 | BR5: 10300 | BS5: 10400 | BT5: 10500 | BU5: 10600 | BV5: 10700 | BW5: 10800
A6: Active contracts (vintage-weighted) | C6: =C7 | D6: =$D5*'Cancel Curves'!$B$12 + 12739.4285 | E6: =$D5*'Cancel Curves'!$C$12 + $E5*'Cancel Curves'!$B$12 + 12012.1763 | F6: =$D5*'Cancel Curves'!$D$12 + $E5*'Cancel Curves'!$C$12 + $F5*'Cancel Curves'!$B$12 + 11428.8419 | G6: =$D5*'Cancel Curves'!$E$12 + $E5*'Cancel Curves'!$D$12 + $F5*'Cancel Curves'!$C$12 + $G5*'Cancel Curves'!$B$12 + 10940.1364 | H6: =$D5*'Cancel Curves'!$F$12 + $E5*'Cancel Curves'!$E$12 + $F5*'Cancel Curves'!$D$12 + $G5*'Cancel Curves'!$C$12 + $H5*'Cancel Curves'!$B$12 + 10514.6037 | I6: =$D5*'Cancel Curves'!$G$12 + $E5*'Cancel Curves'!$F$12 + $F5*'Cancel Curves'!$E$12 + $G5*'Cancel Curves'!$D$12 + $H5*'Cancel Curves'!$C$12 + $I5*'Cancel Curves'!$B$12 + 10141.9899 | J6: =$D5*'Cancel Curves'!$H$12 + $E5*'Cancel Curves'!$G$12 + $F5*'Cancel Curves'!$F$12 + $G5*'Cancel Curves'!$E$12 + $H5*'Cancel Curves'!$D$12 + $I5*'Cancel Curves'!$C$12 + $J5*'Cancel Curves'!$B$12 + 9817.0405 | K6: =$D5*'Cancel Curves'!$I$12 + $E5*'Cancel Curves'!$H$12 + $F5*'Cancel Curves'!$G$12 + $G5*'Cancel Curves'!$F$12 + $H5*'Cancel Curves'!$E$12 + $I5*'Cancel Curves'!$D$12 + $J5*'Cancel Curves'!$C$12 + $K5*'Cancel Curves'!$B$12 + 9544.8502 | L6: =$D5*'Cancel Curves'!$J$12 + $E5*'Cancel Curves'!$I$12 + $F5*'Cancel Curves'!$H$12 + $G5*'Cancel Curves'!$G$12 + $H5*'Cancel Curves'!$F$12 + $I5*'Cancel Curves'!$E$12 + $J5*'Cancel Curves'!$D$12 + $K5*'Cancel Curves'!$C$12 + $L5*'Cancel Curves'!$B$12 + 9314.3362 | M6: =$D5*'Cancel Curves'!$K$12 + $E5*'Cancel Curves'!$J$12 + $F5*'Cancel Curves'!$I$12 + $G5*'Cancel Curves'!$H$12 + $H5*'Cancel Curves'!$G$12 + $I5*'Cancel Curves'!$F$12 + $J5*'Cancel Curves'!$E$12 + $K5*'Cancel Curves'!$D$12 + $L5*'Cancel Curves'!$C$12 + $M5*'Cancel Curves'!$B$12 + 9123.0987 | N6: =$D5*'Cancel Curves'!$L$12 + $E5*'Cancel Curves'!$K$12 + $F5*'Cancel Curves'!$J$12 + $G5*'Cancel Curves'!$I$12 + $H5*'Cancel Curves'!$H$12 + $I5*'Cancel Curves'!$G$12 + $J5*'Cancel Curves'!$F$12 + $K5*'Cancel Curves'!$E$12 + $L5*'Cancel Curves'!$D$12 + $M5*'Cancel Curves'!$C$12 + $N5*'Cancel Curves'!$B$12 + 8965.9846 | O6: =$D5*'Cancel Curves'!$M$12 + $E5*'Cancel Curves'!$L$12 + $F5*'Cancel Curves'!$K$12 + $G5*'Cancel Curves'!$J$12 + $H5*'Cancel Curves'!$I$12 + $I5*'Cancel Curves'!$H$12 + $J5*'Cancel Curves'!$G$12 + $K5*'Cancel Curves'!$F$12 + $L5*'Cancel Curves'!$E$12 + $M5*'Cancel Curves'!$D$12 + $N5*'Cancel Curves'!$C$12 + $O5*'Cancel Curves'!$B$12 + 8835.6899 | P6: =$D5*'Cancel Curves'!$N$12 + $E5*'Cancel Curves'!$M$12 + $F5*'Cancel Curves'!$L$12 + $G5*'Cancel Curves'!$K$12 + $H5*'Cancel Curves'!$J$12 + $I5*'Cancel Curves'!$I$12 + $J5*'Cancel Curves'!$H$12 + $K5*'Cancel Curves'!$G$12 + $L5*'Cancel Curves'!$F$12 + $M5*'Cancel Curves'!$E$12 + $N5*'Cancel Curves'!$D$12 + $O5*'Cancel Curves'!$C$12 + $P5*'Cancel Curves'!$B$12 + 8377.0854 | Q6: =$D5*'Cancel Curves'!$O$12 + $E5*'Cancel Curves'!$N$12 + $F5*'Cancel Curves'!$M$12 + $G5*'Cancel Curves'!$L$12 + $H5*'Cancel Curves'!$K$12 + $I5*'Cancel Curves'!$J$12 + $J5*'Cancel Curves'!$I$12 + $K5*'Cancel Curves'!$H$12 + $L5*'Cancel Curves'!$G$12 + $M5*'Cancel Curves'!$F$12 + $N5*'Cancel Curves'!$E$12 + $O5*'Cancel Curves'!$D$12 + $P5*'Cancel Curves'!$C$12 + $Q5*'Cancel Curves'!$B$12 + 7437.9559 | R6: =$D5*'Cancel Curves'!$P$12 + $E5*'Cancel Curves'!$O$12 + $F5*'Cancel Curves'!$N$12 + $G5*'Cancel Curves'!$M$12 + $H5*'Cancel Curves'!$L$12 + $I5*'Cancel Curves'!$K$12 + $J5*'Cancel Curves'!$J$12 + $K5*'Cancel Curves'!$I$12 + $L5*'Cancel Curves'!$H$12 + $M5*'Cancel Curves'!$G$12 + $N5*'Cancel Curves'!$F$12 + $O5*'Cancel Curves'!$E$12 + $P5*'Cancel Curves'!$D$12 + $Q5*'Cancel Curves'!$C$12 + $R5*'Cancel Curves'!$B$12 + 6636.0397 | S6: =$D5*'Cancel Curves'!$Q$12 + $E5*'Cancel Curves'!$P$12 + $F5*'Cancel Curves'!$O$12 + $G5*'Cancel Curves'!$N$12 + $H5*'Cancel Curves'!$M$12 + $I5*'Cancel Curves'!$L$12 + $J5*'Cancel Curves'!$K$12 + $K5*'Cancel Curves'!$J$12 + $L5*'Cancel Curves'!$I$12 + $M5*'Cancel Curves'!$H$12 + $N5*'Cancel Curves'!$G$12 + $O5*'Cancel Curves'!$F$12 + $P5*'Cancel Curves'!$E$12 + $Q5*'Cancel Curves'!$D$12 + $R5*'Cancel Curves'!$C$12 + $S5*'Cancel Curves'!$B$12 + 5794.8677 | T6: =$D5*'Cancel Curves'!$R$12 + $E5*'Cancel Curves'!$Q$12 + $F5*'Cancel Curves'!$P$12 + $G5*'Cancel Curves'!$O$12 + $H5*'Cancel Curves'!$N$12 + $I5*'Cancel Curves'!$M$12 + $J5*'Cancel Curves'!$L$12 + $K5*'Cancel Curves'!$K$12 + $L5*'Cancel Curves'!$J$12 + $M5*'Cancel Curves'!$I$12 + $N5*'Cancel Curves'!$H$12 + $O5*'Cancel Curves'!$G$12 + $P5*'Cancel Curves'!$F$12 + $Q5*'Cancel Curves'!$E$12 + $R5*'Cancel Curves'!$D$12 + $S5*'Cancel Curves'!$C$12 + $T5*'Cancel Curves'!$B$12 + 5211.6177 | U6: =$D5*'Cancel Curves'!$S$12 + $E5*'Cancel Curves'!$R$12 + $F5*'Cancel Curves'!$Q$12 + $G5*'Cancel Curves'!$P$12 + $H5*'Cancel Curves'!$O$12 + $I5*'Cancel Curves'!$N$12 + $J5*'Cancel Curves'!$M$12 + $K5*'Cancel Curves'!$L$12 + $L5*'Cancel Curves'!$K$12 + $M5*'Cancel Curves'!$J$12 + $N5*'Cancel Curves'!$I$12 + $O5*'Cancel Curves'!$H$12 + $P5*'Cancel Curves'!$G$12 + $Q5*'Cancel Curves'!$F$12 + $R5*'Cancel Curves'!$E$12 + $S5*'Cancel Curves'!$D$12 + $T5*'Cancel Curves'!$C$12 + $U5*'Cancel Curves'!$B$12 + 4623.3973 | V6: =$D5*'Cancel Curves'!$T$12 + $E5*'Cancel Curves'!$S$12 + $F5*'Cancel Curves'!$R$12 + $G5*'Cancel Curves'!$Q$12 + $H5*'Cancel Curves'!$P$12 + $I5*'Cancel Curves'!$O$12 + $J5*'Cancel Curves'!$N$12 + $K5*'Cancel Curves'!$M$12 + $L5*'Cancel Curves'!$L$12 + $M5*'Cancel Curves'!$K$12 + $N5*'Cancel Curves'!$J$12 + $O5*'Cancel Curves'!$I$12 + $P5*'Cancel Curves'!$H$12 + $Q5*'Cancel Curves'!$G$12 + $R5*'Cancel Curves'!$F$12 + $S5*'Cancel Curves'!$E$12 + $T5*'Cancel Curves'!$D$12 + $U5*'Cancel Curves'!$C$12 + $V5*'Cancel Curves'!$B$12 + 3982.1468 | W6: =$D5*'Cancel Curves'!$U$12 + $E5*'Cancel Curves'!$T$12 + $F5*'Cancel Curves'!$S$12 + $G5*'Cancel Curves'!$R$12 + $H5*'Cancel Curves'!$Q$12 + $I5*'Cancel Curves'!$P$12 + $J5*'Cancel Curves'!$O$12 + $K5*'Cancel Curves'!$N$12 + $L5*'Cancel Curves'!$M$12 + $M5*'Cancel Curves'!$L$12 + $N5*'Cancel Curves'!$K$12 + $O5*'Cancel Curves'!$J$12 + $P5*'Cancel Curves'!$I$12 + $Q5*'Cancel Curves'!$H$12 + $R5*'Cancel Curves'!$G$12 + $S5*'Cancel Curves'!$F$12 + $T5*'Cancel Curves'!$E$12 + $U5*'Cancel Curves'!$D$12 + $V5*'Cancel Curves'!$C$12 + $W5*'Cancel Curves'!$B$12 + 3266.8046 | X6: =$D5*'Cancel Curves'!$V$12 + $E5*'Cancel Curves'!$U$12 + $F5*'Cancel Curves'!$T$12 + $G5*'Cancel Curves'!$S$12 + $H5*'Cancel Curves'!$R$12 + $I5*'Cancel Curves'!$Q$12 + $J5*'Cancel Curves'!$P$12 + $K5*'Cancel Curves'!$O$12 + $L5*'Cancel Curves'!$N$12 + $M5*'Cancel Curves'!$M$12 + $N5*'Cancel Curves'!$L$12 + $O5*'Cancel Curves'!$K$12 + $P5*'Cancel Curves'!$J$12 + $Q5*'Cancel Curves'!$I$12 + $R5*'Cancel Curves'!$H$12 + $S5*'Cancel Curves'!$G$12 + $T5*'Cancel Curves'!$F$12 + $U5*'Cancel Curves'!$E$12 + $V5*'Cancel Curves'!$D$12 + $W5*'Cancel Curves'!$C$12 + $X5*'Cancel Curves'!$B$12 + 2495.0474 | Y6: =$D5*'Cancel Curves'!$W$12 + $E5*'Cancel Curves'!$V$12 + $F5*'Cancel Curves'!$U$12 + $G5*'Cancel Curves'!$T$12 + $H5*'Cancel Curves'!$S$12 + $I5*'Cancel Curves'!$R$12 + $J5*'Cancel Curves'!$Q$12 + $K5*'Cancel Curves'!$P$12 + $L5*'Cancel Curves'!$O$12 + $M5*'Cancel Curves'!$N$12 + $N5*'Cancel Curves'!$M$12 + $O5*'Cancel Curves'!$L$12 + $P5*'Cancel Curves'!$K$12 + $Q5*'Cancel Curves'!$J$12 + $R5*'Cancel Curves'!$I$12 + $S5*'Cancel Curves'!$H$12 + $T5*'Cancel Curves'!$G$12 + $U5*'Cancel Curves'!$F$12 + $V5*'Cancel Curves'!$E$12 + $W5*'Cancel Curves'!$D$12 + $X5*'Cancel Curves'!$C$12 + $Y5*'Cancel Curves'!$B$12 + 1606.6992 | Z6: =$D5*'Cancel Curves'!$X$12 + $E5*'Cancel Curves'!$W$12 + $F5*'Cancel Curves'!$V$12 + $G5*'Cancel Curves'!$U$12 + $H5*'Cancel Curves'!$T$12 + $I5*'Cancel Curves'!$S$12 + $J5*'Cancel Curves'!$R$12 + $K5*'Cancel Curves'!$Q$12 + $L5*'Cancel Curves'!$P$12 + $M5*'Cancel Curves'!$O$12 + $N5*'Cancel Curves'!$N$12 + $O5*'Cancel Curves'!$M$12 + $P5*'Cancel Curves'!$L$12 + $Q5*'Cancel Curves'!$K$12 + $R5*'Cancel Curves'!$J$12 + $S5*'Cancel Curves'!$I$12 + $T5*'Cancel Curves'!$H$12 + $U5*'Cancel Curves'!$G$12 + $V5*'Cancel Curves'!$F$12 + $W5*'Cancel Curves'!$E$12 + $X5*'Cancel Curves'!$D$12 + $Y5*'Cancel Curves'!$C$12 + $Z5*'Cancel Curves'!$B$12 + 783.4163 | AA6: =$D5*'Cancel Curves'!$Y$12 + $E5*'Cancel Curves'!$X$12 + $F5*'Cancel Curves'!$W$12 + $G5*'Cancel Curves'!$V$12 + $H5*'Cancel Curves'!$U$12 + $I5*'Cancel Curves'!$T$12 + $J5*'Cancel Curves'!$S$12 + $K5*'Cancel Curves'!$R$12 + $L5*'Cancel Curves'!$Q$12 + $M5*'Cancel Curves'!$P$12 + $N5*'Cancel Curves'!$O$12 + $O5*'Cancel Curves'!$N$12 + $P5*'Cancel Curves'!$M$12 + $Q5*'Cancel Curves'!$L$12 + $R5*'Cancel Curves'!$K$12 + $S5*'Cancel Curves'!$J$12 + $T5*'Cancel Curves'!$I$12 + $U5*'Cancel Curves'!$H$12 + $V5*'Cancel Curves'!$G$12 + $W5*'Cancel Curves'!$F$12 + $X5*'Cancel Curves'!$E$12 + $Y5*'Cancel Curves'!$D$12 + $Z5*'Cancel Curves'!$C$12 + $AA5*'Cancel Curves'!$B$12 | AB6: =$D5*'Cancel Curves'!$Z$12 + $E5*'Cancel Curves'!$Y$12 + $F5*'Cancel Curves'!$X$12 + $G5*'Cancel Curves'!$W$12 + $H5*'Cancel Curves'!$V$12 + $I5*'Cancel Curves'!$U$12 + $J5*'Cancel Curves'!$T$12 + $K5*'Cancel Curves'!$S$12 + $L5*'Cancel Curves'!$R$12 + $M5*'Cancel Curves'!$Q$12 + $N5*'Cancel Curves'!$P$12 + $O5*'Cancel Curves'!$O$12 + $P5*'Cancel Curves'!$N$12 + $Q5*'Cancel Curves'!$M$12 + $R5*'Cancel Curves'!$L$12 + $S5*'Cancel Curves'!$K$12 + $T5*'Cancel Curves'!$J$12 + $U5*'Cancel Curves'!$I$12 + $V5*'Cancel Curves'!$H$12 + $W5*'Cancel Curves'!$G$12 + $X5*'Cancel Curves'!$F$12 + $Y5*'Cancel Curves'!$E$12 + $Z5*'Cancel Curves'!$D$12 + $AA5*'Cancel Curves'!$C$12 + $AB5*'Cancel Curves'!$B$12 | AC6: =$D5*'Cancel Curves'!$AA$12 + $E5*'Cancel Curves'!$Z$12 + $F5*'Cancel Curves'!$Y$12 + $G5*'Cancel Curves'!$X$12 + $H5*'Cancel Curves'!$W$12 + $I5*'Cancel Curves'!$V$12 + $J5*'Cancel Curves'!$U$12 + $K5*'Cancel Curves'!$T$12 + $L5*'Cancel Curves'!$S$12 + $M5*'Cancel Curves'!$R$12 + $N5*'Cancel Curves'!$Q$12 + $O5*'Cancel Curves'!$P$12 + $P5*'Cancel Curves'!$O$12 + $Q5*'Cancel Curves'!$N$12 + $R5*'Cancel Curves'!$M$12 + $S5*'Cancel Curves'!$L$12 + $T5*'Cancel Curves'!$K$12 + $U5*'Cancel Curves'!$J$12 + $V5*'Cancel Curves'!$I$12 + $W5*'Cancel Curves'!$H$12 + $X5*'Cancel Curves'!$G$12 + $Y5*'Cancel Curves'!$F$12 + $Z5*'Cancel Curves'!$E$12 + $AA5*'Cancel Curves'!$D$12 + $AB5*'Cancel Curves'!$C$12 + $AC5*'Cancel Curves'!$B$12 | AD6: =$D5*'Cancel Curves'!$AB$12 + $E5*'Cancel Curves'!$AA$12 + $F5*'Cancel Curves'!$Z$12 + $G5*'Cancel Curves'!$Y$12 + $H5*'Cancel Curves'!$X$12 + $I5*'Cancel Curves'!$W$12 + $J5*'Cancel Curves'!$V$12 + $K5*'Cancel Curves'!$U$12 + $L5*'Cancel Curves'!$T$12 + $M5*'Cancel Curves'!$S$12 + $N5*'Cancel Curves'!$R$12 + $O5*'Cancel Curves'!$Q$12 + $P5*'Cancel Curves'!$P$12 + $Q5*'Cancel Curves'!$O$12 + $R5*'Cancel Curves'!$N$12 + $S5*'Cancel Curves'!$M$12 + $T5*'Cancel Curves'!$L$12 + $U5*'Cancel Curves'!$K$12 + $V5*'Cancel Curves'!$J$12 + $W5*'Cancel Curves'!$I$12 + $X5*'Cancel Curves'!$H$12 + $Y5*'Cancel Curves'!$G$12 + $Z5*'Cancel Curves'!$F$12 + $AA5*'Cancel Curves'!$E$12 + $AB5*'Cancel Curves'!$D$12 + $AC5*'Cancel Curves'!$C$12 + $AD5*'Cancel Curves'!$B$12 | AE6: =$D5*'Cancel Curves'!$AC$12 + $E5*'Cancel Curves'!$AB$12 + $F5*'Cancel Curves'!$AA$12 + $G5*'Cancel Curves'!$Z$12 + $H5*'Cancel Curves'!$Y$12 + $I5*'Cancel Curves'!$X$12 + $J5*'Cancel Curves'!$W$12 + $K5*'Cancel Curves'!$V$12 + $L5*'Cancel Curves'!$U$12 + $M5*'Cancel Curves'!$T$12 + $N5*'Cancel Curves'!$S$12 + $O5*'Cancel Curves'!$R$12 + $P5*'Cancel Curves'!$Q$12 + $Q5*'Cancel Curves'!$P$12 + $R5*'Cancel Curves'!$O$12 + $S5*'Cancel Curves'!$N$12 + $T5*'Cancel Curves'!$M$12 + $U5*'Cancel Curves'!$L$12 + $V5*'Cancel Curves'!$K$12 + $W5*'Cancel Curves'!$J$12 + $X5*'Cancel Curves'!$I$12 + $Y5*'Cancel Curves'!$H$12 + $Z5*'Cancel Curves'!$G$12 + $AA5*'Cancel Curves'!$F$12 + $AB5*'Cancel Curves'!$E$12 + $AC5*'Cancel Curves'!$D$12 + $AD5*'Cancel Curves'!$C$12 + $AE5*'Cancel Curves'!$B$12 | AF6: =$D5*'Cancel Curves'!$AD$12 + $E5*'Cancel Curves'!$AC$12 + $F5*'Cancel Curves'!$AB$12 + $G5*'Cancel Curves'!$AA$12 + $H5*'Cancel Curves'!$Z$12 + $I5*'Cancel Curves'!$Y$12 + $J5*'Cancel Curves'!$X$12 + $K5*'Cancel Curves'!$W$12 + $L5*'Cancel Curves'!$V$12 + $M5*'Cancel Curves'!$U$12 + $N5*'Cancel Curves'!$T$12 + $O5*'Cancel Curves'!$S$12 + $P5*'Cancel Curves'!$R$12 + $Q5*'Cancel Curves'!$Q$12 + $R5*'Cancel Curves'!$P$12 + $S5*'Cancel Curves'!$O$12 + $T5*'Cancel Curves'!$N$12 + $U5*'Cancel Curves'!$M$12 + $V5*'Cancel Curves'!$L$12 + $W5*'Cancel Curves'!$K$12 + $X5*'Cancel Curves'!$J$12 + $Y5*'Cancel Curves'!$I$12 + $Z5*'Cancel Curves'!$H$12 + $AA5*'Cancel Curves'!$G$12 + $AB5*'Cancel Curves'!$F$12 + $AC5*'Cancel Curves'!$E$12 + $AD5*'Cancel Curves'!$D$12 + $AE5*'Cancel Curves'!$C$12 + $AF5*'Cancel Curves'!$B$12 | AG6: =$D5*'Cancel Curves'!$AE$12 + $E5*'Cancel Curves'!$AD$12 + $F5*'Cancel Curves'!$AC$12 + $G5*'Cancel Curves'!$AB$12 + $H5*'Cancel Curves'!$AA$12 + $I5*'Cancel Curves'!$Z$12 + $J5*'Cancel Curves'!$Y$12 + $K5*'Cancel Curves'!$X$12 + $L5*'Cancel Curves'!$W$12 + $M5*'Cancel Curves'!$V$12 + $N5*'Cancel Curves'!$U$12 + $O5*'Cancel Curves'!$T$12 + $P5*'Cancel Curves'!$S$12 + $Q5*'Cancel Curves'!$R$12 + $R5*'Cancel Curves'!$Q$12 + $S5*'Cancel Curves'!$P$12 + $T5*'Cancel Curves'!$O$12 + $U5*'Cancel Curves'!$N$12 + $V5*'Cancel Curves'!$M$12 + $W5*'Cancel Curves'!$L$12 + $X5*'Cancel Curves'!$K$12 + $Y5*'Cancel Curves'!$J$12 + $Z5*'Cancel Curves'!$I$12 + $AA5*'Cancel Curves'!$H$12 + $AB5*'Cancel Curves'!$G$12 + $AC5*'Cancel Curves'!$F$12 + $AD5*'Cancel Curves'!$E$12 + $AE5*'Cancel Curves'!$D$12 + $AF5*'Cancel Curves'!$C$12 + $AG5*'Cancel Curves'!$B$12 | AH6: =$E5*'Cancel Curves'!$AE$12 + $F5*'Cancel Curves'!$AD$12 + $G5*'Cancel Curves'!$AC$12 + $H5*'Cancel Curves'!$AB$12 + $I5*'Cancel Curves'!$AA$12 + $J5*'Cancel Curves'!$Z$12 + $K5*'Cancel Curves'!$Y$12 + $L5*'Cancel Curves'!$X$12 + $M5*'Cancel Curves'!$W$12 + $N5*'Cancel Curves'!$V$12 + $O5*'Cancel Curves'!$U$12 + $P5*'Cancel Curves'!$T$12 + $Q5*'Cancel Curves'!$S$12 + $R5*'Cancel Curves'!$R$12 + $S5*'Cancel Curves'!$Q$12 + $T5*'Cancel Curves'!$P$12 + $U5*'Cancel Curves'!$O$12 + $V5*'Cancel Curves'!$N$12 + $W5*'Cancel Curves'!$M$12 + $X5*'Cancel Curves'!$L$12 + $Y5*'Cancel Curves'!$K$12 + $Z5*'Cancel Curves'!$J$12 + $AA5*'Cancel Curves'!$I$12 + $AB5*'Cancel Curves'!$H$12 + $AC5*'Cancel Curves'!$G$12 + $AD5*'Cancel Curves'!$F$12 + $AE5*'Cancel Curves'!$E$12 + $AF5*'Cancel Curves'!$D$12 + $AG5*'Cancel Curves'!$C$12 + $AH5*'Cancel Curves'!$B$12 | AI6: =$F5*'Cancel Curves'!$AE$12 + $G5*'Cancel Curves'!$AD$12 + $H5*'Cancel Curves'!$AC$12 + $I5*'Cancel Curves'!$AB$12 + $J5*'Cancel Curves'!$AA$12 + $K5*'Cancel Curves'!$Z$12 + $L5*'Cancel Curves'!$Y$12 + $M5*'Cancel Curves'!$X$12 + $N5*'Cancel Curves'!$W$12 + $O5*'Cancel Curves'!$V$12 + $P5*'Cancel Curves'!$U$12 + $Q5*'Cancel Curves'!$T$12 + $R5*'Cancel Curves'!$S$12 + $S5*'Cancel Curves'!$R$12 + $T5*'Cancel Curves'!$Q$12 + $U5*'Cancel Curves'!$P$12 + $V5*'Cancel Curves'!$O$12 + $W5*'Cancel Curves'!$N$12 + $X5*'Cancel Curves'!$M$12 + $Y5*'Cancel Curves'!$L$12 + $Z5*'Cancel Curves'!$K$12 + $AA5*'Cancel Curves'!$J$12 + $AB5*'Cancel Curves'!$I$12 + $AC5*'Cancel Curves'!$H$12 + $AD5*'Cancel Curves'!$G$12 + $AE5*'Cancel Curves'!$F$12 + $AF5*'Cancel Curves'!$E$12 + $AG5*'Cancel Curves'!$D$12 + $AH5*'Cancel Curves'!$C$12 + $AI5*'Cancel Curves'!$B$12 | AJ6: =$G5*'Cancel Curves'!$AE$12 + $H5*'Cancel Curves'!$AD$12 + $I5*'Cancel Curves'!$AC$12 + $J5*'Cancel Curves'!$AB$12 + $K5*'Cancel Curves'!$AA$12 + $L5*'Cancel Curves'!$Z$12 + $M5*'Cancel Curves'!$Y$12 + $N5*'Cancel Curves'!$X$12 + $O5*'Cancel Curves'!$W$12 + $P5*'Cancel Curves'!$V$12 + $Q5*'Cancel Curves'!$U$12 + $R5*'Cancel Curves'!$T$12 + $S5*'Cancel Curves'!$S$12 + $T5*'Cancel Curves'!$R$12 + $U5*'Cancel Curves'!$Q$12 + $V5*'Cancel Curves'!$P$12 + $W5*'Cancel Curves'!$O$12 + $X5*'Cancel Curves'!$N$12 + $Y5*'Cancel Curves'!$M$12 + $Z5*'Cancel Curves'!$L$12 + $AA5*'Cancel Curves'!$K$12 + $AB5*'Cancel Curves'!$J$12 + $AC5*'Cancel Curves'!$I$12 + $AD5*'Cancel Curves'!$H$12 + $AE5*'Cancel Curves'!$G$12 + $AF5*'Cancel Curves'!$F$12 + $AG5*'Cancel Curves'!$E$12 + $AH5*'Cancel Curves'!$D$12 + $AI5*'Cancel Curves'!$C$12 + $AJ5*'Cancel Curves'!$B$12 | AK6: =$H5*'Cancel Curves'!$AE$12 + $I5*'Cancel Curves'!$AD$12 + $J5*'Cancel Curves'!$AC$12 + $K5*'Cancel Curves'!$AB$12 + $L5*'Cancel Curves'!$AA$12 + $M5*'Cancel Curves'!$Z$12 + $N5*'Cancel Curves'!$Y$12 + $O5*'Cancel Curves'!$X$12 + $P5*'Cancel Curves'!$W$12 + $Q5*'Cancel Curves'!$V$12 + $R5*'Cancel Curves'!$U$12 + $S5*'Cancel Curves'!$T$12 + $T5*'Cancel Curves'!$S$12 + $U5*'Cancel Curves'!$R$12 + $V5*'Cancel Curves'!$Q$12 + $W5*'Cancel Curves'!$P$12 + $X5*'Cancel Curves'!$O$12 + $Y5*'Cancel Curves'!$N$12 + $Z5*'Cancel Curves'!$M$12 + $AA5*'Cancel Curves'!$L$12 + $AB5*'Cancel Curves'!$K$12 + $AC5*'Cancel Curves'!$J$12 + $AD5*'Cancel Curves'!$I$12 + $AE5*'Cancel Curves'!$H$12 + $AF5*'Cancel Curves'!$G$12 + $AG5*'Cancel Curves'!$F$12 + $AH5*'Cancel Curves'!$E$12 + $AI5*'Cancel Curves'!$D$12 + $AJ5*'Cancel Curves'!$C$12 + $AK5*'Cancel Curves'!$B$12 | AL6: =$I5*'Cancel Curves'!$AE$12 + $J5*'Cancel Curves'!$AD$12 + $K5*'Cancel Curves'!$AC$12 + $L5*'Cancel Curves'!$AB$12 + $M5*'Cancel Curves'!$AA$12 + $N5*'Cancel Curves'!$Z$12 + $O5*'Cancel Curves'!$Y$12 + $P5*'Cancel Curves'!$X$12 + $Q5*'Cancel Curves'!$W$12 + $R5*'Cancel Curves'!$V$12 + $S5*'Cancel Curves'!$U$12 + $T5*'Cancel Curves'!$T$12 + $U5*'Cancel Curves'!$S$12 + $V5*'Cancel Curves'!$R$12 + $W5*'Cancel Curves'!$Q$12 + $X5*'Cancel Curves'!$P$12 + $Y5*'Cancel Curves'!$O$12 + $Z5*'Cancel Curves'!$N$12 + $AA5*'Cancel Curves'!$M$12 + $AB5*'Cancel Curves'!$L$12 + $AC5*'Cancel Curves'!$K$12 + $AD5*'Cancel Curves'!$J$12 + $AE5*'Cancel Curves'!$I$12 + $AF5*'Cancel Curves'!$H$12 + $AG5*'Cancel Curves'!$G$12 + $AH5*'Cancel Curves'!$F$12 + $AI5*'Cancel Curves'!$E$12 + $AJ5*'Cancel Curves'!$D$12 + $AK5*'Cancel Curves'!$C$12 + $AL5*'Cancel Curves'!$B$12 | AM6: =$J5*'Cancel Curves'!$AE$12 + $K5*'Cancel Curves'!$AD$12 + $L5*'Cancel Curves'!$AC$12 + $M5*'Cancel Curves'!$AB$12 + $N5*'Cancel Curves'!$AA$12 + $O5*'Cancel Curves'!$Z$12 + $P5*'Cancel Curves'!$Y$12 + $Q5*'Cancel Curves'!$X$12 + $R5*'Cancel Curves'!$W$12 + $S5*'Cancel Curves'!$V$12 + $T5*'Cancel Curves'!$U$12 + $U5*'Cancel Curves'!$T$12 + $V5*'Cancel Curves'!$S$12 + $W5*'Cancel Curves'!$R$12 + $X5*'Cancel Curves'!$Q$12 + $Y5*'Cancel Curves'!$P$12 + $Z5*'Cancel Curves'!$O$12 + $AA5*'Cancel Curves'!$N$12 + $AB5*'Cancel Curves'!$M$12 + $AC5*'Cancel Curves'!$L$12 + $AD5*'Cancel Curves'!$K$12 + $AE5*'Cancel Curves'!$J$12 + $AF5*'Cancel Curves'!$I$12 + $AG5*'Cancel Curves'!$H$12 + $AH5*'Cancel Curves'!$G$12 + $AI5*'Cancel Curves'!$F$12 + $AJ5*'Cancel Curves'!$E$12 + $AK5*'Cancel Curves'!$D$12 + $AL5*'Cancel Curves'!$C$12 + $AM5*'Cancel Curves'!$B$12 | AN6: =$K5*'Cancel Curves'!$AE$12 + $L5*'Cancel Curves'!$AD$12 + $M5*'Cancel Curves'!$AC$12 + $N5*'Cancel Curves'!$AB$12 + $O5*'Cancel Curves'!$AA$12 + $P5*'Cancel Curves'!$Z$12 + $Q5*'Cancel Curves'!$Y$12 + $R5*'Cancel Curves'!$X$12 + $S5*'Cancel Curves'!$W$12 + $T5*'Cancel Curves'!$V$12 + $U5*'Cancel Curves'!$U$12 + $V5*'Cancel Curves'!$T$12 + $W5*'Cancel Curves'!$S$12 + $X5*'Cancel Curves'!$R$12 + $Y5*'Cancel Curves'!$Q$12 + $Z5*'Cancel Curves'!$P$12 + $AA5*'Cancel Curves'!$O$12 + $AB5*'Cancel Curves'!$N$12 + $AC5*'Cancel Curves'!$M$12 + $AD5*'Cancel Curves'!$L$12 + $AE5*'Cancel Curves'!$K$12 + $AF5*'Cancel Curves'!$J$12 + $AG5*'Cancel Curves'!$I$12 + $AH5*'Cancel Curves'!$H$12 + $AI5*'Cancel Curves'!$G$12 + $AJ5*'Cancel Curves'!$F$12 + $AK5*'Cancel Curves'!$E$12 + $AL5*'Cancel Curves'!$D$12 + $AM5*'Cancel Curves'!$C$12 + $AN5*'Cancel Curves'!$B$12 | AO6: =$L5*'Cancel Curves'!$AE$12 + $M5*'Cancel Curves'!$AD$12 + $N5*'Cancel Curves'!$AC$12 + $O5*'Cancel Curves'!$AB$12 + $P5*'Cancel Curves'!$AA$12 + $Q5*'Cancel Curves'!$Z$12 + $R5*'Cancel Curves'!$Y$12 + $S5*'Cancel Curves'!$X$12 + $T5*'Cancel Curves'!$W$12 + $U5*'Cancel Curves'!$V$12 + $V5*'Cancel Curves'!$U$12 + $W5*'Cancel Curves'!$T$12 + $X5*'Cancel Curves'!$S$12 + $Y5*'Cancel Curves'!$R$12 + $Z5*'Cancel Curves'!$Q$12 + $AA5*'Cancel Curves'!$P$12 + $AB5*'Cancel Curves'!$O$12 + $AC5*'Cancel Curves'!$N$12 + $AD5*'Cancel Curves'!$M$12 + $AE5*'Cancel Curves'!$L$12 + $AF5*'Cancel Curves'!$K$12 + $AG5*'Cancel Curves'!$J$12 + $AH5*'Cancel Curves'!$I$12 + $AI5*'Cancel Curves'!$H$12 + $AJ5*'Cancel Curves'!$G$12 + $AK5*'Cancel Curves'!$F$12 + $AL5*'Cancel Curves'!$E$12 + $AM5*'Cancel Curves'!$D$12 + $AN5*'Cancel Curves'!$C$12 + $AO5*'Cancel Curves'!$B$12 | AP6: =$M5*'Cancel Curves'!$AE$12 + $N5*'Cancel Curves'!$AD$12 + $O5*'Cancel Curves'!$AC$12 + $P5*'Cancel Curves'!$AB$12 + $Q5*'Cancel Curves'!$AA$12 + $R5*'Cancel Curves'!$Z$12 + $S5*'Cancel Curves'!$Y$12 + $T5*'Cancel Curves'!$X$12 + $U5*'Cancel Curves'!$W$12 + $V5*'Cancel Curves'!$V$12 + $W5*'Cancel Curves'!$U$12 + $X5*'Cancel Curves'!$T$12 + $Y5*'Cancel Curves'!$S$12 + $Z5*'Cancel Curves'!$R$12 + $AA5*'Cancel Curves'!$Q$12 + $AB5*'Cancel Curves'!$P$12 + $AC5*'Cancel Curves'!$O$12 + $AD5*'Cancel Curves'!$N$12 + $AE5*'Cancel Curves'!$M$12 + $AF5*'Cancel Curves'!$L$12 + $AG5*'Cancel Curves'!$K$12 + $AH5*'Cancel Curves'!$J$12 + $AI5*'Cancel Curves'!$I$12 + $AJ5*'Cancel Curves'!$H$12 + $AK5*'Cancel Curves'!$G$12 + $AL5*'Cancel Curves'!$F$12 + $AM5*'Cancel Curves'!$E$12 + $AN5*'Cancel Curves'!$D$12 + $AO5*'Cancel Curves'!$C$12 + $AP5*'Cancel Curves'!$B$12 | AQ6: =$N5*'Cancel Curves'!$AE$12 + $O5*'Cancel Curves'!$AD$12 + $P5*'Cancel Curves'!$AC$12 + $Q5*'Cancel Curves'!$AB$12 + $R5*'Cancel Curves'!$AA$12 + $S5*'Cancel Curves'!$Z$12 + $T5*'Cancel Curves'!$Y$12 + $U5*'Cancel Curves'!$X$12 + $V5*'Cancel Curves'!$W$12 + $W5*'Cancel Curves'!$V$12 + $X5*'Cancel Curves'!$U$12 + $Y5*'Cancel Curves'!$T$12 + $Z5*'Cancel Curves'!$S$12 + $AA5*'Cancel Curves'!$R$12 + $AB5*'Cancel Curves'!$Q$12 + $AC5*'Cancel Curves'!$P$12 + $AD5*'Cancel Curves'!$O$12 + $AE5*'Cancel Curves'!$N$12 + $AF5*'Cancel Curves'!$M$12 + $AG5*'Cancel Curves'!$L$12 + $AH5*'Cancel Curves'!$K$12 + $AI5*'Cancel Curves'!$J$12 + $AJ5*'Cancel Curves'!$I$12 + $AK5*'Cancel Curves'!$H$12 + $AL5*'Cancel Curves'!$G$12 + $AM5*'Cancel Curves'!$F$12 + $AN5*'Cancel Curves'!$E$12 + $AO5*'Cancel Curves'!$D$12 + $AP5*'Cancel Curves'!$C$12 + $AQ5*'Cancel Curves'!$B$12 | AR6: =$O5*'Cancel Curves'!$AE$12 + $P5*'Cancel Curves'!$AD$12 + $Q5*'Cancel Curves'!$AC$12 + $R5*'Cancel Curves'!$AB$12 + $S5*'Cancel Curves'!$AA$12 + $T5*'Cancel Curves'!$Z$12 + $U5*'Cancel Curves'!$Y$12 + $V5*'Cancel Curves'!$X$12 + $W5*'Cancel Curves'!$W$12 + $X5*'Cancel Curves'!$V$12 + $Y5*'Cancel Curves'!$U$12 + $Z5*'Cancel Curves'!$T$12 + $AA5*'Cancel Curves'!$S$12 + $AB5*'Cancel Curves'!$R$12 + $AC5*'Cancel Curves'!$Q$12 + $AD5*'Cancel Curves'!$P$12 + $AE5*'Cancel Curves'!$O$12 + $AF5*'Cancel Curves'!$N$12 + $AG5*'Cancel Curves'!$M$12 + $AH5*'Cancel Curves'!$L$12 + $AI5*'Cancel Curves'!$K$12 + $AJ5*'Cancel Curves'!$J$12 + $AK5*'Cancel Curves'!$I$12 + $AL5*'Cancel Curves'!$H$12 + $AM5*'Cancel Curves'!$G$12 + $AN5*'Cancel Curves'!$F$12 + $AO5*'Cancel Curves'!$E$12 + $AP5*'Cancel Curves'!$D$12 + $AQ5*'Cancel Curves'!$C$12 + $AR5*'Cancel Curves'!$B$12 | AS6: =$P5*'Cancel Curves'!$AE$12 + $Q5*'Cancel Curves'!$AD$12 + $R5*'Cancel Curves'!$AC$12 + $S5*'Cancel Curves'!$AB$12 + $T5*'Cancel Curves'!$AA$12 + $U5*'Cancel Curves'!$Z$12 + $V5*'Cancel Curves'!$Y$12 + $W5*'Cancel Curves'!$X$12 + $X5*'Cancel Curves'!$W$12 + $Y5*'Cancel Curves'!$V$12 + $Z5*'Cancel Curves'!$U$12 + $AA5*'Cancel Curves'!$T$12 + $AB5*'Cancel Curves'!$S$12 + $AC5*'Cancel Curves'!$R$12 + $AD5*'Cancel Curves'!$Q$12 + $AE5*'Cancel Curves'!$P$12 + $AF5*'Cancel Curves'!$O$12 + $AG5*'Cancel Curves'!$N$12 + $AH5*'Cancel Curves'!$M$12 + $AI5*'Cancel Curves'!$L$12 + $AJ5*'Cancel Curves'!$K$12 + $AK5*'Cancel Curves'!$J$12 + $AL5*'Cancel Curves'!$I$12 + $AM5*'Cancel Curves'!$H$12 + $AN5*'Cancel Curves'!$G$12 + $AO5*'Cancel Curves'!$F$12 + $AP5*'Cancel Curves'!$E$12 + $AQ5*'Cancel Curves'!$D$12 + $AR5*'Cancel Curves'!$C$12 + $AS5*'Cancel Curves'!$B$12 | AT6: =$Q5*'Cancel Curves'!$AE$12 + $R5*'Cancel Curves'!$AD$12 + $S5*'Cancel Curves'!$AC$12 + $T5*'Cancel Curves'!$AB$12 + $U5*'Cancel Curves'!$AA$12 + $V5*'Cancel Curves'!$Z$12 + $W5*'Cancel Curves'!$Y$12 + $X5*'Cancel Curves'!$X$12 + $Y5*'Cancel Curves'!$W$12 + $Z5*'Cancel Curves'!$V$12 + $AA5*'Cancel Curves'!$U$12 + $AB5*'Cancel Curves'!$T$12 + $AC5*'Cancel Curves'!$S$12 + $AD5*'Cancel Curves'!$R$12 + $AE5*'Cancel Curves'!$Q$12 + $AF5*'Cancel Curves'!$P$12 + $AG5*'Cancel Curves'!$O$12 + $AH5*'Cancel Curves'!$N$12 + $AI5*'Cancel Curves'!$M$12 + $AJ5*'Cancel Curves'!$L$12 + $AK5*'Cancel Curves'!$K$12 + $AL5*'Cancel Curves'!$J$12 + $AM5*'Cancel Curves'!$I$12 + $AN5*'Cancel Curves'!$H$12 + $AO5*'Cancel Curves'!$G$12 + $AP5*'Cancel Curves'!$F$12 + $AQ5*'Cancel Curves'!$E$12 + $AR5*'Cancel Curves'!$D$12 + $AS5*'Cancel Curves'!$C$12 + $AT5*'Cancel Curves'!$B$12 | AU6: =$R5*'Cancel Curves'!$AE$12 + $S5*'Cancel Curves'!$AD$12 + $T5*'Cancel Curves'!$AC$12 + $U5*'Cancel Curves'!$AB$12 + $V5*'Cancel Curves'!$AA$12 + $W5*'Cancel Curves'!$Z$12 + $X5*'Cancel Curves'!$Y$12 + $Y5*'Cancel Curves'!$X$12 + $Z5*'Cancel Curves'!$W$12 + $AA5*'Cancel Curves'!$V$12 + $AB5*'Cancel Curves'!$U$12 + $AC5*'Cancel Curves'!$T$12 + $AD5*'Cancel Curves'!$S$12 + $AE5*'Cancel Curves'!$R$12 + $AF5*'Cancel Curves'!$Q$12 + $AG5*'Cancel Curves'!$P$12 + $AH5*'Cancel Curves'!$O$12 + $AI5*'Cancel Curves'!$N$12 + $AJ5*'Cancel Curves'!$M$12 + $AK5*'Cancel Curves'!$L$12 + $AL5*'Cancel Curves'!$K$12 + $AM5*'Cancel Curves'!$J$12 + $AN5*'Cancel Curves'!$I$12 + $AO5*'Cancel Curves'!$H$12 + $AP5*'Cancel Curves'!$G$12 + $AQ5*'Cancel Curves'!$F$12 + $AR5*'Cancel Curves'!$E$12 + $AS5*'Cancel Curves'!$D$12 + $AT5*'Cancel Curves'!$C$12 + $AU5*'Cancel Curves'!$B$12 | AV6: =$S5*'Cancel Curves'!$AE$12 + $T5*'Cancel Curves'!$AD$12 + $U5*'Cancel Curves'!$AC$12 + $V5*'Cancel Curves'!$AB$12 + $W5*'Cancel Curves'!$AA$12 + $X5*'Cancel Curves'!$Z$12 + $Y5*'Cancel Curves'!$Y$12 + $Z5*'Cancel Curves'!$X$12 + $AA5*'Cancel Curves'!$W$12 + $AB5*'Cancel Curves'!$V$12 + $AC5*'Cancel Curves'!$U$12 + $AD5*'Cancel Curves'!$T$12 + $AE5*'Cancel Curves'!$S$12 + $AF5*'Cancel Curves'!$R$12 + $AG5*'Cancel Curves'!$Q$12 + $AH5*'Cancel Curves'!$P$12 + $AI5*'Cancel Curves'!$O$12 + $AJ5*'Cancel Curves'!$N$12 + $AK5*'Cancel Curves'!$M$12 + $AL5*'Cancel Curves'!$L$12 + $AM5*'Cancel Curves'!$K$12 + $AN5*'Cancel Curves'!$J$12 + $AO5*'Cancel Curves'!$I$12 + $AP5*'Cancel Curves'!$H$12 + $AQ5*'Cancel Curves'!$G$12 + $AR5*'Cancel Curves'!$F$12 + $AS5*'Cancel Curves'!$E$12 + $AT5*'Cancel Curves'!$D$12 + $AU5*'Cancel Curves'!$C$12 + $AV5*'Cancel Curves'!$B$12 | AW6: =$T5*'Cancel Curves'!$AE$12 + $U5*'Cancel Curves'!$AD$12 + $V5*'Cancel Curves'!$AC$12 + $W5*'Cancel Curves'!$AB$12 + $X5*'Cancel Curves'!$AA$12 + $Y5*'Cancel Curves'!$Z$12 + $Z5*'Cancel Curves'!$Y$12 + $AA5*'Cancel Curves'!$X$12 + $AB5*'Cancel Curves'!$W$12 + $AC5*'Cancel Curves'!$V$12 + $AD5*'Cancel Curves'!$U$12 + $AE5*'Cancel Curves'!$T$12 + $AF5*'Cancel Curves'!$S$12 + $AG5*'Cancel Curves'!$R$12 + $AH5*'Cancel Curves'!$Q$12 + $AI5*'Cancel Curves'!$P$12 + $AJ5*'Cancel Curves'!$O$12 + $AK5*'Cancel Curves'!$N$12 + $AL5*'Cancel Curves'!$M$12 + $AM5*'Cancel Curves'!$L$12 + $AN5*'Cancel Curves'!$K$12 + $AO5*'Cancel Curves'!$J$12 + $AP5*'Cancel Curves'!$I$12 + $AQ5*'Cancel Curves'!$H$12 + $AR5*'Cancel Curves'!$G$12 + $AS5*'Cancel Curves'!$F$12 + $AT5*'Cancel Curves'!$E$12 + $AU5*'Cancel Curves'!$D$12 + $AV5*'Cancel Curves'!$C$12 + $AW5*'Cancel Curves'!$B$12 | AX6: =$U5*'Cancel Curves'!$AE$12 + $V5*'Cancel Curves'!$AD$12 + $W5*'Cancel Curves'!$AC$12 + $X5*'Cancel Curves'!$AB$12 + $Y5*'Cancel Curves'!$AA$12 + $Z5*'Cancel Curves'!$Z$12 + $AA5*'Cancel Curves'!$Y$12 + $AB5*'Cancel Curves'!$X$12 + $AC5*'Cancel Curves'!$W$12 + $AD5*'Cancel Curves'!$V$12 + $AE5*'Cancel Curves'!$U$12 + $AF5*'Cancel Curves'!$T$12 + $AG5*'Cancel Curves'!$S$12 + $AH5*'Cancel Curves'!$R$12 + $AI5*'Cancel Curves'!$Q$12 + $AJ5*'Cancel Curves'!$P$12 + $AK5*'Cancel Curves'!$O$12 + $AL5*'Cancel Curves'!$N$12 + $AM5*'Cancel Curves'!$M$12 + $AN5*'Cancel Curves'!$L$12 + $AO5*'Cancel Curves'!$K$12 + $AP5*'Cancel Curves'!$J$12 + $AQ5*'Cancel Curves'!$I$12 + $AR5*'Cancel Curves'!$H$12 + $AS5*'Cancel Curves'!$G$12 + $AT5*'Cancel Curves'!$F$12 + $AU5*'Cancel Curves'!$E$12 + $AV5*'Cancel Curves'!$D$12 + $AW5*'Cancel Curves'!$C$12 + $AX5*'Cancel Curves'!$B$12 | AY6: =$V5*'Cancel Curves'!$AE$12 + $W5*'Cancel Curves'!$AD$12 + $X5*'Cancel Curves'!$AC$12 + $Y5*'Cancel Curves'!$AB$12 + $Z5*'Cancel Curves'!$AA$12 + $AA5*'Cancel Curves'!$Z$12 + $AB5*'Cancel Curves'!$Y$12 + $AC5*'Cancel Curves'!$X$12 + $AD5*'Cancel Curves'!$W$12 + $AE5*'Cancel Curves'!$V$12 + $AF5*'Cancel Curves'!$U$12 + $AG5*'Cancel Curves'!$T$12 + $AH5*'Cancel Curves'!$S$12 + $AI5*'Cancel Curves'!$R$12 + $AJ5*'Cancel Curves'!$Q$12 + $AK5*'Cancel Curves'!$P$12 + $AL5*'Cancel Curves'!$O$12 + $AM5*'Cancel Curves'!$N$12 + $AN5*'Cancel Curves'!$M$12 + $AO5*'Cancel Curves'!$L$12 + $AP5*'Cancel Curves'!$K$12 + $AQ5*'Cancel Curves'!$J$12 + $AR5*'Cancel Curves'!$I$12 + $AS5*'Cancel Curves'!$H$12 + $AT5*'Cancel Curves'!$G$12 + $AU5*'Cancel Curves'!$F$12 + $AV5*'Cancel Curves'!$E$12 + $AW5*'Cancel Curves'!$D$12 + $AX5*'Cancel Curves'!$C$12 + $AY5*'Cancel Curves'!$B$12 | AZ6: =$W5*'Cancel Curves'!$AE$12 + $X5*'Cancel Curves'!$AD$12 + $Y5*'Cancel Curves'!$AC$12 + $Z5*'Cancel Curves'!$AB$12 + $AA5*'Cancel Curves'!$AA$12 + $AB5*'Cancel Curves'!$Z$12 + $AC5*'Cancel Curves'!$Y$12 + $AD5*'Cancel Curves'!$X$12 + $AE5*'Cancel Curves'!$W$12 + $AF5*'Cancel Curves'!$V$12 + $AG5*'Cancel Curves'!$U$12 + $AH5*'Cancel Curves'!$T$12 + $AI5*'Cancel Curves'!$S$12 + $AJ5*'Cancel Curves'!$R$12 + $AK5*'Cancel Curves'!$Q$12 + $AL5*'Cancel Curves'!$P$12 + $AM5*'Cancel Curves'!$O$12 + $AN5*'Cancel Curves'!$N$12 + $AO5*'Cancel Curves'!$M$12 + $AP5*'Cancel Curves'!$L$12 + $AQ5*'Cancel Curves'!$K$12 + $AR5*'Cancel Curves'!$J$12 + $AS5*'Cancel Curves'!$I$12 + $AT5*'Cancel Curves'!$H$12 + $AU5*'Cancel Curves'!$G$12 + $AV5*'Cancel Curves'!$F$12 + $AW5*'Cancel Curves'!$E$12 + $AX5*'Cancel Curves'!$D$12 + $AY5*'Cancel Curves'!$C$12 + $AZ5*'Cancel Curves'!$B$12 | BA6: =$X5*'Cancel Curves'!$AE$12 + $Y5*'Cancel Curves'!$AD$12 + $Z5*'Cancel Curves'!$AC$12 + $AA5*'Cancel Curves'!$AB$12 + $AB5*'Cancel Curves'!$AA$12 + $AC5*'Cancel Curves'!$Z$12 + $AD5*'Cancel Curves'!$Y$12 + $AE5*'Cancel Curves'!$X$12 + $AF5*'Cancel Curves'!$W$12 + $AG5*'Cancel Curves'!$V$12 + $AH5*'Cancel Curves'!$U$12 + $AI5*'Cancel Curves'!$T$12 + $AJ5*'Cancel Curves'!$S$12 + $AK5*'Cancel Curves'!$R$12 + $AL5*'Cancel Curves'!$Q$12 + $AM5*'Cancel Curves'!$P$12 + $AN5*'Cancel Curves'!$O$12 + $AO5*'Cancel Curves'!$N$12 + $AP5*'Cancel Curves'!$M$12 + $AQ5*'Cancel Curves'!$L$12 + $AR5*'Cancel Curves'!$K$12 + $AS5*'Cancel Curves'!$J$12 + $AT5*'Cancel Curves'!$I$12 + $AU5*'Cancel Curves'!$H$12 + $AV5*'Cancel Curves'!$G$12 + $AW5*'Cancel Curves'!$F$12 + $AX5*'Cancel Curves'!$E$12 + $AY5*'Cancel Curves'!$D$12 + $AZ5*'Cancel Curves'!$C$12 + $BA5*'Cancel Curves'!$B$12 | BB6: =$Y5*'Cancel Curves'!$AE$12 + $Z5*'Cancel Curves'!$AD$12 + $AA5*'Cancel Curves'!$AC$12 + $AB5*'Cancel Curves'!$AB$12 + $AC5*'Cancel Curves'!$AA$12 + $AD5*'Cancel Curves'!$Z$12 + $AE5*'Cancel Curves'!$Y$12 + $AF5*'Cancel Curves'!$X$12 + $AG5*'Cancel Curves'!$W$12 + $AH5*'Cancel Curves'!$V$12 + $AI5*'Cancel Curves'!$U$12 + $AJ5*'Cancel Curves'!$T$12 + $AK5*'Cancel Curves'!$S$12 + $AL5*'Cancel Curves'!$R$12 + $AM5*'Cancel Curves'!$Q$12 + $AN5*'Cancel Curves'!$P$12 + $AO5*'Cancel Curves'!$O$12 + $AP5*'Cancel Curves'!$N$12 + $AQ5*'Cancel Curves'!$M$12 + $AR5*'Cancel Curves'!$L$12 + $AS5*'Cancel Curves'!$K$12 + $AT5*'Cancel Curves'!$J$12 + $AU5*'Cancel Curves'!$I$12 + $AV5*'Cancel Curves'!$H$12 + $AW5*'Cancel Curves'!$G$12 + $AX5*'Cancel Curves'!$F$12 + $AY5*'Cancel Curves'!$E$12 + $AZ5*'Cancel Curves'!$D$12 + $BA5*'Cancel Curves'!$C$12 + $BB5*'Cancel Curves'!$B$12 | BC6: =$Z5*'Cancel Curves'!$AE$12 + $AA5*'Cancel Curves'!$AD$12 + $AB5*'Cancel Curves'!$AC$12 + $AC5*'Cancel Curves'!$AB$12 + $AD5*'Cancel Curves'!$AA$12 + $AE5*'Cancel Curves'!$Z$12 + $AF5*'Cancel Curves'!$Y$12 + $AG5*'Cancel Curves'!$X$12 + $AH5*'Cancel Curves'!$W$12 + $AI5*'Cancel Curves'!$V$12 + $AJ5*'Cancel Curves'!$U$12 + $AK5*'Cancel Curves'!$T$12 + $AL5*'Cancel Curves'!$S$12 + $AM5*'Cancel Curves'!$R$12 + $AN5*'Cancel Curves'!$Q$12 + $AO5*'Cancel Curves'!$P$12 + $AP5*'Cancel Curves'!$O$12 + $AQ5*'Cancel Curves'!$N$12 + $AR5*'Cancel Curves'!$M$12 + $AS5*'Cancel Curves'!$L$12 + $AT5*'Cancel Curves'!$K$12 + $AU5*'Cancel Curves'!$J$12 + $AV5*'Cancel Curves'!$I$12 + $AW5*'Cancel Curves'!$H$12 + $AX5*'Cancel Curves'!$G$12 + $AY5*'Cancel Curves'!$F$12 + $AZ5*'Cancel Curves'!$E$12 + $BA5*'Cancel Curves'!$D$12 + $BB5*'Cancel Curves'!$C$12 + $BC5*'Cancel Curves'!$B$12 | BD6: =$AA5*'Cancel Curves'!$AE$12 + $AB5*'Cancel Curves'!$AD$12 + $AC5*'Cancel Curves'!$AC$12 + $AD5*'Cancel Curves'!$AB$12 + $AE5*'Cancel Curves'!$AA$12 + $AF5*'Cancel Curves'!$Z$12 + $AG5*'Cancel Curves'!$Y$12 + $AH5*'Cancel Curves'!$X$12 + $AI5*'Cancel Curves'!$W$12 + $AJ5*'Cancel Curves'!$V$12 + $AK5*'Cancel Curves'!$U$12 + $AL5*'Cancel Curves'!$T$12 + $AM5*'Cancel Curves'!$S$12 + $AN5*'Cancel Curves'!$R$12 + $AO5*'Cancel Curves'!$Q$12 + $AP5*'Cancel Curves'!$P$12 + $AQ5*'Cancel Curves'!$O$12 + $AR5*'Cancel Curves'!$N$12 + $AS5*'Cancel Curves'!$M$12 + $AT5*'Cancel Curves'!$L$12 + $AU5*'Cancel Curves'!$K$12 + $AV5*'Cancel Curves'!$J$12 + $AW5*'Cancel Curves'!$I$12 + $AX5*'Cancel Curves'!$H$12 + $AY5*'Cancel Curves'!$G$12 + $AZ5*'Cancel Curves'!$F$12 + $BA5*'Cancel Curves'!$E$12 + $BB5*'Cancel Curves'!$D$12 + $BC5*'Cancel Curves'!$C$12 + $BD5*'Cancel Curves'!$B$12 | BE6: =$AB5*'Cancel Curves'!$AE$12 + $AC5*'Cancel Curves'!$AD$12 + $AD5*'Cancel Curves'!$AC$12 + $AE5*'Cancel Curves'!$AB$12 + $AF5*'Cancel Curves'!$AA$12 + $AG5*'Cancel Curves'!$Z$12 + $AH5*'Cancel Curves'!$Y$12 + $AI5*'Cancel Curves'!$X$12 + $AJ5*'Cancel Curves'!$W$12 + $AK5*'Cancel Curves'!$V$12 + $AL5*'Cancel Curves'!$U$12 + $AM5*'Cancel Curves'!$T$12 + $AN5*'Cancel Curves'!$S$12 + $AO5*'Cancel Curves'!$R$12 + $AP5*'Cancel Curves'!$Q$12 + $AQ5*'Cancel Curves'!$P$12 + $AR5*'Cancel Curves'!$O$12 + $AS5*'Cancel Curves'!$N$12 + $AT5*'Cancel Curves'!$M$12 + $AU5*'Cancel Curves'!$L$12 + $AV5*'Cancel Curves'!$K$12 + $AW5*'Cancel Curves'!$J$12 + $AX5*'Cancel Curves'!$I$12 + $AY5*'Cancel Curves'!$H$12 + $AZ5*'Cancel Curves'!$G$12 + $BA5*'Cancel Curves'!$F$12 + $BB5*'Cancel Curves'!$E$12 + $BC5*'Cancel Curves'!$D$12 + $BD5*'Cancel Curves'!$C$12 + $BE5*'Cancel Curves'!$B$12 | BF6: =$AC5*'Cancel Curves'!$AE$12 + $AD5*'Cancel Curves'!$AD$12 + $AE5*'Cancel Curves'!$AC$12 + $AF5*'Cancel Curves'!$AB$12 + $AG5*'Cancel Curves'!$AA$12 + $AH5*'Cancel Curves'!$Z$12 + $AI5*'Cancel Curves'!$Y$12 + $AJ5*'Cancel Curves'!$X$12 + $AK5*'Cancel Curves'!$W$12 + $AL5*'Cancel Curves'!$V$12 + $AM5*'Cancel Curves'!$U$12 + $AN5*'Cancel Curves'!$T$12 + $AO5*'Cancel Curves'!$S$12 + $AP5*'Cancel Curves'!$R$12 + $AQ5*'Cancel Curves'!$Q$12 + $AR5*'Cancel Curves'!$P$12 + $AS5*'Cancel Curves'!$O$12 + $AT5*'Cancel Curves'!$N$12 + $AU5*'Cancel Curves'!$M$12 + $AV5*'Cancel Curves'!$L$12 + $AW5*'Cancel Curves'!$K$12 + $AX5*'Cancel Curves'!$J$12 + $AY5*'Cancel Curves'!$I$12 + $AZ5*'Cancel Curves'!$H$12 + $BA5*'Cancel Curves'!$G$12 + $BB5*'Cancel Curves'!$F$12 + $BC5*'Cancel Curves'!$E$12 + $BD5*'Cancel Curves'!$D$12 + $BE5*'Cancel Curves'!$C$12 + $BF5*'Cancel Curves'!$B$12 | BG6: =$AD5*'Cancel Curves'!$AE$12 + $AE5*'Cancel Curves'!$AD$12 + $AF5*'Cancel Curves'!$AC$12 + $AG5*'Cancel Curves'!$AB$12 + $AH5*'Cancel Curves'!$AA$12 + $AI5*'Cancel Curves'!$Z$12 + $AJ5*'Cancel Curves'!$Y$12 + $AK5*'Cancel Curves'!$X$12 + $AL5*'Cancel Curves'!$W$12 + $AM5*'Cancel Curves'!$V$12 + $AN5*'Cancel Curves'!$U$12 + $AO5*'Cancel Curves'!$T$12 + $AP5*'Cancel Curves'!$S$12 + $AQ5*'Cancel Curves'!$R$12 + $AR5*'Cancel Curves'!$Q$12 + $AS5*'Cancel Curves'!$P$12 + $AT5*'Cancel Curves'!$O$12 + $AU5*'Cancel Curves'!$N$12 + $AV5*'Cancel Curves'!$M$12 + $AW5*'Cancel Curves'!$L$12 + $AX5*'Cancel Curves'!$K$12 + $AY5*'Cancel Curves'!$J$12 + $AZ5*'Cancel Curves'!$I$12 + $BA5*'Cancel Curves'!$H$12 + $BB5*'Cancel Curves'!$G$12 + $BC5*'Cancel Curves'!$F$12 + $BD5*'Cancel Curves'!$E$12 + $BE5*'Cancel Curves'!$D$12 + $BF5*'Cancel Curves'!$C$12 + $BG5*'Cancel Curves'!$B$12 | BH6: =$AE5*'Cancel Curves'!$AE$12 + $AF5*'Cancel Curves'!$AD$12 + $AG5*'Cancel Curves'!$AC$12 + $AH5*'Cancel Curves'!$AB$12 + $AI5*'Cancel Curves'!$AA$12 + $AJ5*'Cancel Curves'!$Z$12 + $AK5*'Cancel Curves'!$Y$12 + $AL5*'Cancel Curves'!$X$12 + $AM5*'Cancel Curves'!$W$12 + $AN5*'Cancel Curves'!$V$12 + $AO5*'Cancel Curves'!$U$12 + $AP5*'Cancel Curves'!$T$12 + $AQ5*'Cancel Curves'!$S$12 + $AR5*'Cancel Curves'!$R$12 + $AS5*'Cancel Curves'!$Q$12 + $AT5*'Cancel Curves'!$P$12 + $AU5*'Cancel Curves'!$O$12 + $AV5*'Cancel Curves'!$N$12 + $AW5*'Cancel Curves'!$M$12 + $AX5*'Cancel Curves'!$L$12 + $AY5*'Cancel Curves'!$K$12 + $AZ5*'Cancel Curves'!$J$12 + $BA5*'Cancel Curves'!$I$12 + $BB5*'Cancel Curves'!$H$12 + $BC5*'Cancel Curves'!$G$12 + $BD5*'Cancel Curves'!$F$12 + $BE5*'Cancel Curves'!$E$12 + $BF5*'Cancel Curves'!$D$12 + $BG5*'Cancel Curves'!$C$12 + $BH5*'Cancel Curves'!$B$12 | BI6: =$AF5*'Cancel Curves'!$AE$12 + $AG5*'Cancel Curves'!$AD$12 + $AH5*'Cancel Curves'!$AC$12 + $AI5*'Cancel Curves'!$AB$12 + $AJ5*'Cancel Curves'!$AA$12 + $AK5*'Cancel Curves'!$Z$12 + $AL5*'Cancel Curves'!$Y$12 + $AM5*'Cancel Curves'!$X$12 + $AN5*'Cancel Curves'!$W$12 + $AO5*'Cancel Curves'!$V$12 + $AP5*'Cancel Curves'!$U$12 + $AQ5*'Cancel Curves'!$T$12 + $AR5*'Cancel Curves'!$S$12 + $AS5*'Cancel Curves'!$R$12 + $AT5*'Cancel Curves'!$Q$12 + $AU5*'Cancel Curves'!$P$12 + $AV5*'Cancel Curves'!$O$12 + $AW5*'Cancel Curves'!$N$12 + $AX5*'Cancel Curves'!$M$12 + $AY5*'Cancel Curves'!$L$12 + $AZ5*'Cancel Curves'!$K$12 + $BA5*'Cancel Curves'!$J$12 + $BB5*'Cancel Curves'!$I$12 + $BC5*'Cancel Curves'!$H$12 + $BD5*'Cancel Curves'!$G$12 + $BE5*'Cancel Curves'!$F$12 + $BF5*'Cancel Curves'!$E$12 + $BG5*'Cancel Curves'!$D$12 + $BH5*'Cancel Curves'!$C$12 + $BI5*'Cancel Curves'!$B$12 | BJ6: =$AG5*'Cancel Curves'!$AE$12 + $AH5*'Cancel Curves'!$AD$12 + $AI5*'Cancel Curves'!$AC$12 + $AJ5*'Cancel Curves'!$AB$12 + $AK5*'Cancel Curves'!$AA$12 + $AL5*'Cancel Curves'!$Z$12 + $AM5*'Cancel Curves'!$Y$12 + $AN5*'Cancel Curves'!$X$12 + $AO5*'Cancel Curves'!$W$12 + $AP5*'Cancel Curves'!$V$12 + $AQ5*'Cancel Curves'!$U$12 + $AR5*'Cancel Curves'!$T$12 + $AS5*'Cancel Curves'!$S$12 + $AT5*'Cancel Curves'!$R$12 + $AU5*'Cancel Curves'!$Q$12 + $AV5*'Cancel Curves'!$P$12 + $AW5*'Cancel Curves'!$O$12 + $AX5*'Cancel Curves'!$N$12 + $AY5*'Cancel Curves'!$M$12 + $AZ5*'Cancel Curves'!$L$12 + $BA5*'Cancel Curves'!$K$12 + $BB5*'Cancel Curves'!$J$12 + $BC5*'Cancel Curves'!$I$12 + $BD5*'Cancel Curves'!$H$12 + $BE5*'Cancel Curves'!$G$12 + $BF5*'Cancel Curves'!$F$12 + $BG5*'Cancel Curves'!$E$12 + $BH5*'Cancel Curves'!$D$12 + $BI5*'Cancel Curves'!$C$12 + $BJ5*'Cancel Curves'!$B$12 | BK6: =$AH5*'Cancel Curves'!$AE$12 + $AI5*'Cancel Curves'!$AD$12 + $AJ5*'Cancel Curves'!$AC$12 + $AK5*'Cancel Curves'!$AB$12 + $AL5*'Cancel Curves'!$AA$12 + $AM5*'Cancel Curves'!$Z$12 + $AN5*'Cancel Curves'!$Y$12 + $AO5*'Cancel Curves'!$X$12 + $AP5*'Cancel Curves'!$W$12 + $AQ5*'Cancel Curves'!$V$12 + $AR5*'Cancel Curves'!$U$12 + $AS5*'Cancel Curves'!$T$12 + $AT5*'Cancel Curves'!$S$12 + $AU5*'Cancel Curves'!$R$12 + $AV5*'Cancel Curves'!$Q$12 + $AW5*'Cancel Curves'!$P$12 + $AX5*'Cancel Curves'!$O$12 + $AY5*'Cancel Curves'!$N$12 + $AZ5*'Cancel Curves'!$M$12 + $BA5*'Cancel Curves'!$L$12 + $BB5*'Cancel Curves'!$K$12 + $BC5*'Cancel Curves'!$J$12 + $BD5*'Cancel Curves'!$I$12 + $BE5*'Cancel Curves'!$H$12 + $BF5*'Cancel Curves'!$G$12 + $BG5*'Cancel Curves'!$F$12 + $BH5*'Cancel Curves'!$E$12 + $BI5*'Cancel Curves'!$D$12 + $BJ5*'Cancel Curves'!$C$12 + $BK5*'Cancel Curves'!$B$12 | BL6: =$AI5*'Cancel Curves'!$AE$12 + $AJ5*'Cancel Curves'!$AD$12 + $AK5*'Cancel Curves'!$AC$12 + $AL5*'Cancel Curves'!$AB$12 + $AM5*'Cancel Curves'!$AA$12 + $AN5*'Cancel Curves'!$Z$12 + $AO5*'Cancel Curves'!$Y$12 + $AP5*'Cancel Curves'!$X$12 + $AQ5*'Cancel Curves'!$W$12 + $AR5*'Cancel Curves'!$V$12 + $AS5*'Cancel Curves'!$U$12 + $AT5*'Cancel Curves'!$T$12 + $AU5*'Cancel Curves'!$S$12 + $AV5*'Cancel Curves'!$R$12 + $AW5*'Cancel Curves'!$Q$12 + $AX5*'Cancel Curves'!$P$12 + $AY5*'Cancel Curves'!$O$12 + $AZ5*'Cancel Curves'!$N$12 + $BA5*'Cancel Curves'!$M$12 + $BB5*'Cancel Curves'!$L$12 + $BC5*'Cancel Curves'!$K$12 + $BD5*'Cancel Curves'!$J$12 + $BE5*'Cancel Curves'!$I$12 + $BF5*'Cancel Curves'!$H$12 + $BG5*'Cancel Curves'!$G$12 + $BH5*'Cancel Curves'!$F$12 + $BI5*'Cancel Curves'!$E$12 + $BJ5*'Cancel Curves'!$D$12 + $BK5*'Cancel Curves'!$C$12 + $BL5*'Cancel Curves'!$B$12 | BM6: =$AJ5*'Cancel Curves'!$AE$12 + $AK5*'Cancel Curves'!$AD$12 + $AL5*'Cancel Curves'!$AC$12 + $AM5*'Cancel Curves'!$AB$12 + $AN5*'Cancel Curves'!$AA$12 + $AO5*'Cancel Curves'!$Z$12 + $AP5*'Cancel Curves'!$Y$12 + $AQ5*'Cancel Curves'!$X$12 + $AR5*'Cancel Curves'!$W$12 + $AS5*'Cancel Curves'!$V$12 + $AT5*'Cancel Curves'!$U$12 + $AU5*'Cancel Curves'!$T$12 + $AV5*'Cancel Curves'!$S$12 + $AW5*'Cancel Curves'!$R$12 + $AX5*'Cancel Curves'!$Q$12 + $AY5*'Cancel Curves'!$P$12 + $AZ5*'Cancel Curves'!$O$12 + $BA5*'Cancel Curves'!$N$12 + $BB5*'Cancel Curves'!$M$12 + $BC5*'Cancel Curves'!$L$12 + $BD5*'Cancel Curves'!$K$12 + $BE5*'Cancel Curves'!$J$12 + $BF5*'Cancel Curves'!$I$12 + $BG5*'Cancel Curves'!$H$12 + $BH5*'Cancel Curves'!$G$12 + $BI5*'Cancel Curves'!$F$12 + $BJ5*'Cancel Curves'!$E$12 + $BK5*'Cancel Curves'!$D$12 + $BL5*'Cancel Curves'!$C$12 + $BM5*'Cancel Curves'!$B$12 | BN6: =$AK5*'Cancel Curves'!$AE$12 + $AL5*'Cancel Curves'!$AD$12 + $AM5*'Cancel Curves'!$AC$12 + $AN5*'Cancel Curves'!$AB$12 + $AO5*'Cancel Curves'!$AA$12 + $AP5*'Cancel Curves'!$Z$12 + $AQ5*'Cancel Curves'!$Y$12 + $AR5*'Cancel Curves'!$X$12 + $AS5*'Cancel Curves'!$W$12 + $AT5*'Cancel Curves'!$V$12 + $AU5*'Cancel Curves'!$U$12 + $AV5*'Cancel Curves'!$T$12 + $AW5*'Cancel Curves'!$S$12 + $AX5*'Cancel Curves'!$R$12 + $AY5*'Cancel Curves'!$Q$12 + $AZ5*'Cancel Curves'!$P$12 + $BA5*'Cancel Curves'!$O$12 + $BB5*'Cancel Curves'!$N$12 + $BC5*'Cancel Curves'!$M$12 + $BD5*'Cancel Curves'!$L$12 + $BE5*'Cancel Curves'!$K$12 + $BF5*'Cancel Curves'!$J$12 + $BG5*'Cancel Curves'!$I$12 + $BH5*'Cancel Curves'!$H$12 + $BI5*'Cancel Curves'!$G$12 + $BJ5*'Cancel Curves'!$F$12 + $BK5*'Cancel Curves'!$E$12 + $BL5*'Cancel Curves'!$D$12 + $BM5*'Cancel Curves'!$C$12 + $BN5*'Cancel Curves'!$B$12 | BO6: =$AL5*'Cancel Curves'!$AE$12 + $AM5*'Cancel Curves'!$AD$12 + $AN5*'Cancel Curves'!$AC$12 + $AO5*'Cancel Curves'!$AB$12 + $AP5*'Cancel Curves'!$AA$12 + $AQ5*'Cancel Curves'!$Z$12 + $AR5*'Cancel Curves'!$Y$12 + $AS5*'Cancel Curves'!$X$12 + $AT5*'Cancel Curves'!$W$12 + $AU5*'Cancel Curves'!$V$12 + $AV5*'Cancel Curves'!$U$12 + $AW5*'Cancel Curves'!$T$12 + $AX5*'Cancel Curves'!$S$12 + $AY5*'Cancel Curves'!$R$12 + $AZ5*'Cancel Curves'!$Q$12 + $BA5*'Cancel Curves'!$P$12 + $BB5*'Cancel Curves'!$O$12 + $BC5*'Cancel Curves'!$N$12 + $BD5*'Cancel Curves'!$M$12 + $BE5*'Cancel Curves'!$L$12 + $BF5*'Cancel Curves'!$K$12 + $BG5*'Cancel Curves'!$J$12 + $BH5*'Cancel Curves'!$I$12 + $BI5*'Cancel Curves'!$H$12 + $BJ5*'Cancel Curves'!$G$12 + $BK5*'Cancel Curves'!$F$12 + $BL5*'Cancel Curves'!$E$12 + $BM5*'Cancel Curves'!$D$12 + $BN5*'Cancel Curves'!$C$12 + $BO5*'Cancel Curves'!$B$12 | BP6: =$AM5*'Cancel Curves'!$AE$12 + $AN5*'Cancel Curves'!$AD$12 + $AO5*'Cancel Curves'!$AC$12 + $AP5*'Cancel Curves'!$AB$12 + $AQ5*'Cancel Curves'!$AA$12 + $AR5*'Cancel Curves'!$Z$12 + $AS5*'Cancel Curves'!$Y$12 + $AT5*'Cancel Curves'!$X$12 + $AU5*'Cancel Curves'!$W$12 + $AV5*'Cancel Curves'!$V$12 + $AW5*'Cancel Curves'!$U$12 + $AX5*'Cancel Curves'!$T$12 + $AY5*'Cancel Curves'!$S$12 + $AZ5*'Cancel Curves'!$R$12 + $BA5*'Cancel Curves'!$Q$12 + $BB5*'Cancel Curves'!$P$12 + $BC5*'Cancel Curves'!$O$12 + $BD5*'Cancel Curves'!$N$12 + $BE5*'Cancel Curves'!$M$12 + $BF5*'Cancel Curves'!$L$12 + $BG5*'Cancel Curves'!$K$12 + $BH5*'Cancel Curves'!$J$12 + $BI5*'Cancel Curves'!$I$12 + $BJ5*'Cancel Curves'!$H$12 + $BK5*'Cancel Curves'!$G$12 + $BL5*'Cancel Curves'!$F$12 + $BM5*'Cancel Curves'!$E$12 + $BN5*'Cancel Curves'!$D$12 + $BO5*'Cancel Curves'!$C$12 + $BP5*'Cancel Curves'!$B$12 | BQ6: =$AN5*'Cancel Curves'!$AE$12 + $AO5*'Cancel Curves'!$AD$12 + $AP5*'Cancel Curves'!$AC$12 + $AQ5*'Cancel Curves'!$AB$12 + $AR5*'Cancel Curves'!$AA$12 + $AS5*'Cancel Curves'!$Z$12 + $AT5*'Cancel Curves'!$Y$12 + $AU5*'Cancel Curves'!$X$12 + $AV5*'Cancel Curves'!$W$12 + $AW5*'Cancel Curves'!$V$12 + $AX5*'Cancel Curves'!$U$12 + $AY5*'Cancel Curves'!$T$12 + $AZ5*'Cancel Curves'!$S$12 + $BA5*'Cancel Curves'!$R$12 + $BB5*'Cancel Curves'!$Q$12 + $BC5*'Cancel Curves'!$P$12 + $BD5*'Cancel Curves'!$O$12 + $BE5*'Cancel Curves'!$N$12 + $BF5*'Cancel Curves'!$M$12 + $BG5*'Cancel Curves'!$L$12 + $BH5*'Cancel Curves'!$K$12 + $BI5*'Cancel Curves'!$J$12 + $BJ5*'Cancel Curves'!$I$12 + $BK5*'Cancel Curves'!$H$12 + $BL5*'Cancel Curves'!$G$12 + $BM5*'Cancel Curves'!$F$12 + $BN5*'Cancel Curves'!$E$12 + $BO5*'Cancel Curves'!$D$12 + $BP5*'Cancel Curves'!$C$12 + $BQ5*'Cancel Curves'!$B$12 | BR6: =$AO5*'Cancel Curves'!$AE$12 + $AP5*'Cancel Curves'!$AD$12 + $AQ5*'Cancel Curves'!$AC$12 + $AR5*'Cancel Curves'!$AB$12 + $AS5*'Cancel Curves'!$AA$12 + $AT5*'Cancel Curves'!$Z$12 + $AU5*'Cancel Curves'!$Y$12 + $AV5*'Cancel Curves'!$X$12 + $AW5*'Cancel Curves'!$W$12 + $AX5*'Cancel Curves'!$V$12 + $AY5*'Cancel Curves'!$U$12 + $AZ5*'Cancel Curves'!$T$12 + $BA5*'Cancel Curves'!$S$12 + $BB5*'Cancel Curves'!$R$12 + $BC5*'Cancel Curves'!$Q$12 + $BD5*'Cancel Curves'!$P$12 + $BE5*'Cancel Curves'!$O$12 + $BF5*'Cancel Curves'!$N$12 + $BG5*'Cancel Curves'!$M$12 + $BH5*'Cancel Curves'!$L$12 + $BI5*'Cancel Curves'!$K$12 + $BJ5*'Cancel Curves'!$J$12 + $BK5*'Cancel Curves'!$I$12 + $BL5*'Cancel Curves'!$H$12 + $BM5*'Cancel Curves'!$G$12 + $BN5*'Cancel Curves'!$F$12 + $BO5*'Cancel Curves'!$E$12 + $BP5*'Cancel Curves'!$D$12 + $BQ5*'Cancel Curves'!$C$12 + $BR5*'Cancel Curves'!$B$12 | BS6: =$AP5*'Cancel Curves'!$AE$12 + $AQ5*'Cancel Curves'!$AD$12 + $AR5*'Cancel Curves'!$AC$12 + $AS5*'Cancel Curves'!$AB$12 + $AT5*'Cancel Curves'!$AA$12 + $AU5*'Cancel Curves'!$Z$12 + $AV5*'Cancel Curves'!$Y$12 + $AW5*'Cancel Curves'!$X$12 + $AX5*'Cancel Curves'!$W$12 + $AY5*'Cancel Curves'!$V$12 + $AZ5*'Cancel Curves'!$U$12 + $BA5*'Cancel Curves'!$T$12 + $BB5*'Cancel Curves'!$S$12 + $BC5*'Cancel Curves'!$R$12 + $BD5*'Cancel Curves'!$Q$12 + $BE5*'Cancel Curves'!$P$12 + $BF5*'Cancel Curves'!$O$12 + $BG5*'Cancel Curves'!$N$12 + $BH5*'Cancel Curves'!$M$12 + $BI5*'Cancel Curves'!$L$12 + $BJ5*'Cancel Curves'!$K$12 + $BK5*'Cancel Curves'!$J$12 + $BL5*'Cancel Curves'!$I$12 + $BM5*'Cancel Curves'!$H$12 + $BN5*'Cancel Curves'!$G$12 + $BO5*'Cancel Curves'!$F$12 + $BP5*'Cancel Curves'!$E$12 + $BQ5*'Cancel Curves'!$D$12 + $BR5*'Cancel Curves'!$C$12 + $BS5*'Cancel Curves'!$B$12 | BT6: =$AQ5*'Cancel Curves'!$AE$12 + $AR5*'Cancel Curves'!$AD$12 + $AS5*'Cancel Curves'!$AC$12 + $AT5*'Cancel Curves'!$AB$12 + $AU5*'Cancel Curves'!$AA$12 + $AV5*'Cancel Curves'!$Z$12 + $AW5*'Cancel Curves'!$Y$12 + $AX5*'Cancel Curves'!$X$12 + $AY5*'Cancel Curves'!$W$12 + $AZ5*'Cancel Curves'!$V$12 + $BA5*'Cancel Curves'!$U$12 + $BB5*'Cancel Curves'!$T$12 + $BC5*'Cancel Curves'!$S$12 + $BD5*'Cancel Curves'!$R$12 + $BE5*'Cancel Curves'!$Q$12 + $BF5*'Cancel Curves'!$P$12 + $BG5*'Cancel Curves'!$O$12 + $BH5*'Cancel Curves'!$N$12 + $BI5*'Cancel Curves'!$M$12 + $BJ5*'Cancel Curves'!$L$12 + $BK5*'Cancel Curves'!$K$12 + $BL5*'Cancel Curves'!$J$12 + $BM5*'Cancel Curves'!$I$12 + $BN5*'Cancel Curves'!$H$12 + $BO5*'Cancel Curves'!$G$12 + $BP5*'Cancel Curves'!$F$12 + $BQ5*'Cancel Curves'!$E$12 + $BR5*'Cancel Curves'!$D$12 + $BS5*'Cancel Curves'!$C$12 + $BT5*'Cancel Curves'!$B$12 | BU6: =$AR5*'Cancel Curves'!$AE$12 + $AS5*'Cancel Curves'!$AD$12 + $AT5*'Cancel Curves'!$AC$12 + $AU5*'Cancel Curves'!$AB$12 + $AV5*'Cancel Curves'!$AA$12 + $AW5*'Cancel Curves'!$Z$12 + $AX5*'Cancel Curves'!$Y$12 + $AY5*'Cancel Curves'!$X$12 + $AZ5*'Cancel Curves'!$W$12 + $BA5*'Cancel Curves'!$V$12 + $BB5*'Cancel Curves'!$U$12 + $BC5*'Cancel Curves'!$T$12 + $BD5*'Cancel Curves'!$S$12 + $BE5*'Cancel Curves'!$R$12 + $BF5*'Cancel Curves'!$Q$12 + $BG5*'Cancel Curves'!$P$12 + $BH5*'Cancel Curves'!$O$12 + $BI5*'Cancel Curves'!$N$12 + $BJ5*'Cancel Curves'!$M$12 + $BK5*'Cancel Curves'!$L$12 + $BL5*'Cancel Curves'!$K$12 + $BM5*'Cancel Curves'!$J$12 + $BN5*'Cancel Curves'!$I$12 + $BO5*'Cancel Curves'!$H$12 + $BP5*'Cancel Curves'!$G$12 + $BQ5*'Cancel Curves'!$F$12 + $BR5*'Cancel Curves'!$E$12 + $BS5*'Cancel Curves'!$D$12 + $BT5*'Cancel Curves'!$C$12 + $BU5*'Cancel Curves'!$B$12 | BV6: =$AS5*'Cancel Curves'!$AE$12 + $AT5*'Cancel Curves'!$AD$12 + $AU5*'Cancel Curves'!$AC$12 + $AV5*'Cancel Curves'!$AB$12 + $AW5*'Cancel Curves'!$AA$12 + $AX5*'Cancel Curves'!$Z$12 + $AY5*'Cancel Curves'!$Y$12 + $AZ5*'Cancel Curves'!$X$12 + $BA5*'Cancel Curves'!$W$12 + $BB5*'Cancel Curves'!$V$12 + $BC5*'Cancel Curves'!$U$12 + $BD5*'Cancel Curves'!$T$12 + $BE5*'Cancel Curves'!$S$12 + $BF5*'Cancel Curves'!$R$12 + $BG5*'Cancel Curves'!$Q$12 + $BH5*'Cancel Curves'!$P$12 + $BI5*'Cancel Curves'!$O$12 + $BJ5*'Cancel Curves'!$N$12 + $BK5*'Cancel Curves'!$M$12 + $BL5*'Cancel Curves'!$L$12 + $BM5*'Cancel Curves'!$K$12 + $BN5*'Cancel Curves'!$J$12 + $BO5*'Cancel Curves'!$I$12 + $BP5*'Cancel Curves'!$H$12 + $BQ5*'Cancel Curves'!$G$12 + $BR5*'Cancel Curves'!$F$12 + $BS5*'Cancel Curves'!$E$12 + $BT5*'Cancel Curves'!$D$12 + $BU5*'Cancel Curves'!$C$12 + $BV5*'Cancel Curves'!$B$12 | BW6: =$AT5*'Cancel Curves'!$AE$12 + $AU5*'Cancel Curves'!$AD$12 + $AV5*'Cancel Curves'!$AC$12 + $AW5*'Cancel Curves'!$AB$12 + $AX5*'Cancel Curves'!$AA$12 + $AY5*'Cancel Curves'!$Z$12 + $AZ5*'Cancel Curves'!$Y$12 + $BA5*'Cancel Curves'!$X$12 + $BB5*'Cancel Curves'!$W$12 + $BC5*'Cancel Curves'!$V$12 + $BD5*'Cancel Curves'!$U$12 + $BE5*'Cancel Curves'!$T$12 + $BF5*'Cancel Curves'!$S$12 + $BG5*'Cancel Curves'!$R$12 + $BH5*'Cancel Curves'!$Q$12 + $BI5*'Cancel Curves'!$P$12 + $BJ5*'Cancel Curves'!$O$12 + $BK5*'Cancel Curves'!$N$12 + $BL5*'Cancel Curves'!$M$12 + $BM5*'Cancel Curves'!$L$12 + $BN5*'Cancel Curves'!$K$12 + $BO5*'Cancel Curves'!$J$12 + $BP5*'Cancel Curves'!$I$12 + $BQ5*'Cancel Curves'!$H$12 + $BR5*'Cancel Curves'!$G$12 + $BS5*'Cancel Curves'!$F$12 + $BT5*'Cancel Curves'!$E$12 + $BU5*'Cancel Curves'!$D$12 + $BV5*'Cancel Curves'!$C$12 + $BW5*'Cancel Curves'!$B$12
A7: Active contracts (start of period) | C7: 12000
A8: Cancels (period) | D8: =C6+D5-D6 | E8: =D6+E5-E6 | F8: =E6+F5-F6 | G8: =F6+G5-G6 | H8: =G6+H5-H6 | I8: =H6+I5-I6 | J8: =I6+J5-J6 | K8: =J6+K5-K6 | ... BW8: =BV6+BW5-BW6
A10: REVENUE
A11: Monthly contract value (active × CPS)
A12: CPS (customer payment per service) | D12: =Assumptions!$B$17*(1+Assumptions!$B$9)^0 | E12: =Assumptions!$B$17*(1+Assumptions!$B$9)^0 | F12: =Assumptions!$B$17*(1+Assumptions!$B$9)^0 | G12: =Assumptions!$B$17*(1+Assumptions!$B$9)^0 | H12: =Assumptions!$B$17*(1+Assumptions!$B$9)^0 | I12: =Assumptions!$B$17*(1+Assumptions!$B$9)^0 | J12: =Assumptions!$B$17*(1+Assumptions!$B$9)^0 | K12: =Assumptions!$B$17*(1+Assumptions!$B$9)^0 | ... O12: =Assumptions!$B$17*(1+Assumptions!$B$9)^0 | P12: =Assumptions!$B$17*(1+Assumptions!$B$9)^1 | Q12: =Assumptions!$B$17*(1+Assumptions!$B$9)^1 | R12: =Assumptions!$B$17*(1+Assumptions!$B$9)^1 | S12: =Assumptions!$B$17*(1+Assumptions!$B$9)^1 | T12: =Assumptions!$B$17*(1+Assumptions!$B$9)^1 | U12: =Assumptions!$B$17*(1+Assumptions!$B$9)^1 | V12: =Assumptions!$B$17*(1+Assumptions!$B$9)^1 | W12: =Assumptions!$B$17*(1+Assumptions!$B$9)^1 | ... AA12: =Assumptions!$B$17*(1+Assumptions!$B$9)^1 | AB12: =Assumptions!$B$17*(1+Assumptions!$B$9)^2 | AC12: =Assumptions!$B$17*(1+Assumptions!$B$9)^2 | AD12: =Assumptions!$B$17*(1+Assumptions!$B$9)^2 | AE12: =Assumptions!$B$17*(1+Assumptions!$B$9)^2 | AF12: =Assumptions!$B$17*(1+Assumptions!$B$9)^2 | AG12: =Assumptions!$B$17*(1+Assumptions!$B$9)^2 | AH12: =Assumptions!$B$17*(1+Assumptions!$B$9)^2 | AI12: =Assumptions!$B$17*(1+Assumptions!$B$9)^2 | ... AM12: =Assumptions!$B$17*(1+Assumptions!$B$9)^2 | AN12: =Assumptions!$B$17*(1+Assumptions!$B$9)^3 | AO12: =Assumptions!$B$17*(1+Assumptions!$B$9)^3 | AP12: =Assumptions!$B$17*(1+Assumptions!$B$9)^3 | AQ12: =Assumptions!$B$17*(1+Assumptions!$B$9)^3 | AR12: =Assumptions!$B$17*(1+Assumptions!$B$9)^3 | AS12: =Assumptions!$B$17*(1+Assumptions!$B$9)^3 | AT12: =Assumptions!$B$17*(1+Assumptions!$B$9)^3 | AU12: =Assumptions!$B$17*(1+Assumptions!$B$9)^3 | ... AY12: =Assumptions!$B$17*(1+Assumptions!$B$9)^3 | AZ12: =Assumptions!$B$17*(1+Assumptions!$B$9)^4 | BA12: =Assumptions!$B$17*(1+Assumptions!$B$9)^4 | BB12: =Assumptions!$B$17*(1+Assumptions!$B$9)^4 | BC12: =Assumptions!$B$17*(1+Assumptions!$B$9)^4 | BD12: =Assumptions!$B$17*(1+Assumptions!$B$9)^4 | BE12: =Assumptions!$B$17*(1+Assumptions!$B$9)^4 | BF12: =Assumptions!$B$17*(1+Assumptions!$B$9)^4 | BG12: =Assumptions!$B$17*(1+Assumptions!$B$9)^4 | ... BK12: =Assumptions!$B$17*(1+Assumptions!$B$9)^4 | BL12: =Assumptions!$B$17*(1+Assumptions!$B$9)^5 | BM12: =Assumptions!$B$17*(1+Assumptions!$B$9)^5 | BN12: =Assumptions!$B$17*(1+Assumptions!$B$9)^5 | BO12: =Assumptions!$B$17*(1+Assumptions!$B$9)^5 | BP12: =Assumptions!$B$17*(1+Assumptions!$B$9)^5 | BQ12: =Assumptions!$B$17*(1+Assumptions!$B$9)^5 | BR12: =Assumptions!$B$17*(1+Assumptions!$B$9)^5 | BS12: =Assumptions!$B$17*(1+Assumptions!$B$9)^5 | ... BW12: =Assumptions!$B$17*(1+Assumptions!$B$9)^5
A13: Subscription revenue (CPS + IAA amort.) | D13: =D6*D12 + ($D$5*'Cancel Curves'!$B$12 + 2294*'Cancel Curves'!$M$12 + 1986*'Cancel Curves'!$L$12 + 2149*'Cancel Curves'!$K$12 + 1517*'Cancel Curves'!$J$12 + 1564*'Cancel Curves'!$I$12 + 1705*'Cancel Curves'!$H$12 + 1902*'Cancel Curves'!$G$12 + 2052*'Cancel Curves'!$F$12 + 2362*'Cancel Curves'!$E$12 + 2189*'Cancel Curves'!$D$12 + 2083*'Cancel Curves'!$C$12)*Assumptions!$B$76 | E13: =E6*E12 + ($D$5*'Cancel Curves'!$C$12 + $E$5*'Cancel Curves'!$B$12 + 1986*'Cancel Curves'!$M$12 + 2149*'Cancel Curves'!$L$12 + 1517*'Cancel Curves'!$K$12 + 1564*'Cancel Curves'!$J$12 + 1705*'Cancel Curves'!$I$12 + 1902*'Cancel Curves'!$H$12 + 2052*'Cancel Curves'!$G$12 + 2362*'Cancel Curves'!$F$12 + 2189*'Cancel Curves'!$E$12 + 2083*'Cancel Curves'!$D$12)*Assumptions!$B$76 | F13: =F6*F12 + ($D$5*'Cancel Curves'!$D$12 + $E$5*'Cancel Curves'!$C$12 + $F$5*'Cancel Curves'!$B$12 + 2149*'Cancel Curves'!$M$12 + 1517*'Cancel Curves'!$L$12 + 1564*'Cancel Curves'!$K$12 + 1705*'Cancel Curves'!$J$12 + 1902*'Cancel Curves'!$I$12 + 2052*'Cancel Curves'!$H$12 + 2362*'Cancel Curves'!$G$12 + 2189*'Cancel Curves'!$F$12 + 2083*'Cancel Curves'!$E$12)*Assumptions!$B$76 | G13: =G6*G12 + ($D$5*'Cancel Curves'!$E$12 + $E$5*'Cancel Curves'!$D$12 + $F$5*'Cancel Curves'!$C$12 + $G$5*'Cancel Curves'!$B$12 + 1517*'Cancel Curves'!$M$12 + 1564*'Cancel Curves'!$L$12 + 1705*'Cancel Curves'!$K$12 + 1902*'Cancel Curves'!$J$12 + 2052*'Cancel Curves'!$I$12 + 2362*'Cancel Curves'!$H$12 + 2189*'Cancel Curves'!$G$12 + 2083*'Cancel Curves'!$F$12)*Assumptions!$B$76 | H13: =H6*H12 + ($D$5*'Cancel Curves'!$F$12 + $E$5*'Cancel Curves'!$E$12 + $F$5*'Cancel Curves'!$D$12 + $G$5*'Cancel Curves'!$C$12 + $H$5*'Cancel Curves'!$B$12 + 1564*'Cancel Curves'!$M$12 + 1705*'Cancel Curves'!$L$12 + 1902*'Cancel Curves'!$K$12 + 2052*'Cancel Curves'!$J$12 + 2362*'Cancel Curves'!$I$12 + 2189*'Cancel Curves'!$H$12 + 2083*'Cancel Curves'!$G$12)*Assumptions!$B$76 | I13: =I6*I12 + ($D$5*'Cancel Curves'!$G$12 + $E$5*'Cancel Curves'!$F$12 + $F$5*'Cancel Curves'!$E$12 + $G$5*'Cancel Curves'!$D$12 + $H$5*'Cancel Curves'!$C$12 + $I$5*'Cancel Curves'!$B$12 + 1705*'Cancel Curves'!$M$12 + 1902*'Cancel Curves'!$L$12 + 2052*'Cancel Curves'!$K$12 + 2362*'Cancel Curves'!$J$12 + 2189*'Cancel Curves'!$I$12 + 2083*'Cancel Curves'!$H$12)*Assumptions!$B$76 | J13: =J6*J12 + ($D$5*'Cancel Curves'!$H$12 + $E$5*'Cancel Curves'!$G$12 + $F$5*'Cancel Curves'!$F$12 + $G$5*'Cancel Curves'!$E$12 + $H$5*'Cancel Curves'!$D$12 + $I$5*'Cancel Curves'!$C$12 + $J$5*'Cancel Curves'!$B$12 + 1902*'Cancel Curves'!$M$12 + 2052*'Cancel Curves'!$L$12 + 2362*'Cancel Curves'!$K$12 + 2189*'Cancel Curves'!$J$12 + 2083*'Cancel Curves'!$I$12)*Assumptions!$B$76 | K13: =K6*K12 + ($D$5*'Cancel Curves'!$I$12 + $E$5*'Cancel Curves'!$H$12 + $F$5*'Cancel Curves'!$G$12 + $G$5*'Cancel Curves'!$F$12 + $H$5*'Cancel Curves'!$E$12 + $I$5*'Cancel Curves'!$D$12 + $J$5*'Cancel Curves'!$C$12 + $K$5*'Cancel Curves'!$B$12 + 2052*'Cancel Curves'!$M$12 + 2362*'Cancel Curves'!$L$12 + 2189*'Cancel Curves'!$K$12 + 2083*'Cancel Curves'!$J$12)*Assumptions!$B$76 | L13: =L6*L12 + ($D$5*'Cancel Curves'!$J$12 + $E$5*'Cancel Curves'!$I$12 + $F$5*'Cancel Curves'!$H$12 + $G$5*'Cancel Curves'!$G$12 + $H$5*'Cancel Curves'!$F$12 + $I$5*'Cancel Curves'!$E$12 + $J$5*'Cancel Curves'!$D$12 + $K$5*'Cancel Curves'!$C$12 + $L$5*'Cancel Curves'!$B$12 + 2362*'Cancel Curves'!$M$12 + 2189*'Cancel Curves'!$L$12 + 2083*'Cancel Curves'!$K$12)*Assumptions!$B$76 | M13: =M6*M12 + ($D$5*'Cancel Curves'!$K$12 + $E$5*'Cancel Curves'!$J$12 + $F$5*'Cancel Curves'!$I$12 + $G$5*'Cancel Curves'!$H$12 + $H$5*'Cancel Curves'!$G$12 + $I$5*'Cancel Curves'!$F$12 + $J$5*'Cancel Curves'!$E$12 + $K$5*'Cancel Curves'!$D$12 + $L$5*'Cancel Curves'!$C$12 + $M$5*'Cancel Curves'!$B$12 + 2189*'Cancel Curves'!$M$12 + 2083*'Cancel Curves'!$L$12)*Assumptions!$B$76 | N13: =N6*N12 + ($D$5*'Cancel Curves'!$L$12 + $E$5*'Cancel Curves'!$K$12 + $F$5*'Cancel Curves'!$J$12 + $G$5*'Cancel Curves'!$I$12 + $H$5*'Cancel Curves'!$H$12 + $I$5*'Cancel Curves'!$G$12 + $J$5*'Cancel Curves'!$F$12 + $K$5*'Cancel Curves'!$E$12 + $L$5*'Cancel Curves'!$D$12 + $M$5*'Cancel Curves'!$C$12 + $N$5*'Cancel Curves'!$B$12 + 2083*'Cancel Curves'!$M$12)*Assumptions!$B$76 | O13: =O6*O12 + ($D$5*'Cancel Curves'!$M$12 + $E$5*'Cancel Curves'!$L$12 + $F$5*'Cancel Curves'!$K$12 + $G$5*'Cancel Curves'!$J$12 + $H$5*'Cancel Curves'!$I$12 + $I$5*'Cancel Curves'!$H$12 + $J$5*'Cancel Curves'!$G$12 + $K$5*'Cancel Curves'!$F$12 + $L$5*'Cancel Curves'!$E$12 + $M$5*'Cancel Curves'!$D$12 + $N$5*'Cancel Curves'!$C$12 + $O$5*'Cancel Curves'!$B$12)*Assumptions!$B$76 | P13: =P6*P12 + ($E$5*'Cancel Curves'!$M$12 + $F$5*'Cancel Curves'!$L$12 + $G$5*'Cancel Curves'!$K$12 + $H$5*'Cancel Curves'!$J$12 + $I$5*'Cancel Curves'!$I$12 + $J$5*'Cancel Curves'!$H$12 + $K$5*'Cancel Curves'!$G$12 + $L$5*'Cancel Curves'!$F$12 + $M$5*'Cancel Curves'!$E$12 + $N$5*'Cancel Curves'!$D$12 + $O$5*'Cancel Curves'!$C$12 + $P$5*'Cancel Curves'!$B$12)*Assumptions!$B$76 | Q13: =Q6*Q12 + ($F$5*'Cancel Curves'!$M$12 + $G$5*'Cancel Curves'!$L$12 + $H$5*'Cancel Curves'!$K$12 + $I$5*'Cancel Curves'!$J$12 + $J$5*'Cancel Curves'!$I$12 + $K$5*'Cancel Curves'!$H$12 + $L$5*'Cancel Curves'!$G$12 + $M$5*'Cancel Curves'!$F$12 + $N$5*'Cancel Curves'!$E$12 + $O$5*'Cancel Curves'!$D$12 + $P$5*'Cancel Curves'!$C$12 + $Q$5*'Cancel Curves'!$B$12)*Assumptions!$B$76 | R13: =R6*R12 + ($G$5*'Cancel Curves'!$M$12 + $H$5*'Cancel Curves'!$L$12 + $I$5*'Cancel Curves'!$K$12 + $J$5*'Cancel Curves'!$J$12 + $K$5*'Cancel Curves'!$I$12 + $L$5*'Cancel Curves'!$H$12 + $M$5*'Cancel Curves'!$G$12 + $N$5*'Cancel Curves'!$F$12 + $O$5*'Cancel Curves'!$E$12 + $P$5*'Cancel Curves'!$D$12 + $Q$5*'Cancel Curves'!$C$12 + $R$5*'Cancel Curves'!$B$12)*Assumptions!$B$76 | S13: =S6*S12 + ($H$5*'Cancel Curves'!$M$12 + $I$5*'Cancel Curves'!$L$12 + $J$5*'Cancel Curves'!$K$12 + $K$5*'Cancel Curves'!$J$12 + $L$5*'Cancel Curves'!$I$12 + $M$5*'Cancel Curves'!$H$12 + $N$5*'Cancel Curves'!$G$12 + $O$5*'Cancel Curves'!$F$12 + $P$5*'Cancel Curves'!$E$12 + $Q$5*'Cancel Curves'!$D$12 + $R$5*'Cancel Curves'!$C$12 + $S$5*'Cancel Curves'!$B$12)*Assumptions!$B$76 | T13: =T6*T12 + ($I$5*'Cancel Curves'!$M$12 + $J$5*'Cancel Curves'!$L$12 + $K$5*'Cancel Curves'!$K$12 + $L$5*'Cancel Curves'!$J$12 + $M$5*'Cancel Curves'!$I$12 + $N$5*'Cancel Curves'!$H$12 + $O$5*'Cancel Curves'!$G$12 + $P$5*'Cancel Curves'!$F$12 + $Q$5*'Cancel Curves'!$E$12 + $R$5*'Cancel Curves'!$D$12 + $S$5*'Cancel Curves'!$C$12 + $T$5*'Cancel Curves'!$B$12)*Assumptions!$B$76 | U13: =U6*U12 + ($J$5*'Cancel Curves'!$M$12 + $K$5*'Cancel Curves'!$L$12 + $L$5*'Cancel Curves'!$K$12 + $M$5*'Cancel Curves'!$J$12 + $N$5*'Cancel Curves'!$I$12 + $O$5*'Cancel Curves'!$H$12 + $P$5*'Cancel Curves'!$G$12 + $Q$5*'Cancel Curves'!$F$12 + $R$5*'Cancel Curves'!$E$12 + $S$5*'Cancel Curves'!$D$12 + $T$5*'Cancel Curves'!$C$12 + $U$5*'Cancel Curves'!$B$12)*Assumptions!$B$76 | V13: =V6*V12 + ($K$5*'Cancel Curves'!$M$12 + $L$5*'Cancel Curves'!$L$12 + $M$5*'Cancel Curves'!$K$12 + $N$5*'Cancel Curves'!$J$12 + $O$5*'Cancel Curves'!$I$12 + $P$5*'Cancel Curves'!$H$12 + $Q$5*'Cancel Curves'!$G$12 + $R$5*'Cancel Curves'!$F$12 + $S$5*'Cancel Curves'!$E$12 + $T$5*'Cancel Curves'!$D$12 + $U$5*'Cancel Curves'!$C$12 + $V$5*'Cancel Curves'!$B$12)*Assumptions!$B$76 | W13: =W6*W12 + ($L$5*'Cancel Curves'!$M$12 + $M$5*'Cancel Curves'!$L$12 + $N$5*'Cancel Curves'!$K$12 + $O$5*'Cancel Curves'!$J$12 + $P$5*'Cancel Curves'!$I$12 + $Q$5*'Cancel Curves'!$H$12 + $R$5*'Cancel Curves'!$G$12 + $S$5*'Cancel Curves'!$F$12 + $T$5*'Cancel Curves'!$E$12 + $U$5*'Cancel Curves'!$D$12 + $V$5*'Cancel Curves'!$C$12 + $W$5*'Cancel Curves'!$B$12)*Assumptions!$B$76 | X13: =X6*X12 + ($M$5*'Cancel Curves'!$M$12 + $N$5*'Cancel Curves'!$L$12 + $O$5*'Cancel Curves'!$K$12 + $P$5*'Cancel Curves'!$J$12 + $Q$5*'Cancel Curves'!$I$12 + $R$5*'Cancel Curves'!$H$12 + $S$5*'Cancel Curves'!$G$12 + $T$5*'Cancel Curves'!$F$12 + $U$5*'Cancel Curves'!$E$12 + $V$5*'Cancel Curves'!$D$12 + $W$5*'Cancel Curves'!$C$12 + $X$5*'Cancel Curves'!$B$12)*Assumptions!$B$76 | Y13: =Y6*Y12 + ($N$5*'Cancel Curves'!$M$12 + $O$5*'Cancel Curves'!$L$12 + $P$5*'Cancel Curves'!$K$12 + $Q$5*'Cancel Curves'!$J$12 + $R$5*'Cancel Curves'!$I$12 + $S$5*'Cancel Curves'!$H$12 + $T$5*'Cancel Curves'!$G$12 + $U$5*'Cancel Curves'!$F$12 + $V$5*'Cancel Curves'!$E$12 + $W$5*'Cancel Curves'!$D$12 + $X$5*'Cancel Curves'!$C$12 + $Y$5*'Cancel Curves'!$B$12)*Assumptions!$B$76 | Z13: =Z6*Z12 + ($O$5*'Cancel Curves'!$M$12 + $P$5*'Cancel Curves'!$L$12 + $Q$5*'Cancel Curves'!$K$12 + $R$5*'Cancel Curves'!$J$12 + $S$5*'Cancel Curves'!$I$12 + $T$5*'Cancel Curves'!$H$12 + $U$5*'Cancel Curves'!$G$12 + $V$5*'Cancel Curves'!$F$12 + $W$5*'Cancel Curves'!$E$12 + $X$5*'Cancel Curves'!$D$12 + $Y$5*'Cancel Curves'!$C$12 + $Z$5*'Cancel Curves'!$B$12)*Assumptions!$B$76 | AA13: =AA6*AA12 + ($P$5*'Cancel Curves'!$M$12 + $Q$5*'Cancel Curves'!$L$12 + $R$5*'Cancel Curves'!$K$12 + $S$5*'Cancel Curves'!$J$12 + $T$5*'Cancel Curves'!$I$12 + $U$5*'Cancel Curves'!$H$12 + $V$5*'Cancel Curves'!$G$12 + $W$5*'Cancel Curves'!$F$12 + $X$5*'Cancel Curves'!$E$12 + $Y$5*'Cancel Curves'!$D$12 + $Z$5*'Cancel Curves'!$C$12 + $AA$5*'Cancel Curves'!$B$12)*Assumptions!$B$76 | AB13: =AB6*AB12 + ($Q$5*'Cancel Curves'!$M$12 + $R$5*'Cancel Curves'!$L$12 + $S$5*'Cancel Curves'!$K$12 + $T$5*'Cancel Curves'!$J$12 + $U$5*'Cancel Curves'!$I$12 + $V$5*'Cancel Curves'!$H$12 + $W$5*'Cancel Curves'!$G$12 + $X$5*'Cancel Curves'!$F$12 + $Y$5*'Cancel Curves'!$E$12 + $Z$5*'Cancel Curves'!$D$12 + $AA$5*'Cancel Curves'!$C$12 + $AB$5*'Cancel Curves'!$B$12)*Assumptions!$B$76 | AC13: =AC6*AC12 + ($R$5*'Cancel Curves'!$M$12 + $S$5*'Cancel Curves'!$L$12 + $T$5*'Cancel Curves'!$K$12 + $U$5*'Cancel Curves'!$J$12 + $V$5*'Cancel Curves'!$I$12 + $W$5*'Cancel Curves'!$H$12 + $X$5*'Cancel Curves'!$G$12 + $Y$5*'Cancel Curves'!$F$12 + $Z$5*'Cancel Curves'!$E$12 + $AA$5*'Cancel Curves'!$D$12 + $AB$5*'Cancel Curves'!$C$12 + $AC$5*'Cancel Curves'!$B$12)*Assumptions!$B$76 | AD13: =AD6*AD12 + ($S$5*'Cancel Curves'!$M$12 + $T$5*'Cancel Curves'!$L$12 + $U$5*'Cancel Curves'!$K$12 + $V$5*'Cancel Curves'!$J$12 + $W$5*'Cancel Curves'!$I$12 + $X$5*'Cancel Curves'!$H$12 + $Y$5*'Cancel Curves'!$G$12 + $Z$5*'Cancel Curves'!$F$12 + $AA$5*'Cancel Curves'!$E$12 + $AB$5*'Cancel Curves'!$D$12 + $AC$5*'Cancel Curves'!$C$12 + $AD$5*'Cancel Curves'!$B$12)*Assumptions!$B$76 | AE13: =AE6*AE12 + ($T$5*'Cancel Curves'!$M$12 + $U$5*'Cancel Curves'!$L$12 + $V$5*'Cancel Curves'!$K$12 + $W$5*'Cancel Curves'!$J$12 + $X$5*'Cancel Curves'!$I$12 + $Y$5*'Cancel Curves'!$H$12 + $Z$5*'Cancel Curves'!$G$12 + $AA$5*'Cancel Curves'!$F$12 + $AB$5*'Cancel Curves'!$E$12 + $AC$5*'Cancel Curves'!$D$12 + $AD$5*'Cancel Curves'!$C$12 + $AE$5*'Cancel Curves'!$B$12)*Assumptions!$B$76 | AF13: =AF6*AF12 + ($U$5*'Cancel Curves'!$M$12 + $V$5*'Cancel Curves'!$L$12 + $W$5*'Cancel Curves'!$K$12 + $X$5*'Cancel Curves'!$J$12 + $Y$5*'Cancel Curves'!$I$12 + $Z$5*'Cancel Curves'!$H$12 + $AA$5*'Cancel Curves'!$G$12 + $AB$5*'Cancel Curves'!$F$12 + $AC$5*'Cancel Curves'!$E$12 + $AD$5*'Cancel Curves'!$D$12 + $AE$5*'Cancel Curves'!$C$12 + $AF$5*'Cancel Curves'!$B$12)*Assumptions!$B$76 | AG13: =AG6*AG12 + ($V$5*'Cancel Curves'!$M$12 + $W$5*'Cancel Curves'!$L$12 + $X$5*'Cancel Curves'!$K$12 + $Y$5*'Cancel Curves'!$J$12 + $Z$5*'Cancel Curves'!$I$12 + $AA$5*'Cancel Curves'!$H$12 + $AB$5*'Cancel Curves'!$G$12 + $AC$5*'Cancel Curves'!$F$12 + $AD$5*'Cancel Curves'!$E$12 + $AE$5*'Cancel Curves'!$D$12 + $AF$5*'Cancel Curves'!$C$12 + $AG$5*'Cancel Curves'!$B$12)*Assumptions!$B$76 | AH13: =AH6*AH12 + ($W$5*'Cancel Curves'!$M$12 + $X$5*'Cancel Curves'!$L$12 + $Y$5*'Cancel Curves'!$K$12 + $Z$5*'Cancel Curves'!$J$12 + $AA$5*'Cancel Curves'!$I$12 + $AB$5*'Cancel Curves'!$H$12 + $AC$5*'Cancel Curves'!$G$12 + $AD$5*'Cancel Curves'!$F$12 + $AE$5*'Cancel Curves'!$E$12 + $AF$5*'Cancel Curves'!$D$12 + $AG$5*'Cancel Curves'!$C$12 + $AH$5*'Cancel Curves'!$B$12)*Assumptions!$B$76 | AI13: =AI6*AI12 + ($X$5*'Cancel Curves'!$M$12 + $Y$5*'Cancel Curves'!$L$12 + $Z$5*'Cancel Curves'!$K$12 + $AA$5*'Cancel Curves'!$J$12 + $AB$5*'Cancel Curves'!$I$12 + $AC$5*'Cancel Curves'!$H$12 + $AD$5*'Cancel Curves'!$G$12 + $AE$5*'Cancel Curves'!$F$12 + $AF$5*'Cancel Curves'!$E$12 + $AG$5*'Cancel Curves'!$D$12 + $AH$5*'Cancel Curves'!$C$12 + $AI$5*'Cancel Curves'!$B$12)*Assumptions!$B$76 | AJ13: =AJ6*AJ12 + ($Y$5*'Cancel Curves'!$M$12 + $Z$5*'Cancel Curves'!$L$12 + $AA$5*'Cancel Curves'!$K$12 + $AB$5*'Cancel Curves'!$J$12 + $AC$5*'Cancel Curves'!$I$12 + $AD$5*'Cancel Curves'!$H$12 + $AE$5*'Cancel Curves'!$G$12 + $AF$5*'Cancel Curves'!$F$12 + $AG$5*'Cancel Curves'!$E$12 + $AH$5*'Cancel Curves'!$D$12 + $AI$5*'Cancel Curves'!$C$12 + $AJ$5*'Cancel Curves'!$B$12)*Assumptions!$B$76 | AK13: =AK6*AK12 + ($Z$5*'Cancel Curves'!$M$12 + $AA$5*'Cancel Curves'!$L$12 + $AB$5*'Cancel Curves'!$K$12 + $AC$5*'Cancel Curves'!$J$12 + $AD$5*'Cancel Curves'!$I$12 + $AE$5*'Cancel Curves'!$H$12 + $AF$5*'Cancel Curves'!$G$12 + $AG$5*'Cancel Curves'!$F$12 + $AH$5*'Cancel Curves'!$E$12 + $AI$5*'Cancel Curves'!$D$12 + $AJ$5*'Cancel Curves'!$C$12 + $AK$5*'Cancel Curves'!$B$12)*Assumptions!$B$76 | AL13: =AL6*AL12 + ($AA$5*'Cancel Curves'!$M$12 + $AB$5*'Cancel Curves'!$L$12 + $AC$5*'Cancel Curves'!$K$12 + $AD$5*'Cancel Curves'!$J$12 + $AE$5*'Cancel Curves'!$I$12 + $AF$5*'Cancel Curves'!$H$12 + $AG$5*'Cancel Curves'!$G$12 + $AH$5*'Cancel Curves'!$F$12 + $AI$5*'Cancel Curves'!$E$12 + $AJ$5*'Cancel Curves'!$D$12 + $AK$5*'Cancel Curves'!$C$12 + $AL$5*'Cancel Curves'!$B$12)*Assumptions!$B$76 | AM13: =AM6*AM12 + ($AB$5*'Cancel Curves'!$M$12 + $AC$5*'Cancel Curves'!$L$12 + $AD$5*'Cancel Curves'!$K$12 + $AE$5*'Cancel Curves'!$J$12 + $AF$5*'Cancel Curves'!$I$12 + $AG$5*'Cancel Curves'!$H$12 + $AH$5*'Cancel Curves'!$G$12 + $AI$5*'Cancel Curves'!$F$12 + $AJ$5*'Cancel Curves'!$E$12 + $AK$5*'Cancel Curves'!$D$12 + $AL$5*'Cancel Curves'!$C$12 + $AM$5*'Cancel Curves'!$B$12)*Assumptions!$B$76 | AN13: =AN6*AN12 + ($AC$5*'Cancel Curves'!$M$12 + $AD$5*'Cancel Curves'!$L$12 + $AE$5*'Cancel Curves'!$K$12 + $AF$5*'Cancel Curves'!$J$12 + $AG$5*'Cancel Curves'!$I$12 + $AH$5*'Cancel Curves'!$H$12 + $AI$5*'Cancel Curves'!$G$12 + $AJ$5*'Cancel Curves'!$F$12 + $AK$5*'Cancel Curves'!$E$12 + $AL$5*'Cancel Curves'!$D$12 + $AM$5*'Cancel Curves'!$C$12 + $AN$5*'Cancel Curves'!$B$12)*Assumptions!$B$76 | AO13: =AO6*AO12 + ($AD$5*'Cancel Curves'!$M$12 + $AE$5*'Cancel Curves'!$L$12 + $AF$5*'Cancel Curves'!$K$12 + $AG$5*'Cancel Curves'!$J$12 + $AH$5*'Cancel Curves'!$I$12 + $AI$5*'Cancel Curves'!$H$12 + $AJ$5*'Cancel Curves'!$G$12 + $AK$5*'Cancel Curves'!$F$12 + $AL$5*'Cancel Curves'!$E$12 + $AM$5*'Cancel Curves'!$D$12 + $AN$5*'Cancel Curves'!$C$12 + $AO$5*'Cancel Curves'!$B$12)*Assumptions!$B$76 | AP13: =AP6*AP12 + ($AE$5*'Cancel Curves'!$M$12 + $AF$5*'Cancel Curves'!$L$12 + $AG$5*'Cancel Curves'!$K$12 + $AH$5*'Cancel Curves'!$J$12 + $AI$5*'Cancel Curves'!$I$12 + $AJ$5*'Cancel Curves'!$H$12 + $AK$5*'Cancel Curves'!$G$12 + $AL$5*'Cancel Curves'!$F$12 + $AM$5*'Cancel Curves'!$E$12 + $AN$5*'Cancel Curves'!$D$12 + $AO$5*'Cancel Curves'!$C$12 + $AP$5*'Cancel Curves'!$B$12)*Assumptions!$B$76 | AQ13: =AQ6*AQ12 + ($AF$5*'Cancel Curves'!$M$12 + $AG$5*'Cancel Curves'!$L$12 + $AH$5*'Cancel Curves'!$K$12 + $AI$5*'Cancel Curves'!$J$12 + $AJ$5*'Cancel Curves'!$I$12 + $AK$5*'Cancel Curves'!$H$12 + $AL$5*'Cancel Curves'!$G$12 + $AM$5*'Cancel Curves'!$F$12 + $AN$5*'Cancel Curves'!$E$12 + $AO$5*'Cancel Curves'!$D$12 + $AP$5*'Cancel Curves'!$C$12 + $AQ$5*'Cancel Curves'!$B$12)*Assumptions!$B$76 | AR13: =AR6*AR12 + ($AG$5*'Cancel Curves'!$M$12 + $AH$5*'Cancel Curves'!$L$12 + $AI$5*'Cancel Curves'!$K$12 + $AJ$5*'Cancel Curves'!$J$12 + $AK$5*'Cancel Curves'!$I$12 + $AL$5*'Cancel Curves'!$H$12 + $AM$5*'Cancel Curves'!$G$12 + $AN$5*'Cancel Curves'!$F$12 + $AO$5*'Cancel Curves'!$E$12 + $AP$5*'Cancel Curves'!$D$12 + $AQ$5*'Cancel Curves'!$C$12 + $AR$5*'Cancel Curves'!$B$12)*Assumptions!$B$76 | AS13: =AS6*AS12 + ($AH$5*'Cancel Curves'!$M$12 + $AI$5*'Cancel Curves'!$L$12 + $AJ$5*'Cancel Curves'!$K$12 + $AK$5*'Cancel Curves'!$J$12 + $AL$5*'Cancel Curves'!$I$12 + $AM$5*'Cancel Curves'!$H$12 + $AN$5*'Cancel Curves'!$G$12 + $AO$5*'Cancel Curves'!$F$12 + $AP$5*'Cancel Curves'!$E$12 + $AQ$5*'Cancel Curves'!$D$12 + $AR$5*'Cancel Curves'!$C$12 + $AS$5*'Cancel Curves'!$B$12)*Assumptions!$B$76 | AT13: =AT6*AT12 + ($AI$5*'Cancel Curves'!$M$12 + $AJ$5*'Cancel Curves'!$L$12 + $AK$5*'Cancel Curves'!$K$12 + $AL$5*'Cancel Curves'!$J$12 + $AM$5*'Cancel Curves'!$I$12 + $AN$5*'Cancel Curves'!$H$12 + $AO$5*'Cancel Curves'!$G$12 + $AP$5*'Cancel Curves'!$F$12 + $AQ$5*'Cancel Curves'!$E$12 + $AR$5*'Cancel Curves'!$D$12 + $AS$5*'Cancel Curves'!$C$12 + $AT$5*'Cancel Curves'!$B$12)*Assumptions!$B$76 | AU13: =AU6*AU12 + ($AJ$5*'Cancel Curves'!$M$12 + $AK$5*'Cancel Curves'!$L$12 + $AL$5*'Cancel Curves'!$K$12 + $AM$5*'Cancel Curves'!$J$12 + $AN$5*'Cancel Curves'!$I$12 + $AO$5*'Cancel Curves'!$H$12 + $AP$5*'Cancel Curves'!$G$12 + $AQ$5*'Cancel Curves'!$F$12 + $AR$5*'Cancel Curves'!$E$12 + $AS$5*'Cancel Curves'!$D$12 + $AT$5*'Cancel Curves'!$C$12 + $AU$5*'Cancel Curves'!$B$12)*Assumptions!$B$76 | AV13: =AV6*AV12 + ($AK$5*'Cancel Curves'!$M$12 + $AL$5*'Cancel Curves'!$L$12 + $AM$5*'Cancel Curves'!$K$12 + $AN$5*'Cancel Curves'!$J$12 + $AO$5*'Cancel Curves'!$I$12 + $AP$5*'Cancel Curves'!$H$12 + $AQ$5*'Cancel Curves'!$G$12 + $AR$5*'Cancel Curves'!$F$12 + $AS$5*'Cancel Curves'!$E$12 + $AT$5*'Cancel Curves'!$D$12 + $AU$5*'Cancel Curves'!$C$12 + $AV$5*'Cancel Curves'!$B$12)*Assumptions!$B$76 | AW13: =AW6*AW12 + ($AL$5*'Cancel Curves'!$M$12 + $AM$5*'Cancel Curves'!$L$12 + $AN$5*'Cancel Curves'!$K$12 + $AO$5*'Cancel Curves'!$J$12 + $AP$5*'Cancel Curves'!$I$12 + $AQ$5*'Cancel Curves'!$H$12 + $AR$5*'Cancel Curves'!$G$12 + $AS$5*'Cancel Curves'!$F$12 + $AT$5*'Cancel Curves'!$E$12 + $AU$5*'Cancel Curves'!$D$12 + $AV$5*'Cancel Curves'!$C$12 + $AW$5*'Cancel Curves'!$B$12)*Assumptions!$B$76 | AX13: =AX6*AX12 + ($AM$5*'Cancel Curves'!$M$12 + $AN$5*'Cancel Curves'!$L$12 + $AO$5*'Cancel Curves'!$K$12 + $AP$5*'Cancel Curves'!$J$12 + $AQ$5*'Cancel Curves'!$I$12 + $AR$5*'Cancel Curves'!$H$12 + $AS$5*'Cancel Curves'!$G$12 + $AT$5*'Cancel Curves'!$F$12 + $AU$5*'Cancel Curves'!$E$12 + $AV$5*'Cancel Curves'!$D$12 + $AW$5*'Cancel Curves'!$C$12 + $AX$5*'Cancel Curves'!$B$12)*Assumptions!$B$76 | AY13: =AY6*AY12 + ($AN$5*'Cancel Curves'!$M$12 + $AO$5*'Cancel Curves'!$L$12 + $AP$5*'Cancel Curves'!$K$12 + $AQ$5*'Cancel Curves'!$J$12 + $AR$5*'Cancel Curves'!$I$12 + $AS$5*'Cancel Curves'!$H$12 + $AT$5*'Cancel Curves'!$G$12 + $AU$5*'Cancel Curves'!$F$12 + $AV$5*'Cancel Curves'!$E$12 + $AW$5*'Cancel Curves'!$D$12 + $AX$5*'Cancel Curves'!$C$12 + $AY$5*'Cancel Curves'!$B$12)*Assumptions!$B$76 | AZ13: =AZ6*AZ12 + ($AO$5*'Cancel Curves'!$M$12 + $AP$5*'Cancel Curves'!$L$12 + $AQ$5*'Cancel Curves'!$K$12 + $AR$5*'Cancel Curves'!$J$12 + $AS$5*'Cancel Curves'!$I$12 + $AT$5*'Cancel Curves'!$H$12 + $AU$5*'Cancel Curves'!$G$12 + $AV$5*'Cancel Curves'!$F$12 + $AW$5*'Cancel Curves'!$E$12 + $AX$5*'Cancel Curves'!$D$12 + $AY$5*'Cancel Curves'!$C$12 + $AZ$5*'Cancel Curves'!$B$12)*Assumptions!$B$76 | BA13: =BA6*BA12 + ($AP$5*'Cancel Curves'!$M$12 + $AQ$5*'Cancel Curves'!$L$12 + $AR$5*'Cancel Curves'!$K$12 + $AS$5*'Cancel Curves'!$J$12 + $AT$5*'Cancel Curves'!$I$12 + $AU$5*'Cancel Curves'!$H$12 + $AV$5*'Cancel Curves'!$G$12 + $AW$5*'Cancel Curves'!$F$12 + $AX$5*'Cancel Curves'!$E$12 + $AY$5*'Cancel Curves'!$D$12 + $AZ$5*'Cancel Curves'!$C$12 + $BA$5*'Cancel Curves'!$B$12)*Assumptions!$B$76 | BB13: =BB6*BB12 + ($AQ$5*'Cancel Curves'!$M$12 + $AR$5*'Cancel Curves'!$L$12 + $AS$5*'Cancel Curves'!$K$12 + $AT$5*'Cancel Curves'!$J$12 + $AU$5*'Cancel Curves'!$I$12 + $AV$5*'Cancel Curves'!$H$12 + $AW$5*'Cancel Curves'!$G$12 + $AX$5*'Cancel Curves'!$F$12 + $AY$5*'Cancel Curves'!$E$12 + $AZ$5*'Cancel Curves'!$D$12 + $BA$5*'Cancel Curves'!$C$12 + $BB$5*'Cancel Curves'!$B$12)*Assumptions!$B$76 | BC13: =BC6*BC12 + ($AR$5*'Cancel Curves'!$M$12 + $AS$5*'Cancel Curves'!$L$12 + $AT$5*'Cancel Curves'!$K$12 + $AU$5*'Cancel Curves'!$J$12 + $AV$5*'Cancel Curves'!$I$12 + $AW$5*'Cancel Curves'!$H$12 + $AX$5*'Cancel Curves'!$G$12 + $AY$5*'Cancel Curves'!$F$12 + $AZ$5*'Cancel Curves'!$E$12 + $BA$5*'Cancel Curves'!$D$12 + $BB$5*'Cancel Curves'!$C$12 + $BC$5*'Cancel Curves'!$B$12)*Assumptions!$B$76 | BD13: =BD6*BD12 + ($AS$5*'Cancel Curves'!$M$12 + $AT$5*'Cancel Curves'!$L$12 + $AU$5*'Cancel Curves'!$K$12 + $AV$5*'Cancel Curves'!$J$12 + $AW$5*'Cancel Curves'!$I$12 + $AX$5*'Cancel Curves'!$H$12 + $AY$5*'Cancel Curves'!$G$12 + $AZ$5*'Cancel Curves'!$F$12 + $BA$5*'Cancel Curves'!$E$12 + $BB$5*'Cancel Curves'!$D$12 + $BC$5*'Cancel Curves'!$C$12 + $BD$5*'Cancel Curves'!$B$12)*Assumptions!$B$76 | BE13: =BE6*BE12 + ($AT$5*'Cancel Curves'!$M$12 + $AU$5*'Cancel Curves'!$L$12 + $AV$5*'Cancel Curves'!$K$12 + $AW$5*'Cancel Curves'!$J$12 + $AX$5*'Cancel Curves'!$I$12 + $AY$5*'Cancel Curves'!$H$12 + $AZ$5*'Cancel Curves'!$G$12 + $BA$5*'Cancel Curves'!$F$12 + $BB$5*'Cancel Curves'!$E$12 + $BC$5*'Cancel Curves'!$D$12 + $BD$5*'Cancel Curves'!$C$12 + $BE$5*'Cancel Curves'!$B$12)*Assumptions!$B$76 | BF13: =BF6*BF12 + ($AU$5*'Cancel Curves'!$M$12 + $AV$5*'Cancel Curves'!$L$12 + $AW$5*'Cancel Curves'!$K$12 + $AX$5*'Cancel Curves'!$J$12 + $AY$5*'Cancel Curves'!$I$12 + $AZ$5*'Cancel Curves'!$H$12 + $BA$5*'Cancel Curves'!$G$12 + $BB$5*'Cancel Curves'!$F$12 + $BC$5*'Cancel Curves'!$E$12 + $BD$5*'Cancel Curves'!$D$12 + $BE$5*'Cancel Curves'!$C$12 + $BF$5*'Cancel Curves'!$B$12)*Assumptions!$B$76 | BG13: =BG6*BG12 + ($AV$5*'Cancel Curves'!$M$12 + $AW$5*'Cancel Curves'!$L$12 + $AX$5*'Cancel Curves'!$K$12 + $AY$5*'Cancel Curves'!$J$12 + $AZ$5*'Cancel Curves'!$I$12 + $BA$5*'Cancel Curves'!$H$12 + $BB$5*'Cancel Curves'!$G$12 + $BC$5*'Cancel Curves'!$F$12 + $BD$5*'Cancel Curves'!$E$12 + $BE$5*'Cancel Curves'!$D$12 + $BF$5*'Cancel Curves'!$C$12 + $BG$5*'Cancel Curves'!$B$12)*Assumptions!$B$76 | BH13: =BH6*BH12 + ($AW$5*'Cancel Curves'!$M$12 + $AX$5*'Cancel Curves'!$L$12 + $AY$5*'Cancel Curves'!$K$12 + $AZ$5*'Cancel Curves'!$J$12 + $BA$5*'Cancel Curves'!$I$12 + $BB$5*'Cancel Curves'!$H$12 + $BC$5*'Cancel Curves'!$G$12 + $BD$5*'Cancel Curves'!$F$12 + $BE$5*'Cancel Curves'!$E$12 + $BF$5*'Cancel Curves'!$D$12 + $BG$5*'Cancel Curves'!$C$12 + $BH$5*'Cancel Curves'!$B$12)*Assumptions!$B$76 | BI13: =BI6*BI12 + ($AX$5*'Cancel Curves'!$M$12 + $AY$5*'Cancel Curves'!$L$12 + $AZ$5*'Cancel Curves'!$K$12 + $BA$5*'Cancel Curves'!$J$12 + $BB$5*'Cancel Curves'!$I$12 + $BC$5*'Cancel Curves'!$H$12 + $BD$5*'Cancel Curves'!$G$12 + $BE$5*'Cancel Curves'!$F$12 + $BF$5*'Cancel Curves'!$E$12 + $BG$5*'Cancel Curves'!$D$12 + $BH$5*'Cancel Curves'!$C$12 + $BI$5*'Cancel Curves'!$B$12)*Assumptions!$B$76 | BJ13: =BJ6*BJ12 + ($AY$5*'Cancel Curves'!$M$12 + $AZ$5*'Cancel Curves'!$L$12 + $BA$5*'Cancel Curves'!$K$12 + $BB$5*'Cancel Curves'!$J$12 + $BC$5*'Cancel Curves'!$I$12 + $BD$5*'Cancel Curves'!$H$12 + $BE$5*'Cancel Curves'!$G$12 + $BF$5*'Cancel Curves'!$F$12 + $BG$5*'Cancel Curves'!$E$12 + $BH$5*'Cancel Curves'!$D$12 + $BI$5*'Cancel Curves'!$C$12 + $BJ$5*'Cancel Curves'!$B$12)*Assumptions!$B$76 | BK13: =BK6*BK12 + ($AZ$5*'Cancel Curves'!$M$12 + $BA$5*'Cancel Curves'!$L$12 + $BB$5*'Cancel Curves'!$K$12 + $BC$5*'Cancel Curves'!$J$12 + $BD$5*'Cancel Curves'!$I$12 + $BE$5*'Cancel Curves'!$H$12 + $BF$5*'Cancel Curves'!$G$12 + $BG$5*'Cancel Curves'!$F$12 + $BH$5*'Cancel Curves'!$E$12 + $BI$5*'Cancel Curves'!$D$12 + $BJ$5*'Cancel Curves'!$C$12 + $BK$5*'Cancel Curves'!$B$12)*Assumptions!$B$76 | BL13: =BL6*BL12 + ($BA$5*'Cancel Curves'!$M$12 + $BB$5*'Cancel Curves'!$L$12 + $BC$5*'Cancel Curves'!$K$12 + $BD$5*'Cancel Curves'!$J$12 + $BE$5*'Cancel Curves'!$I$12 + $BF$5*'Cancel Curves'!$H$12 + $BG$5*'Cancel Curves'!$G$12 + $BH$5*'Cancel Curves'!$F$12 + $BI$5*'Cancel Curves'!$E$12 + $BJ$5*'Cancel Curves'!$D$12 + $BK$5*'Cancel Curves'!$C$12 + $BL$5*'Cancel Curves'!$B$12)*Assumptions!$B$76 | BM13: =BM6*BM12 + ($BB$5*'Cancel Curves'!$M$12 + $BC$5*'Cancel Curves'!$L$12 + $BD$5*'Cancel Curves'!$K$12 + $BE$5*'Cancel Curves'!$J$12 + $BF$5*'Cancel Curves'!$I$12 + $BG$5*'Cancel Curves'!$H$12 + $BH$5*'Cancel Curves'!$G$12 + $BI$5*'Cancel Curves'!$F$12 + $BJ$5*'Cancel Curves'!$E$12 + $BK$5*'Cancel Curves'!$D$12 + $BL$5*'Cancel Curves'!$C$12 + $BM$5*'Cancel Curves'!$B$12)*Assumptions!$B$76 | BN13: =BN6*BN12 + ($BC$5*'Cancel Curves'!$M$12 + $BD$5*'Cancel Curves'!$L$12 + $BE$5*'Cancel Curves'!$K$12 + $BF$5*'Cancel Curves'!$J$12 + $BG$5*'Cancel Curves'!$I$12 + $BH$5*'Cancel Curves'!$H$12 + $BI$5*'Cancel Curves'!$G$12 + $BJ$5*'Cancel Curves'!$F$12 + $BK$5*'Cancel Curves'!$E$12 + $BL$5*'Cancel Curves'!$D$12 + $BM$5*'Cancel Curves'!$C$12 + $BN$5*'Cancel Curves'!$B$12)*Assumptions!$B$76 | BO13: =BO6*BO12 + ($BD$5*'Cancel Curves'!$M$12 + $BE$5*'Cancel Curves'!$L$12 + $BF$5*'Cancel Curves'!$K$12 + $BG$5*'Cancel Curves'!$J$12 + $BH$5*'Cancel Curves'!$I$12 + $BI$5*'Cancel Curves'!$H$12 + $BJ$5*'Cancel Curves'!$G$12 + $BK$5*'Cancel Curves'!$F$12 + $BL$5*'Cancel Curves'!$E$12 + $BM$5*'Cancel Curves'!$D$12 + $BN$5*'Cancel Curves'!$C$12 + $BO$5*'Cancel Curves'!$B$12)*Assumptions!$B$76 | BP13: =BP6*BP12 + ($BE$5*'Cancel Curves'!$M$12 + $BF$5*'Cancel Curves'!$L$12 + $BG$5*'Cancel Curves'!$K$12 + $BH$5*'Cancel Curves'!$J$12 + $BI$5*'Cancel Curves'!$I$12 + $BJ$5*'Cancel Curves'!$H$12 + $BK$5*'Cancel Curves'!$G$12 + $BL$5*'Cancel Curves'!$F$12 + $BM$5*'Cancel Curves'!$E$12 + $BN$5*'Cancel Curves'!$D$12 + $BO$5*'Cancel Curves'!$C$12 + $BP$5*'Cancel Curves'!$B$12)*Assumptions!$B$76 | BQ13: =BQ6*BQ12 + ($BF$5*'Cancel Curves'!$M$12 + $BG$5*'Cancel Curves'!$L$12 + $BH$5*'Cancel Curves'!$K$12 + $BI$5*'Cancel Curves'!$J$12 + $BJ$5*'Cancel Curves'!$I$12 + $BK$5*'Cancel Curves'!$H$12 + $BL$5*'Cancel Curves'!$G$12 + $BM$5*'Cancel Curves'!$F$12 + $BN$5*'Cancel Curves'!$E$12 + $BO$5*'Cancel Curves'!$D$12 + $BP$5*'Cancel Curves'!$C$12 + $BQ$5*'Cancel Curves'!$B$12)*Assumptions!$B$76 | BR13: =BR6*BR12 + ($BG$5*'Cancel Curves'!$M$12 + $BH$5*'Cancel Curves'!$L$12 + $BI$5*'Cancel Curves'!$K$12 + $BJ$5*'Cancel Curves'!$J$12 + $BK$5*'Cancel Curves'!$I$12 + $BL$5*'Cancel Curves'!$H$12 + $BM$5*'Cancel Curves'!$G$12 + $BN$5*'Cancel Curves'!$F$12 + $BO$5*'Cancel Curves'!$E$12 + $BP$5*'Cancel Curves'!$D$12 + $BQ$5*'Cancel Curves'!$C$12 + $BR$5*'Cancel Curves'!$B$12)*Assumptions!$B$76 | BS13: =BS6*BS12 + ($BH$5*'Cancel Curves'!$M$12 + $BI$5*'Cancel Curves'!$L$12 + $BJ$5*'Cancel Curves'!$K$12 + $BK$5*'Cancel Curves'!$J$12 + $BL$5*'Cancel Curves'!$I$12 + $BM$5*'Cancel Curves'!$H$12 + $BN$5*'Cancel Curves'!$G$12 + $BO$5*'Cancel Curves'!$F$12 + $BP$5*'Cancel Curves'!$E$12 + $BQ$5*'Cancel Curves'!$D$12 + $BR$5*'Cancel Curves'!$C$12 + $BS$5*'Cancel Curves'!$B$12)*Assumptions!$B$76 | BT13: =BT6*BT12 + ($BI$5*'Cancel Curves'!$M$12 + $BJ$5*'Cancel Curves'!$L$12 + $BK$5*'Cancel Curves'!$K$12 + $BL$5*'Cancel Curves'!$J$12 + $BM$5*'Cancel Curves'!$I$12 + $BN$5*'Cancel Curves'!$H$12 + $BO$5*'Cancel Curves'!$G$12 + $BP$5*'Cancel Curves'!$F$12 + $BQ$5*'Cancel Curves'!$E$12 + $BR$5*'Cancel Curves'!$D$12 + $BS$5*'Cancel Curves'!$C$12 + $BT$5*'Cancel Curves'!$B$12)*Assumptions!$B$76 | BU13: =BU6*BU12 + ($BJ$5*'Cancel Curves'!$M$12 + $BK$5*'Cancel Curves'!$L$12 + $BL$5*'Cancel Curves'!$K$12 + $BM$5*'Cancel Curves'!$J$12 + $BN$5*'Cancel Curves'!$I$12 + $BO$5*'Cancel Curves'!$H$12 + $BP$5*'Cancel Curves'!$G$12 + $BQ$5*'Cancel Curves'!$F$12 + $BR$5*'Cancel Curves'!$E$12 + $BS$5*'Cancel Curves'!$D$12 + $BT$5*'Cancel Curves'!$C$12 + $BU$5*'Cancel Curves'!$B$12)*Assumptions!$B$76 | BV13: =BV6*BV12 + ($BK$5*'Cancel Curves'!$M$12 + $BL$5*'Cancel Curves'!$L$12 + $BM$5*'Cancel Curves'!$K$12 + $BN$5*'Cancel Curves'!$J$12 + $BO$5*'Cancel Curves'!$I$12 + $BP$5*'Cancel Curves'!$H$12 + $BQ$5*'Cancel Curves'!$G$12 + $BR$5*'Cancel Curves'!$F$12 + $BS$5*'Cancel Curves'!$E$12 + $BT$5*'Cancel Curves'!$D$12 + $BU$5*'Cancel Curves'!$C$12 + $BV$5*'Cancel Curves'!$B$12)*Assumptions!$B$76 | BW13: =BW6*BW12 + ($BL$5*'Cancel Curves'!$M$12 + $BM$5*'Cancel Curves'!$L$12 + $BN$5*'Cancel Curves'!$K$12 + $BO$5*'Cancel Curves'!$J$12 + $BP$5*'Cancel Curves'!$I$12 + $BQ$5*'Cancel Curves'!$H$12 + $BR$5*'Cancel Curves'!$G$12 + $BS$5*'Cancel Curves'!$F$12 + $BT$5*'Cancel Curves'!$E$12 + $BU$5*'Cancel Curves'!$D$12 + $BV$5*'Cancel Curves'!$C$12 + $BW$5*'Cancel Curves'!$B$12)*Assumptions!$B$76
A14: Initiation fee (new contracts × IAA) | D14: =D5*Assumptions!$B$32 | E14: =E5*Assumptions!$B$32 | F14: =F5*Assumptions!$B$32 | G14: =G5*Assumptions!$B$32 | H14: =H5*Assumptions!$B$32 | I14: =I5*Assumptions!$B$32 | J14: =J5*Assumptions!$B$32 | K14: =K5*Assumptions!$B$32 | ... BW14: =BW5*Assumptions!$B$32
A15: Total revenue | D15: =D13+D14 | E15: =E13+E14 | F15: =F13+F14 | G15: =G13+G14 | H15: =H13+H14 | I15: =I13+I14 | J15: =J13+J14 | K15: =K13+K14 | ... BW15: =BW13+BW14
A17: COST OF SERVICE
A18: Claims expense (active × claims reserve / 12) | D18: =IF(1<Assumptions!$B$25,0,D6*Assumptions!$B$24/12) | E18: =IF(2<Assumptions!$B$25,0,E6*Assumptions!$B$24/12) | F18: =IF(3<Assumptions!$B$25,0,F6*Assumptions!$B$24/12) | G18: =IF(4<Assumptions!$B$25,0,G6*Assumptions!$B$24/12) | H18: =IF(5<Assumptions!$B$25,0,H6*Assumptions!$B$24/12) | I18: =IF(6<Assumptions!$B$25,0,I6*Assumptions!$B$24/12) | J18: =IF(7<Assumptions!$B$25,0,J6*Assumptions!$B$24/12) | K18: =IF(8<Assumptions!$B$25,0,K6*Assumptions!$B$24/12) | L18: =IF(9<Assumptions!$B$25,0,L6*Assumptions!$B$24/12) | M18: =IF(10<Assumptions!$B$25,0,M6*Assumptions!$B$24/12) | N18: =IF(11<Assumptions!$B$25,0,N6*Assumptions!$B$24/12) | O18: =IF(12<Assumptions!$B$25,0,O6*Assumptions!$B$24/12) | P18: =IF(13<Assumptions!$B$25,0,P6*Assumptions!$B$24/12) | Q18: =IF(14<Assumptions!$B$25,0,Q6*Assumptions!$B$24/12) | R18: =IF(15<Assumptions!$B$25,0,R6*Assumptions!$B$24/12) | S18: =IF(16<Assumptions!$B$25,0,S6*Assumptions!$B$24/12) | T18: =IF(17<Assumptions!$B$25,0,T6*Assumptions!$B$24/12) | U18: =IF(18<Assumptions!$B$25,0,U6*Assumptions!$B$24/12) | V18: =IF(19<Assumptions!$B$25,0,V6*Assumptions!$B$24/12) | W18: =IF(20<Assumptions!$B$25,0,W6*Assumptions!$B$24/12) | X18: =IF(21<Assumptions!$B$25,0,X6*Assumptions!$B$24/12) | Y18: =IF(22<Assumptions!$B$25,0,Y6*Assumptions!$B$24/12) | Z18: =IF(23<Assumptions!$B$25,0,Z6*Assumptions!$B$24/12) | AA18: =IF(24<Assumptions!$B$25,0,AA6*Assumptions!$B$24/12) | AB18: =IF(25<Assumptions!$B$25,0,AB6*Assumptions!$B$24/12) | AC18: =IF(26<Assumptions!$B$25,0,AC6*Assumptions!$B$24/12) | AD18: =IF(27<Assumptions!$B$25,0,AD6*Assumptions!$B$24/12) | AE18: =IF(28<Assumptions!$B$25,0,AE6*Assumptions!$B$24/12) | AF18: =IF(29<Assumptions!$B$25,0,AF6*Assumptions!$B$24/12) | AG18: =IF(30<Assumptions!$B$25,0,AG6*Assumptions!$B$24/12) | AH18: =IF(31<Assumptions!$B$25,0,AH6*Assumptions!$B$24/12) | AI18: =IF(32<Assumptions!$B$25,0,AI6*Assumptions!$B$24/12) | AJ18: =IF(33<Assumptions!$B$25,0,AJ6*Assumptions!$B$24/12) | AK18: =IF(34<Assumptions!$B$25,0,AK6*Assumptions!$B$24/12) | AL18: =IF(35<Assumptions!$B$25,0,AL6*Assumptions!$B$24/12) | AM18: =IF(36<Assumptions!$B$25,0,AM6*Assumptions!$B$24/12) | AN18: =IF(37<Assumptions!$B$25,0,AN6*Assumptions!$B$24/12) | AO18: =IF(38<Assumptions!$B$25,0,AO6*Assumptions!$B$24/12) | AP18: =IF(39<Assumptions!$B$25,0,AP6*Assumptions!$B$24/12) | AQ18: =IF(40<Assumptions!$B$25,0,AQ6*Assumptions!$B$24/12) | AR18: =IF(41<Assumptions!$B$25,0,AR6*Assumptions!$B$24/12) | AS18: =IF(42<Assumptions!$B$25,0,AS6*Assumptions!$B$24/12) | AT18: =IF(43<Assumptions!$B$25,0,AT6*Assumptions!$B$24/12) | AU18: =IF(44<Assumptions!$B$25,0,AU6*Assumptions!$B$24/12) | AV18: =IF(45<Assumptions!$B$25,0,AV6*Assumptions!$B$24/12) | AW18: =IF(46<Assumptions!$B$25,0,AW6*Assumptions!$B$24/12) | AX18: =IF(47<Assumptions!$B$25,0,AX6*Assumptions!$B$24/12) | AY18: =IF(48<Assumptions!$B$25,0,AY6*Assumptions!$B$24/12) | AZ18: =IF(49<Assumptions!$B$25,0,AZ6*Assumptions!$B$24/12) | BA18: =IF(50<Assumptions!$B$25,0,BA6*Assumptions!$B$24/12) | BB18: =IF(51<Assumptions!$B$25,0,BB6*Assumptions!$B$24/12) | BC18: =IF(52<Assumptions!$B$25,0,BC6*Assumptions!$B$24/12) | BD18: =IF(53<Assumptions!$B$25,0,BD6*Assumptions!$B$24/12) | BE18: =IF(54<Assumptions!$B$25,0,BE6*Assumptions!$B$24/12) | BF18: =IF(55<Assumptions!$B$25,0,BF6*Assumptions!$B$24/12) | BG18: =IF(56<Assumptions!$B$25,0,BG6*Assumptions!$B$24/12) | BH18: =IF(57<Assumptions!$B$25,0,BH6*Assumptions!$B$24/12) | BI18: =IF(58<Assumptions!$B$25,0,BI6*Assumptions!$B$24/12) | BJ18: =IF(59<Assumptions!$B$25,0,BJ6*Assumptions!$B$24/12) | BK18: =IF(60<Assumptions!$B$25,0,BK6*Assumptions!$B$24/12) | BL18: =IF(61<Assumptions!$B$25,0,BL6*Assumptions!$B$24/12) | BM18: =IF(62<Assumptions!$B$25,0,BM6*Assumptions!$B$24/12) | BN18: =IF(63<Assumptions!$B$25,0,BN6*Assumptions!$B$24/12) | BO18: =IF(64<Assumptions!$B$25,0,BO6*Assumptions!$B$24/12) | BP18: =IF(65<Assumptions!$B$25,0,BP6*Assumptions!$B$24/12) | BQ18: =IF(66<Assumptions!$B$25,0,BQ6*Assumptions!$B$24/12) | BR18: =IF(67<Assumptions!$B$25,0,BR6*Assumptions!$B$24/12) | BS18: =IF(68<Assumptions!$B$25,0,BS6*Assumptions!$B$24/12) | BT18: =IF(69<Assumptions!$B$25,0,BT6*Assumptions!$B$24/12) | BU18: =IF(70<Assumptions!$B$25,0,BU6*Assumptions!$B$24/12) | BV18: =IF(71<Assumptions!$B$25,0,BV6*Assumptions!$B$24/12) | BW18: =IF(72<Assumptions!$B$25,0,BW6*Assumptions!$B$24/12)
A19: Contract insurance (Lloyd's premium) | D19: =D5*Assumptions!$B$20 | E19: =E5*Assumptions!$B$20 | F19: =F5*Assumptions!$B$20 | G19: =G5*Assumptions!$B$20 | H19: =H5*Assumptions!$B$20 | I19: =I5*Assumptions!$B$20 | J19: =J5*Assumptions!$B$20 | K19: =K5*Assumptions!$B$20 | ... BW19: =BW5*Assumptions!$B$20
A20: Finance fees | D20: =D6*D12*Assumptions!$B$26 | E20: =E6*E12*Assumptions!$B$26 | F20: =F6*F12*Assumptions!$B$26 | G20: =G6*G12*Assumptions!$B$26 | H20: =H6*H12*Assumptions!$B$26 | I20: =I6*I12*Assumptions!$B$26 | J20: =J6*J12*Assumptions!$B$26 | K20: =K6*K12*Assumptions!$B$26 | ... BW20: =BW6*BW12*Assumptions!$B$26
A22: Fulfillment — postage + printing | D22: =D5*(Assumptions!$B$29+Assumptions!$B$30) | E22: =E5*(Assumptions!$B$29+Assumptions!$B$30) | F22: =F5*(Assumptions!$B$29+Assumptions!$B$30) | G22: =G5*(Assumptions!$B$29+Assumptions!$B$30) | H22: =H5*(Assumptions!$B$29+Assumptions!$B$30) | I22: =I5*(Assumptions!$B$29+Assumptions!$B$30) | J22: =J5*(Assumptions!$B$29+Assumptions!$B$30) | K22: =K5*(Assumptions!$B$29+Assumptions!$B$30) | ... BW22: =BW5*(Assumptions!$B$29+Assumptions!$B$30)
A23: Merchant fees + chargebacks | D23: =D13*Assumptions!$B$27 | E23: =E13*Assumptions!$B$27 | F23: =F13*Assumptions!$B$27 | G23: =G13*Assumptions!$B$27 | H23: =H13*Assumptions!$B$27 | I23: =I13*Assumptions!$B$27 | J23: =J13*Assumptions!$B$27 | K23: =K13*Assumptions!$B$27 | ... BW23: =BW13*Assumptions!$B$27
A24: Total COS | D24: =SUM(D18:D23) | E24: =SUM(E18:E23) | F24: =SUM(F18:F23) | G24: =SUM(G18:G23) | H24: =SUM(H18:H23) | I24: =SUM(I18:I23) | J24: =SUM(J18:J23) | K24: =SUM(K18:K23) | ... BW24: =SUM(BW18:BW23)
A26: Gross profit | D26: =D15-D24 | E26: =E15-E24 | F26: =F15-F24 | G26: =G15-G24 | H26: =H15-H24 | I26: =I15-I24 | J26: =J15-J24 | K26: =K15-K24 | ... BW26: =BW15-BW24
A28: ANNUAL ROLL-UP | BY28: 2025A | BZ28: 2026E | CA28: 2027E | CB28: 2028E | CC28: 2029E | CD28: 2030E
A29: New contracts | BY29: =SUM(D5:O5) | BZ29: =SUM(P5:AA5) | CA29: =SUM(AB5:AM5) | CB29: =SUM(AN5:AY5) | CC29: =SUM(AZ5:BK5) | CD29: =SUM(BL5:BW5)
A30: Active contracts (Dec) | BY30: =O6 | BZ30: =AA6 | CA30: =AM6 | CB30: =AY6 | CC30: =BK6 | CD30: =BW6
A31: Total revenue | BY31: =SUM(D15:O15) | BZ31: =SUM(P15:AA15) | CA31: =SUM(AB15:AM15) | CB31: =SUM(AN15:AY15) | CC31: =SUM(AZ15:BK15) | CD31: =SUM(BL15:BW15)
A32: Total COS | BY32: =SUM(D24:O24) | BZ32: =SUM(P24:AA24) | CA32: =SUM(AB24:AM24) | CB32: =SUM(AN24:AY24) | CC32: =SUM(AZ24:BK24) | CD32: =SUM(BL24:BW24)
A33: Gross profit | BY33: =SUM(D26:O26) | BZ33: =SUM(P26:AA26) | CA33: =SUM(AB26:AM26) | CB33: =SUM(AN26:AY26) | CC33: =SUM(AZ26:BK26) | CD33: =SUM(BL26:BW26)

Sheet Home Sales
A1: CX Home / HWS — Engine (Vintage Cohort Survival)
A2: Monthly originations × shared cancel curve. CPS (customer payment per service) = $100.0/mo.
